Workbook

Sheet Offering Speed
A1: Name | B1: Rarity | C1: Type | D1: Base Soul Speed | E1: Awakened Bonus | F1: Source
A2: INDIVIDUAL RELICS
A3: Prometheus Torch | B3: SSS | C3: FAME | D3: 4.8 | E3: 4 | F3: Lottery Machine #1 (0.09%), Wishing (0.09%), Hellas Treasure Map, Grandmaster Scrolls (0.81%), Relic Forge (120 Relic RF)
A4: Houmuwu Ding | B4: SSS | C4: CIV | D4: 4.8 | E4: 4 | F4: Wish Box, Lottery Machine #1 (0.09%), Wishing (0.08%), Cathay Treasure Maps (0.01%), Grandmaster Scrolls (0.81%), Relic Forge (120 Relic RF)
A5: Crystal Skull | B5: AAA | C5: ART | D5: 3.6 | E5: 2.8 | F5: Fragment Crafting (1.6%), Lottery Machine #1 (0.03%), Wishing (0.14%), Time Chest (1.5%), Relic Forge (Relic RF 80)
A6: Buddha Tooth Sarira | B6: Blue | C6: FTH | D6: 2 | E6: 2 | F6: Lottery Machine #1 (0.03%), Wishing (0.85%), Bharata Treasure Maps (%)
A7: Death Hallows VII | B7: Green | C7: FTH | D7: 1.2 | F7: Dumbledore Fight II
A8: Crying Boy | B8: Green | C8: ART | D8: 1.2 | F8: I want your collection! Dragon Wish
A9: MAX INDIVIDUAL RELICS | D9: =SUM(D2:E8) -> 30.4
A11: PARTNERS
A12: Prince | D12: 18 | F12: lv30
A14: INTEL
A15: Koryeo | D15: 5
A17: COLLECTOR's TALENTS
A18: Offering Speed | D18: 10
A20: ROCKET UPGRADES
A21: Oracle Hall | D21: 5
A23: RESONANCE
A24: BLUE | D24: 3.6
A25: Divergene Meter | B25: Blue | C25: TECH | F25: Lottery Machine #1 (0.36%), Wishing (13.2%), Time Chest (2%), Novice Scrolls (5%)
A26: Guanery's Violin | B26: Blue | C26: ART | F26: Lottery Machine #1 (0.03%), Wishing (1.2%), Indigent Nobleman (72K B-tads)
A27: Tudor Rose | B27: Blue | C27: FAME | F27: Lottery Machine #1 (0.03%), Wishing (1.2%)
A28: Holmes' Pipe | B28: Blue | C28: CIV | F28: Lottery Machine #1 (0.36%), Wishing (10.3%), Trainee Scrolls (5%)
A29: Dunhuang Painting | B29: Blue | C29: FTH | F29: Lottery Machine #1 (0.03%), Wishing (0.85%)
A30: Our Lady of Kazan | B30: Blue | C30: FTH | F30: Lottery Machine #1 (0.36%), Wishing (10.6%), Trainee Scrolls (5%)
A31: ORANGE | D31: 4
A32: Pandora's Box | B32: SS | C32: FAME | F32: Lottery Machine #1 (0.12%), Wishing (0.11%), Soul Chest(1%), Grandmaster Scrolls (1%), Relic Forge (100 Relic RF)
A33: True Cross | B33: SSS | C33: FTH | F33: Oracle Hall (Earth's Will Cabin) Reward
A34: Arkanrock | B34: SSS | C34: FAME | F34: Eternal Hall (Demon God Cabin) Reward
A35: Maya Slate | B35: SSS | C35: FTH | F35: Wish Box, Lottery Machine #1 (0.09%), Wishing (0.06%), Dragon Chest (0.1%), Grandmaster Scrolls (0.81%), Relic Forge (120 Relic RF)
A36: Royal Celtic Harp | B36: SSS | C36: FTH | F36: Lottery Machine #1 (0.09%), Wishing (0.06%), Grandmaster Scrolls (0.76%)
A37: MAX RESONANCE | D37: =SUM(D24:E36) -> 7.6
A40: Total Soul Offering Speed | B40: =D9+D12+D37+D21+D15+D18 -> 76
B42: Base | C42: Actual
A43: Speed Example | B43: 8 | C43: =$B43/(1+$B$40/100) -> 4.5454545
A44: One Round Offering | B44: 240 | C44: =$B44/(1+$B$40/100) -> 136.36364
A46: 5 Rounds (hours) | B46: 1200 | C46: =$B46/(1+$B$40/100) -> 681.81818
A47: Precooked Offerings (hours) | B47: =48*4 + 8*4 -> 224
A48: Non-precooked Offerings (hours) | B48: =B46-B47 -> 976 | C48: =$B48/(1+$B$40/100) -> 554.54545
A49: (days) | B49: =B48/24 -> 40.666667 | C49: =C48/24 -> 23.106061

Sheet Travel Speed
A1: Name | B1: Rarity | C1: Type | D1: Base Travel Speed | E1: Awakened Bonus | F1: Stamp Bonus | G1: Source
A2: INDIVIDUAL RELICS
A3: Voyager 1 | B3: SSS | C3: TECH | D3: 2.4 | G3: Wish Box, Lottery Machine #1 (0.09%), Wishing (0.07%), Murikan Treasure Maps (0.01%), Grandmaster Scrolls (0.81%), Relic Forge (120 Relic RF)
A4: Magellan's Telescope | B4: SSS | C4: FAME | D4: 2.4 | F4: 9 | G4: Lottery Machine #1 (0.09%), Wishing (0.09%), Hellas Treasure Map, Grandmaster Scrolls (0.81%), Relic Forge (120 Relic RF)
A5: Somersault Cloud | B5: SSS | C5: FTH | D5: 2.4 | G5: Wish Pack, Lottery Machine #1 (0.09%), Wishing (0.06%), Super Treasure Maps (0.03%), Grandmaster Scrolls (0.81%), Relic Forge (120 Relic RF), "I want your collection!" Dragon Wish
A6: Travels of Marco Polo | B6: SS | C6: FAME | D6: 2.2 | G6: Lottery Machine #1 (0.12%), Wishing (0.11%), Grandmaster Scrolls (1%), Relic Forge (100 Relic RF), Club Value Pack II ($49.99)
A7: Otto Engine | B7: AAA | C7: TECH | D7: 1.8 | E7: 1.4 | G7: Fragment Crafting (1.6%), Lottery Machine #1 (0.03%), Wishing (0.14%), Tool Chest (1.5%), Relic Forge (80 Relic RF)
A8: Bronze Bird | B8: Blue | C8: FAME | D8: 2 | G8: Cathay Treasure Map (20%)
A9: Flying Broom | B9: Green | C9: FAME | D9: 0.6 | G9: Defeat Ratman
A10: MAX INDIVIDUAL RELICS | D10: =SUM(D3:F9) -> 24.2
A12: GEAR
A13: Tremendous Support | D13: 9.6 | G13: Divine Order Chest (0.8%)
A15: ROCKET UPGRADES
A16: Domain Holograph | D16: 5
A18: FORM SPECIFIC
A19: ZOMBIE
A20: Shroud of Turin | B20: S | C20: FTH | D20: 2 | G20: Fragment Crafting (15.1%), Lottery Machine #1 (0.81%), Wishing (0.53%), Relic Forge (90 Relic RF)
A21: Ludovisi Gaul | B21: Blue | C21: ART | D21: 1 | E21: 1 | G21: Lottery Machine #1 (0.07%), Wishing (3%), Trainee Scrolls (1%), Indigent Nobleman (72K B-tads)
A22: DEMON
A23: Eye of Akamoddo | B23: SS | C23: FTH | D23: 2.2 | G23: Fragment Crafting (4.4%), Lottery Machine #1 (0.24%), Wishing (0.16%), Time Chest (1%), Master Scrolls (1.9%), Grandmaster Scrolls (2.1%), FTH Master Scrolls (9.2%)
A24: Great Wave | B24: Blue | C24: ART | D24: 1 | E24: 1 | G24: Lottery Machine #1 (0.07%), Wishing (3%), Yamato Treasure Maps (20%)
A25: Annabel | B25: Green | C25: CIV | D25: 0.6 | G25: "I want your collection!" Dragon Wish
A26: ANGEL
A27: Golden Chariot | B27: SS | C27: FTH | D27: 2.2 | G27: Fragment Crafting (3.3%), Lottery Machine #1 (0.18%), Wishing (0.12%), Hellas Treasure Maps (%), Grandmaster Scrolls (1.6%)
A28: Guanery's Violin | B28: Blue | C28: ART | D28: 1 | E28: 1 | G28: Lottery Machine #1 (0.03%), Wishing (1.2%), Indigent Nobleman (72K B-tads)
A29: MUTANT
A30: Element R | B30: S | C30: TECH | D30: 2 | G30: Fragment Crafting (17.8%), Lottery Machine #1 (0.81%), Wishing (0.65%), Relic Forge (90 Relic RF)
A31: Torpedo Swimsuit | B31: Blue | C31: TECH | D31: 1 | E31: 1 | G31: Lottery Machine #1 (0.03%), Wishing (1.1%), Evolution Chest (2%)
A32: MECHA
A33: Skyweb Hub | B33: SS | C33: TECH | D33: 2.2 | G33: Koryeon Domain, Fragment Crafting (5.2%), Lottery Machine #1 (0.24%), Wishing (0.19%), Super Treasure Maps (5%), Master Scrolls (1.9%), Grandmaster Scrolls (2.1%), TECH Master Scrolls (9.2%)
A34: Arirange Satellite | B34: Blue | C34: TECH | D34: 1 | E34: 1 | G34: Lottery Machine #1 (0.03%), Wishing (1.1%), Nebula Chest (2%)
A35: DRAGON
A36: Phoenix Feather | B36: SSS | C36: FTH | D36: 2.4 | G36: Lottery Machine #1 (0.09%), Wishing (0.06%), Evolution Chest (0.01%), Grandmaster Scrolls (0.81%), Relic Forge (120 Relic RF)
A37: Dunhuang Painting | B37: Blue | C37: FTH | D37: 1 | E37: 1 | G37: Lottery Machine #1 (0.03%), Wishing (0.85%)
A38: MAX FORM SPECIFIC | D38: =MAX(SUM(D20:E21), SUM(D23:E25), SUM(D27:E28), SUM(D30:E31), SUM(D33:E34), SUM(D36:E37)) -> 4.8
A40: RESONANCE
A41: BLUE | D41: 1.8
A42: Flyer I | B42: Blue | C42: TECH | G42: Lottery Machine #1 (0.03%), Wishing (1.1%)
A43: Storyteller | B43: Blue | C43: ART | G43: Lottery Machine #1 (0.36%), Wishing (15%), Trainee Scrolls (5%)
A44: Dragon Crystal | B44: Blue | C44: FTH | G44: Dragon Gene Research Tier 2
A45: Gone with the Wind | B45: Blue | C45: CIV | G45: Murikan Treasure Maps (20%)
A46: Bellum Gallicum | B46: Blue | C46: FAME | G46: Lottery Machine #1 (0.03%), Wishing (1.2%)
A47: Atomic Clock | B47: Blue | C47: TECH | G47: Lottery Machine #1 (0.03%), Wishing (1.1%)
A48: PURPLE | D48: 1.8
A49: Leaf Manuscript | B49: AAA | C49: FTH | G49: Fragment Crafting (1.5%), Lottery Machine #1 (0.03%), Wishing (0.14%), Bharata Treasure Maps (%), Relic Forge (80 Relic RF)
A50: Skidbladnir Ship | B50: AAA | C50: FTH | G50: Fragment Crafting (1.5%), Lottery Machine #1 (0.03%), Wishing (0.14%), Relic Forge (80 Relic RF)
A51: Yuan Calendar | B51: AA | C51: TECH | G51: Fragment Crafting (3.9%), Lottery Machine #1 (0.08%), Wishing (0.36%), Koryeon Treasure Maps (10%), Expert Scrolls (0.95%)
A52: Moonlight Sonata | B52: AAA | C52: ART | G52: Fragment Crafting (1.6%), Lottery Machine #1 (0.03%), Wishing (0.14%), Relic Forge (80 Relic RF), Nebula Chest (1.5%)
A53: Treaty of Versailles | B53: AAA | C53: FAME | G53: Fragment Crafting (1.6%), Lottery Machine #1 (0.03%), Wishing (0.14%), Club Chest (1.5%), Relic Forge (80 Relic RF)
A54: ORANGE | D54: 2.4
A55: Noah's Ark | B55: SSS | C55: FTH | G55: Weekly Special Reward Relic #3
A56: Golden Trophy | B56: SS | C56: FAME | G56: Lottery Machine #1 (0.12%), Wishing (0.11%), Grandmaster Scrolls (1%), Relic Forge (100 Relic RF), Avatar Value Pack II ($49.99)
A57: Ape's Footprint Fossil | B57: SS | C57: FAME | G57: Super Species Chest (2.4%)
A58: Trojan Horse | B58: SSS | C58: FAME | G58: Lottery Machine #1 (0.09%), Wishing (0.09%), Grandmaster Scrolls (0.81%), Relic Forge (120 Relic RF)
A59: Einstein's Brain | B59: SSS | C59: FAME | G59: Lottery Machine #1 (0.09%), Wishing (0.08%), Grandmaster Scrolls (0.79%)
A60: Gravitation Scripts | B60: SSS | C60: FAME | G60: Daily Pack Relic #10
A61: MAX RESONANCE | D61: =SUM(D41:F60) -> 6
A64: Total Travel Speed (General) | B64: =D10+D13+D38+D61+D16 -> 49.6
A65: Speed Example (Hrs) | B65: 10
A66: Actual Time (General) | B66: =$B$65/(1+$B$64/100) -> 6.684492
A68: AREA SPECIFIC
A69: KORYEO
A70: INTEL | D70: 15
A71: Aries | B71: SSS | C71: CIV | D71: 9 | G71: Supreme Relic ($1k)
A72: Total Travel Speed (Koryeo) | B72: =$B$64+SUM(D70:D71) -> 73.6
A73: Actual Time (Koryeo) | B73: =$B$65/(1+$B72/100) -> 5.7603687
A75: YAMATO
A76: INTEL | D76: 15
A77: Taurus | B77: SSS | C77: ART | D77: 9 | G77: Supreme Relic ($4k)
A78: Total Travel Speed (Yamato) | B78: =$B$64+SUM(D76:D77) -> 73.6
A79: Actual Time (Yamato) | B79: =$B$65/(1+$B78/100) -> 5.7603687
A81: CATHAY
A82: INTEL | D82: 20
A83: Somersault Cloud | B83: SSS | C83: FTH | D83: 9
A84: Gemini | B84: SSS | C84: FTH | D84: 9 | G84: Supreme Relic ($?k)
A85: Total Travel Speed (Cathay) | B85: =$B$64+SUM(D82:D84) -> 87.6
A86: Actual Time (Cathay) | B86: =$B$65/(1+$B85/100) -> 5.3304904
A88: MURIKA
A89: INTEL | D89: 10
A90: Blink Steward | D90: 3
A91: Cancer | B91: SSS | C91: ART | D91: 9 | G91: Supreme Relic ($12k)
A92: Total Travel Speed (Murika) | B92: =$B$64+SUM(D89:D91) -> 71.6
A93: Actual Time (Murika) | B93: =$B$65/(1+$B92/100) -> 5.8275058
A95: BRITLAND
A96: INTEL | D96: 15
A97: Book of the Dead | B97: SSS | C97: FTH | D97: 9 | G97: Traveler Member Reward ($2.99), Premium Member Reward ($49.99)
A98: Leo | B98: SSS | C98: FAME | D98: 9 | G98: Supreme Relic ($20k)
A99: Total Travel Speed (Britland) | B99: =$B$64+SUM(D96:D98) -> 82.6
A100: Actual Time (Britland) | B100: =$B$65/(1+$B99/100) -> 5.4764513
A102: KEMET
A103: INTEL | D103: 15
A104: Gutenberg's Press | B104: SSS | C104: CIV | D104: 9 | G104: Daily Pack
A105: Virgo | B105: SSS | C105: FTH | D105: 9 | G105: Supreme Relic ($?k)
A106: Total Travel Speed (Kemet) | B106: =$B$64+SUM(D103:D105) -> 82.6
A107: Actual Time (Kemet) | B107: =$B$65/(1+$B106/100) -> 5.4764513

Sheet Gene Research
A1: Name | B1: Rarity | C1: Type | D1: Research Speed | E1: Awakening Research Speed | F1: Cells Cost | G1: Awakening Cells Cost | H1: Btad Cost | I1: Awakening Btad Cost | J1: Free Speedup (min) | K1: Awakening Free Speedup | L1: Source
A2: INDIVIDUAL RELICS
A3: Double Helix DNA | B3: SSS | C3: TECH | D3: 2.4 | E3: 2 | H3: 4.8 | J3: 36 | L3: Lottery Machine #1 (0.09%), Wishing (0.07%), Grandmaster Scrolls (0.81%), Relic Forge (120 Relic RF)
A4: The Analects | B4: SSS | C4: CIV | D4: 2.4 | E4: 2 | H4: 4.8 | J4: 36 | L4: Wish Box, Lottery Machine #1 (0.09%), Wishing (0.08%), Grandmaster Scrolls (0.81%), Relic Forge (120 Relic RF)
A5: Voynich Script | B5: AAA | C5: CIV | H5: 3.6 | I5: 2.8 | L5: Form Evo Pack
A6: MAX INDIVIDUAL RELICS | D6: =sum(D3:E5) -> 8.8 | F6: =sum(F3:G5) -> 0 | H6: =sum(H3:I5) -> 16 | J6: =sum(J3:K5) -> 72
A8: PARTNER
A9: Toraemon | D9: 30 | L9: lv30
A11: ORGANS
A12: Savant Eye | D12: 3 | J12: 15 | L12: Organ Chest (3% chance), 1st Purchase Gift Pack Day 3 Reward($Any)
A13: Brainworm Neuron | J13: 15 | L13: Organ Value Pack I ($14.99)
A14: MAX ORGANS | D14: =sum(D12:E13) -> 3 | F14: =sum(F12:G13) -> 0 | H14: =sum(H12:I13) -> 0 | J14: =sum(J12:K13) -> 30
A16: NEBULA
A17: Microscopium | D17: 1.6 | H17: 3.2 | J17: 48 | L17: Beta Galaxy
A18: Circinus | D18: 6 | L18: Delta Galaxy
A19: MAX NEBULA | D19: =SUM(D17:D18) -> 7.6 | F19: =SUM(F17:F18) -> 0 | H19: =SUM(H17:H18) -> 3.2 | J19: =SUM(J17:J18) -> 48
A21: COLLECTORS TALENTS
A22: Genetic Engineering I | D22: 15 | L22: 15 Purple Talent Points
A23: Genetic Engineering II | D23: 15 | J23: 150 | L23: 15 Orange Talent Points
A24: Gene SPD II (purple) | D24: 20 | L24: 15 Purple Talent Points
A25: Gene SPD II (orange) | D25: 20 | J25: 240 | L25: 15 Orange Talent Points
A26: MAX COLLECTORS TALENTS | D26: =sum(D22:E25) -> 70 | F26: =sum(F22:G25) -> 0 | H26: =sum(H22:I25) -> 0 | J26: =sum(J22:K25) -> 390
A28: FUNGUS
A29: Purple | D29: 3 | L29: 500 Purple Fungus Consumed
A31: ROCKET UPGRADES
A32: Silence Hall | D32: 5 | J32: 120 | L32: lv5
A34: AVATAR BONUS
A35: Event Avatar | D35: 5 | F35: 5 | H35: 5 | J35: 20
A37: RESONANCE
A38: BLUE
A39: Research Speed | D39: 1.8
A40: Chakana | B40: Blue | C40: FTH | L40: Lottery Machine #1 (0.03%), Wishing (0.85%), Soul Chest (2%)
A41: Great Wave | B41: Blue | C41: ART | L41: Lottery Machine #1 (0.07%), Wishing (3%), Yamato Treasure Maps (20%)
A42: Janssen Microscope | B42: Blue | C42: TECH | L42: Lottery Machine #1 (0.07%), Wishing (2.6%), Evolution Chest (2%), Novice Scrolls (1%)
A43: Royal Doll | B43: Blue | C43: CIV | L43: Lottery Machine #1 (0.03%), Wishing (0.82%)
A44: Mask of Zorro | B44: Blue | C44: FAME | L44: Lottery Machine #1 (0.03%), Wish (1.2%), Zorro (B+B Reward)
A45: Moai | B45: Blue | C45: FTH | L45: Lottery Machine #1 (0.36%), Wishing (10.6%), Soul Chest (2%), Novice Scrolls (5%)
A46: PURPLE
A47: Research Speed | D47: 2
A48: Fuchun Mountains | B48: AA | C48: FTH | L48: Fragment Crafting (3.9%), Lottery Machine #1 (0.08%), Wishing (0.36%), Expert Scrolls (0.95%)
A49: Tyr's Arm | B49: AA | C49: FTH | L49: Fragment Crafting (3.8%), Lottery Machine #1 (0.08%), Wishing (0.35%), Expert Scrolls (0.95%)
A50: Platinum Record | B50: AA | C50: FAME | L50: Fragment Crafting (3.9%), Lottery Machine #1 (0.08%), Wishing (0.35%), Expert Scrolls (0.95%)
A51: Schindler's List | B51: AAA | C51: CIV | L51: Fragment Crafting (1.5%), Lottery Machine #1 (0.03%), Wishing (0.14%), Soul Chest (1.5%), Relic Forge (80 Relic RF)
A52: Polonium | B52: AA | C52: TECH | L52: Fragment Crafting (3.9%), Lottery Machine #1 (0.08%), Wishes (0.36%), Time Chests (1.5%), Expert Scrolls (0.95%)
A53: Cavendish's Scales | B53: AAA | C53: TECH | L53: Fragment Crafting (1.6%), Lottery Machine #1 (0.03%), Wishing (0.14%), Relic Forge (80 Relic RF)
A54: MAX RESONANCE | D54: =sum(D39:E53) -> 3.8 | F54: =sum(F39:G53) -> 0 | H54: =sum(H39:I53) -> 0 | J54: =sum(J39:K53) -> 0
A56: General Research Speed | B56: =D6+D9+D14+D19+D35+D54+D29+D32+D26 -> 136.2
A57: General Cells Cost Reduction | B57: =F6+F14+F35+F54+F26 -> 5
A58: General Btad Cost Reduction | B58: =H6+H14+H19+H35+H54+H26 -> 24.2
A59: General Research Speed (min) | B59: =J6+J14+J19+J35+J54+J32+J26 -> 680
A64: ZOMBIE
A65: INDIVIDUAL RELICS
A66: 3-Faced Statue | B66: SS | C66: FTH | D66: 6.6 | J66: 66 | K66: 60 | L66: Fragment Crafting (4.4%), Lottery Machine #1 (0.24%), Wishing (0.16%), Demon God Chest (5%), Master Scrolls (1.9%), Grandmaster Scrolls (2.1%), FTH Master Scrolls (9.2%)
A67: Red Dot Award | B67: AAA | C67: FAME | H67: 5.4 | L67: Decoration Bonus Relic #1
A68: Death of Marat | B68: AA | C68: ART | D68: 4.8 | E68: 4.2 | F68: 4.8 | L68: Fragment Crafting (3.9%), Lottery Machine #1 (0.08%), Wishing (0.36%), Expert Scrolls (0.95%)
A69: Hannibal's Cup | B69: AA | C69: FAME | H69: 4.8 | I69: 4.2 | L69: Fragment Crafting (3.9%), Lottery Machine #1 (0.08%), Wishing (0.35%), Expert Scrolls (0.95%)
A70: Cloisters Cards | B70: Blue | C70: FAME | J70: 30 | K70: 30 | L70: Lottery Machine #2 (0.26%)
A71: Storyteller | B71: Blue | C71: ART | J71: 30 | K71: 30 | L71: Lottery Machine #1 (0.07%), Wishing (2.6%), Novice Scrolls (1%)
A72: Gecko Tail Specimen | B72: Green | C72: CIV | H72: 1.8 | L72: Shop Easter Egg
A73: MAX INDIVIDUAL RELICS | D73: =sum(D65:E72) -> 15.6 | F73: =sum(F65:G72) -> 4.8 | H73: =sum(H65:I72) -> 16.2 | J73: =sum(J65:K72) -> 246
A75: PARTNERS
A76: Zadako | J76: 15
A78: RESONANCE
A79: BLUE
A80: Research Speed | D80: 3
A81: Ranjyatai Incense | B81: Blue | C81: FTH | L81: Lottery Machine #1 (0.07%), Wishing (2.1%), Novice Scrolls (1%)
A82: Ancient Block | B82: Blue | C82: FTH | L82: Lottery Machine #1 (0.07%), Wishing (2.1%), Soul Chest (2%), Novice Scrolls (1%)
A83: Free Speedup | J83: 30
A84: Instant Noodle Recipe | B84: Blue | C84: FAME | L84: Lottery Machine #2 (0.26%)
A85: Appert's Glass Bottle | B85: Blue | C85: FAME | L85: Lottery Machine #2 (0.03%)
A86: PURPLE
A87: Research Speed | D87: 3.6
A88: Jade Burial Suit | B88: AA | C88: FTH | L88: Fragment Crafting (1.5%), Lottery Machine #1 (0.03%), Wishing (0.14%), Cathay Treasure Map (10% chance), Relic Forge (80 Relic RF)
A89: Yamato Mirror | B89: AAA | C89: FTH | L89: Fragment Crafting (1.5%), Lottery Machine #1 (0.03%), Wishing (0.14%), Relic Forge (80 Relic RF)
A90: Cells Consumed | F90: 3.6
A91: Crystal Skull | B91: AAA | C91: ART | L91: Fragment Crafting (1.6%), Lottery Machine #1 (0.03%), Wishing (0.14%), Time Chest (1.5%), Relic Forge (Relic RF 80)
A92: Truth Crystal | B92: AAA | C92: FTH | L92: Fragment Crating (1.5%), Lottery Machine #1 (0.03%), Wishing (0.14%), Relic Forge (80 Relic RF), Nebula Chest (1.5%)
A93: ORANGE
A94: Research Speed | D94: 5.4
A95: SkyWeb Hub | B95: SS | C95: TECH | L95: Koryeon Domain, Fragment Crafting (5.2%), Lottery Machine #1 (0.24%), Wishing (0.19%), Super Treasure Maps (5%), Master Scrolls (1.9%), Grandmaster Scrolls (2.1%), TECH Master Scrolls (9.2%)
A96: Fu Hao Scripts | B96: SS | C96: CIV | L96: Fragment Crafting (4.1%), Lottery Machine #1 (0.18%), Wishing (0.15%), Grandmaster Scrolls (1.6%)
A97: Buddha Finger Sarira | B97: SS | C97: FTH | L97: Fragment Crafting (3.3%), Lottery Machine #1 (0.18%), Wishing (0.12%), Bharata Treasure Maps (%), Grandmaster Scrolls (1.6%)
A98: Proclamation 95 | B98: SS | C98: FAME | L98: Fragment Crafting (0.61), Lottery Machine #1 (0.24%), Wishing (0.22%), Master Scrolls (0.19%), Grandmaster Scrolls (2.1%), FAME Master Scroll (9.2%)
A99: Cells Consumed | F99: 4.2
A100: Mummy of Ramesses | B100: SS | C100: FTH | L100: T7.5 Zombie Gene Research
A101: Ark of the Covenant | B101: SS | C101: FTH | L101: Fragment Crafting (15.1%), Lottery Machine #1 (0.81%), Wishing (0.53%), Relic Forge (90 Relic RF)
A102: MAX RESONANCE | D102: =sum(D79:D101) -> 12 | F102: =sum(F79:F101) -> 7.8 | H102: =sum(H79:H101) -> 0 | J102: =sum(J79:J101) -> 30
A105: DEMON
A106: INDIVIDUAL RELICS
A107: 5th Element | B107: SS | C107: TECH | D107: 7.2 | J107: 72 | K107: 60 | L107: Fragment Crafting (5.2%), Lottery Machine #1 (0.24%), Wishing (0.19%), Master Scrolls (1.9%), Grandmaster Scrolls (2.1%), TECH Master Scrolls (9.2%)
A108: Dream Top | B108: AAA | C108: CIV | D108: 5.4 | E108: 4.2 | L108: Fragment Crafting (1.5%), Lottery Machine #1 (0.03%), Wishing (0.14%), Time Chest (1.5%), Relic Forge (80 Relic RF)
A109: Corinthian Pillar | B109: AAA | C109: FTH | F109: 5.4 | H109: 5.4 | I109: 4.2 | L109: Fragment Crafting (1.5%), Lottery Machine #1 (0.03%), Wishing (0.14%), Relic Forge (80 Relic RF)
A110: Pompeii | B110: Blue | C110: ART | J110: 30 | K110: 30 | L110: Lottery Machine #2 (0.03%)
A111: Opera Phantom | B111: Blue | C111: ART | J111: 30 | K111: 30 | L111: Lottery Machine #1 (0.03%), Wishing (1.2%)
A112: Death Vase | B112: Green | C112: ART | H112: 1.8 | L112: "I want your collection!" Dragon Wish
A113: MAX INDIVIDUAL RELICS | D113: =sum(D106:E112) -> 16.8 | F113: =sum(F106:G112) -> 5.4 | H113: =sum(H106:I112) -> 11.4 | J113: =sum(J106:K112) -> 252
A115: RESONANCE
A116: BLUE
A117: Research Speed | D117: 3.6
A118: Ludovisi Gaul | B118: Blue | C118: ART | L118: Lottery Machine #1 (0.07%), Wishing (3%), Novice Scrolls (1%)
...

Sheet Cells Gained
A1: Name | B1: Rarity | C1: Type | D1: Zombie Cells | E1: Zombie Cells (Awakened) | F1: Demon Cells | G1: Demon Cells (Awakened) | H1: Angel Cells | I1: Angel Cells (Awakened) | J1: Mutant Cells | K1: Mutant Cells (Awakened) | L1: Mecha Cells | M1: Mecha Cells (Awakened) | N1: Source
A2: INDIVIDUAL RELICS
A3: Shroud of Turin | B3: S | C3: FTH | D3: 10 | E3: 10 | N3: Fragment Crafting (15.1%), Lottery Machine #1 (0.81%), Wishing (0.53%), Relic Forge (90 Relic RF)
A4: Eye of Akamoddo | B4: SS | C4: FTH | F4: 11 | G4: 10 | N4: Fragment Crafting (4.4%), Lottery Machine #1 (0.24%), Wishing (0.16%), Time Chest (1%), Master Scrolls (1.9%), Grandmaster Scrolls (2.1%), FTH Master Scrolls (9.2%)
A5: Time-Travel Box | B5: SS | C5: FAME | H5: 11 | I5: 10 | N5: Fragment Crafting (4.6%), Lottery Machine #1 (0.18%), Wishing (0.17%), Dragon Chest (5%), Grandmaster Scrolls (1.6%)
A6: Element R | B6: S | C6: TECH | J6: 10 | K6: 10 | N6: Fragment Crafting (17.8%), Lottery Machine #1 (0.81%), Wishing (0.65%), Relic Forge (90 Relic RF)
A7: SkyWeb Hub | B7: SS | C7: TECH | L7: 11 | M7: 10 | N7: Koryeon Domain, Fragment Crafting (5.2%), Lottery Machine #1 (0.24%), Wishing (0.19%), Super Treasure Maps (5%), Master Scrolls (1.9%), Grandmaster Scrolls (2.1%), TECH Master Scrolls (9.2%)
A8: Prehistoric Fossil | B8: AAA | C8: CIV | D8: 5.4 | F8: 5.4 | H8: 5.4 | J8: 5.4 | L8: 5.4 | N8: Fragment Crafting (1.5%), Lottery Machine #1 (0.03%), Wishing (0.14%), Time Chest (1.5%), Relic Forge (80 Relic RF)
A9: Imperial Lamp | B9: Blue | C9: ART | D9: 5 | E9: 5 | N9: Lottery Machine #1 (0.07%), Wishing (3%), Novice Scrolls (1%)
A10: Ranjyatai Incense | B10: Blue | C10: FTH | F10: 5 | G10: 5 | N10: Lottery Machine #1 (0.07%), Wishing (2.1%), Novice Scrolls (1%)
A11: Gone with the Wind | B11: Blue | C11: CIV | H11: 5 | I11: 5 | N11: Murikan Treasure Maps (20%)
A12: Izu Dancer | B12: Blue | C12: CIV | J12: 5 | K12: 5 | N12: Lottery Machine #1 (0.03%), Wishing (0.82%)
A13: Euclid's Elements | B13: Blue | C13: TECH | L13: 5 | M13: 5 | N13: Lottery Machine #1 (0.03%), Wishing (1.1%), Hellenic Treasure Map (%)
A14: MAX INDIVIDUAL RELICS | D14: =sum(D2:E13) -> 35.4 | F14: =sum(F2:G13) -> 36.4 | H14: =sum(H2:I13) -> 36.4 | J14: =sum(J2:K13) -> 35.4 | L14: =sum(L2:M13) -> 36.4
A16: ORGANS
A17: Evil Pattern | D17: 5 | F17: 5 | H17: 5 | J17: 5 | L17: 5 | N17: Tutorial (Evolution)
A18: Demon Spine | D18: 4 | F18: 4 | N18: Demon God Matrix (Demon God Rocket Cabin) Reward
A19: Eden Neuron | H19: 4 | L19: 4 | N19: Garden of Eden (Earth's Will Rocket Cabin) Reward
A20: Dark Matter's Heart | D20: 4 | F20: 4 | H20: 4 | J20: 8 | L20: 4 | N20: Dark Matter Reactor (Rebel Cabin) Reward
A21: Alveolus of Gaia | D21: 20 | F21: 20 | H21: 20 | J21: 20 | L21: 20 | N21: Feast Rewards
A22: MAX ORGANS | D22: =sum(D17:E21) -> 33 | F22: =sum(F17:G21) -> 33 | H22: =sum(H17:I21) -> 33 | J22: =sum(J17:K21) -> 33 | L22: =sum(L17:M21) -> 33
A24: ROCKET CABINS
A25: Eternal Hall | D25: 10 | F25: 10 | H25: 10 | J25: 10 | L25: 10 | N25: Demon God Cabin
A26: Silence Hall | D26: 10 | N26: Rebel Cabin
A27: Apocalypse Hall | F27: 10 | N27: Demon God Cabin
A28: Oracle Hall | H28: 10 | N28: Earth's Will Cabin
A29: Revelation Hall | J29: 10 | N29: Earth's Will Cabin
A30: Steel Hall | L30: 10 | N30: Rebel Cabin
A31: MAX ROCKET CABIN | D31: =sum(D25:E30) -> 20 | F31: =sum(F25:G30) -> 20 | H31: =sum(H25:I30) -> 20 | J31: =sum(J25:K30) -> 20 | L31: =sum(L25:M30) -> 20
A33: RESONANCE
A34: PURPLE
A35: Zombie | D35: 6
A36: Voynich Script | B36: AAA | C36: CIV | N36: Form Evo Pack
A37: The Nutcracker | B37: AAA | C37: ART | N37: Fragment Crafting (1.6%), Lottery Machine #1 (0.03%), Wishing (0.14%), Relic Forge (80 Relic RF)
A38: Demon | F38: 6
A39: Andersen's Fairytales | B39: AAA | C39: CIV | N39: Fragment Crafting (1.5%), Lottery Machine #1 (0.03%), Wishing (0.14%), Relic Forge (80 Relic RF)
A40: Magic Mirror | B40: AAA | C40: FTH | N40: Fragment Crafting (1.5%), Lottery Machine #1 (0.03%), Wishing (0.14%), Relic Forge (80 Relic RF)
A41: Angel | H41: 8
A42: Napoleon Painting | B42: AAA | C42: ART | N42: Fragment Crafting (1.6%), Lottery Machine #1 (0.03%), Wishing (0.14%), Relic Forge (Relic RF x80)
A43: Phoenician Tablet | B43: AA | C43: CIV | N43: Fragment Crafting (3.7%), Lottery Machine #1 (0.8%), Wishing (0.34%), Kemetic Treasure Maps (10%), Expert Scrolls (0.95%)
A44: Hawking's Wheelchair | B44: AAA | C44: TECH | N44: Fragment Crafting (1.6%), Lottery Machine #1 (0.03%), Wishing (0.35%), Relic Forge (80 Relic RF)
A45: Rosetta Stone | B45: A | C45: FAME | N45: Fragment Crafting (31%), Lottery Machine #1 (0.66%), Wishing (2.8%), Kemetic Treasure Maps (10%), Expert Scrolls (7.6%)
A46: Mutant | J46: 7
A47: Sword Throne | B47: AAA | C47: FAME | N47: Power Pack
A48: Marquis Bell | B48: AAA | C48: ART | N48: Fragment Crafting (1.6%), Lottery Machine #1 (0.03%), Wishing (1.4%), Cathay Treasure Maps (10%), Relic Forge (80 Relic RF)
A49: Lennon's Guitar | B49: AAA | C49: CIV | N49: Fragment Crafting (1.5%), Lottery Machine #1 (0.03%), Wishing (0.14%), Relic Forge (80 Relic RF)
A50: Mecha | L50: 7
A51: Dolly Specimen | B51: A | C51: TECH | N51: Fragment Crafting (31.5%), Lottery Machine #1 (0.66%), Wishing (2.9%), Expert Scrolls (7.6%)
A52: Augustus Medal | B52: AAA | C52: FAME | N52: Fragment Crafting (1.6%), Lottery Machine #1 (0.03%), Wishing (0.14%), Club Chest (1.5%), Relic Forge (80 Relic RF)
A53: Cornucopia | B53: AAA | C53: FTH | N53: Fragment Crafting (1.5%), Lottery Machine #1 (0.03%), Wishing (0.14%), Fungus Chest (1.5%), Relic Forge (80 Relic RF)
A54: MAX RESONANCE | D54: =sum(D35:D53) -> 6 | F54: =sum(F35:F53) -> 6 | H54: =sum(H35:H53) -> 8 | J54: =sum(J35:J53) -> 7 | L54: =sum(L35:L53) -> 7
B56: Zombie | C56: Demon | D56: Angel | E56: Mutant | F56: Mecha
A57: General Cell Gain | B57: =D14+D22+D31+D54 -> 94.4 | C57: =F14+F22+F31+F54 -> 95.4 | D57: =H14+H22+H31+H54 -> 97.4 | E57: =J14+J22+J31+J54 -> 95.4 | F57: =L14+L22+L31+L54 -> 96.4
A60: FORM SPECIFIC BONUSES
A61: ZOMBIE
A62: INDIVIDUAL RELICS
A63: Nobel's Will | B63: SSS | C63: FAME | D63: 12 | N63: Lottery Machine #1 (0.09%), Wishing (0.08%), Grandmaster Scrolls (0.79%), Lottery Event 9/22/2023-9/28/2023
A64: MAX INDIVIDUAL RELICS | D64: =sum(D62:E63) -> 12 | F64: =sum(F62:G63) -> 0 | H64: =sum(H62:I63) -> 0 | J64: =sum(J62:K63) -> 0 | L64: =sum(L62:M63) -> 0
A66: ORGANS
A67: Death Claw | D67: 6 | F67: 6 | H67: 6 | J67: 6 | L67: 6 | N67: Organ Chest (3% chance), Koryeo INTEL Exchange "Flesh Modification II"(x4), Wishing Event Value Pack V
A70: DEMON
A71: INDIVIDUAL RELICS
A72: St. Louisa Goblet | B72: SSS | C72: ART | F72: 12 | N72: Weekly Special Reward Relic #2
A73: MAX INDIVIDUAL RELICS | D73: =sum(D71:E72) -> 0 | F73: =sum(F71:G72) -> 12 | H73: =sum(H71:I72) -> 0 | J73: =sum(J71:K72) -> 0 | L73: =sum(L71:M72) -> 0
A75: ORGANS
A76: Demon Skull | D76: 6 | F76: 6 | H76: 6 | J76: 6 | L76: 6 | N76: Organ Chest (3%), Organ Value Pack II ($49.99), Grand Pack Day 2 Reward ($15.00 total anywhere in-game)
A79: ANGEL
A80: INDIVIDUAL RELICS
A81: Creation of Adam | B81: SSS | C81: CIV | H81: 12 | N81: Lottery Machine (0.09%), Wishing (0.08%), Grandmaster Scrolls (0.79%)
A82: MAX INDIVIDUAL RELICS | D82: =sum(D80:E81) -> 0 | F82: =sum(F80:G81) -> 0 | H82: =sum(H80:I81) -> 12 | J82: =sum(J80:K81) -> 0 | L82: =sum(L80:M81) -> 0
A84: ORGANS
A85: Strength Crystal | D85: 6 | F85: 6 | H85: 6 | J85: 6 | L85: 6 | N85: Organ Chest (3% chance)
A88: MUTANT
A89: INDIVIDUAL RELICS
A90: Einstein's Brain | B90: SSS | C90: FAME | J90: 12 | N90: Lottery Machine (0.09%), Wishing (0.08%), Grandmaster Scrolls (0.79%)
A91: MAX INDIVIDUAL RELICS | D91: =sum(D89:E90) -> 0 | F91: =sum(F89:G90) -> 0 | H91: =sum(H89:I90) -> 0 | J91: =sum(J89:K90) -> 12 | L91: =sum(L89:M90) -> 0
A93: ORGANS
A94: Death Claw | D94: 6 | F94: 6 | H94: 6 | J94: 6 | L94: 6 | N94: Organ Chest (3% chance), Koryeo INTEL Exchange "Flesh Modification II"(x4), Wishing Event Value Pack V
A97: MECHA
A98: INDIVIDUAL RELICS
A99: Kepler Telescope | B99: SSS | C99: TECH | L99: 12 | N99: Ultimate Special Reward Relic #1
A100: MAX INDIVIDUAL RELICS | D100: =sum(D98:E99) -> 0 | F100: =sum(F98:G99) -> 0 | H100: =sum(H98:I99) -> 0 | J100: =sum(J98:K99) -> 0 | L100: =sum(L98:M99) -> 12
A102: ORGANS
A103: Strength Crystal | D103: 6 | F103: 6 | H103: 6 | J103: 6 | L103: 6 | N103: Organ Chest (3% chance)
A106: DRAGON
A107: ORGANS
A108: Demon Skull | D108: 6 | F108: 6 | H108: 6 | J108: 6 | L108: 6 | N108: Organ Chest (3%), Organ Value Pack II ($49.99), Grand Pack Day 2 Reward ($15.00 total anywhere in-game)
B111: Zombie | C111: Demon | D111: Angel | E111: Mutant | F111: Mecha
A112: Cells Collected (Zombie Form) | B112: =$B$57+D64+D67 -> 112.4 | C112: =$C$57+F64+F67 -> 101.4 | D112: =$D$57+H64+H67 -> 103.4 | E112: =$D$57+J64+J67 -> 103.4 | F112: =$D$57+L64+L67 -> 103.4
A113: Cells Collected (Demon Form) | B113: =$B$57+D73+D76 -> 100.4 | C113: =$C$57+F73+F76 -> 113.4 | D113: =$D$57+H73+H76 -> 103.4 | E113: =$D$57+J73+J76 -> 103.4 | F113: =$D$57+L73+L76 -> 103.4
A114: Cells Collected (Angel Form) | B114: =$B$57+D82+D85 -> 100.4 | C114: =$C$57+F82+F85 -> 101.4 | D114: =$D$57+H82+H85 -> 115.4 | E114: =$D$57+J82+J85 -> 103.4 | F114: =$D$57+L82+L85 -> 103.4
A115: Cells Collected (Mutant Form) | B115: =$B$57+D91+D94 -> 100.4 | C115: =$C$57+F91+F94 -> 101.4 | D115: =$D$57+H91+H94 -> 103.4 | E115: =$D$57+J91+J94 -> 115.4 | F115: =$D$57+L91+L94 -> 103.4
A116: Cells Collected (Mecha Form) | B116: =$B$57+D100+D103 -> 100.4 | C116: =$C$57+F100+F103 -> 101.4 | D116: =$D$57+H100+H103 -> 103.4 | E116: =$D$57+J100+J103 -> 103.4 | F116: =$D$57+L100+L103 -> 115.4
A117: Cells Collected (Dragon Form) | B117: =$B$57+D108 -> 100.4 | C117: =$C$57+F108 -> 101.4 | D117: =$D$57+H108 -> 103.4 | E117: =$D$57+J108 -> 103.4 | F117: =$D$57+L108 -> 103.4

Sheet Museum
B1: Rarity | C1: AFFCT | D1: Main AFFCT | E1: Total AFFCT | F1: Medal Output | G1: Wish Coin Cost | H1: Btad Output | I1: AFFCT Boost | J1: Effective AFFCT | K1: Total Effective AFFCT | L1: Source
A2: KORYEO
A3: INDIVIDUAL RELICS
A4: Ordinary Casket | B4: SSS | C4: FAME | D4: 104 | E4: 347 | F4: 30 | I4: 15 | J4: =D4+I4 -> 119 | K4: =E4+I4 -> 362 | L4: Relic Power Rewards (8M - 15M Relic Power)
A5: Leaf of Yggdrasil | B5: S | C5: FAME | D5: 100 | E5: 332 | J5: =D5+I5 -> 100 | K5: =E5+I5 -> 332 | L5: Fragment Crafting (20.7%), Lottery Machine #1 (0.81%), Wishing (0.75%), Super Treasure Map (15%), Master Scrolls (6.5%), FAME Master Scrolls (31.5%), Relic Forge (90 Relic RF)
A6: Twin Lions Lantern | B6: AA | C6: FAME | D6: 70 | I6: 10 | J6: =D6+I6 -> 80 | L6: Museum Operation Reward
A7: Mischief Map | B7: AA | C7: FAME | D7: 71 | J7: =D7+I7 -> 71 | L7: Domain Exploration Reward
A8: View of Le Gras | B8: A | C8: FAME | D8: 64 | J8: =D8+I8 -> 64 | L8: Lottery Machine #2 (0.55%)
A9: Peter Pan's Flute | B9: Blue | C9: FAME | D9: 46 | J9: =D9+I9 -> 46 | L9: Lottery Machine #1 (0.03%), Wishing (1.2%), Britland Treasure Map (20%)
A10: Annals of Joseon | B10: Blue | C10: FAME | D10: 45 | J10: =D10+I10 -> 45 | L10: Koryeo Treasure Map (20%)
A11: Hun Min Jong Um | B11: Blue | C11: FAME | D11: 45 | J11: =D11+I11 -> 45 | L11: Koryeo Treasure Map (20%)
A12: King's Gayageum | B12: SSS | C12: ART | D12: 107 | E12: 362 | I12: 15 | J12: =D12+I12 -> 122 | K12: =E12+I12 -> 377 | L12: Daily Pack Relic #7
A13: Irises | B13: SSS | C13: ART | D13: 106 | E13: 362 | H13: 3000 | I13: 15 | J13: =D13+I13 -> 121 | K13: =E13+I13 -> 377 | L13: Star Chart Shop
A14: Suger's Eagle | B14: S | C14: ART | D14: 99 | E14: =48+99+63+66+56 -> 332 | J14: =D14+I14 -> 99 | K14: =E14+I14 -> 332 | L14: Lottery Machine #2 (1.59%)
A15: Death of Marat | B15: AA | C15: ART | D15: 69 | J15: =D15+I15 -> 69 | L15: Fragment Crafting (3.9%), Lottery Machine #1 (0.08%), Wishing (0.36%), Expert Scrolls (0.95%)
A16: King Dangun Statue | B16: S | C16: FTH | D16: 99 | E16: 332 | G16: 30 | J16: =D16+I16 -> 99 | K16: =E16+I16 -> 332 | L16: Fragment Crafting (15.1%), Lottery Machine #1 (0.81%), Wishing (0.81%), Koryeo Treasure Map (5%), Relic Forge (90 Relic RF)
A17: Tree of Life | B17: AAA | C17: FTH | D17: 72 | I17: 10 | J17: =D17+I17 -> 82 | L17: Fragment Crafting (1.5%), Wishing (0.03%), Lottery Machine #1 (0.14%), Fungus chest (1.5%), Relic Forge (80 Relic RF), Home Value Pack II ($4.99)
A18: Tyr's Arm | B18: AA | C18: FTH | D18: 66 | J18: =D18+I18 -> 66 | L18: Fragment Crafting (3.8%), Lottery Machine #1 (0.08%), Wishing (0.35%), Expert Scrolls (0.95%)
A19: Dragon Crystal | B19: Blue | C19: FTH | D19: 45 | J19: =D19+I19 -> 45 | L19: Dragon Gene Research Tier 2
A20: Aries | B20: SSS | C20: CIV | D20: 110 | E20: 365 | J20: =D20+I20 -> 110 | K20: =E20+I20 -> 365 | L20: Supreme Relic ($2k)
A21: Divine Comedy | B21: SSS | C21: CIV | D21: 106 | E21: 362 | F21: 30 | J21: =D21+I21 -> 106 | K21: =E21+I21 -> 362 | L21: Lottery Machine #1 (0.09%), Wishing (0.08%), Grandmaster Scrolls (0.81%), Relic Forge (120 Relic RF)
A22: Prehistoric Fossil | B22: AAA | C22: CIV | D22: 75 | J22: =D22+I22 -> 75 | L22: Fragment Crafting (1.5%), Lottery Machine #1 (0.03%), Wishing (0.14%), Time Chest (1.5%), Relic Forge (80 Relic RF)
A23: Koryeon Sutra | B23: AAA | C23: CIV | D23: 73 | J23: =D23+I23 -> 73 | L23: Fragment Crafting (1.5%), Lottery Machine #1 (0.03%), Wishing (0.14%), Koryeon Treasure Maps (10%), Relic Forge (80 Relic RF)
A24: Im's Arrow | B24: Blue | C24: CIV | D24: 44 | J24: =D24+I24 -> 44 | L24: Lottery Machine #1 (0.07%), Wishing (2.1%), Novice Scrolls (1%)
A25: Energy Missile | B25: SSS | C25: TECH | D25: 109 | E25: 362 | I25: 15 | J25: =D25+I25 -> 124 | K25: =E25+I25 -> 377 | L25: Clover Vendor Reward
A26: Devol's Robot | B26: S | C26: TECH | D26: 97 | E26: 332 | I26: 15 | J26: =D26+I26 -> 112 | K26: =E26+I26 -> 347 | L26: Fragment Crafting (17.8%), Wishing (0.65%), Ad Chest (3%), Master Scrolls (6.5%), TECH Master Scrolls (31.5%), Relic Forge (90 Relic RF)
A27: Artificial Blackhole | B27: SSS | C27: TECH | D27: 106 | E27: 362 | J27: =D27+I27 -> 106 | K27: =E27+I27 -> 362 | L27: Wish Box, Lottery Machine #1 (0.09%), Wishing (0.07%), Demon God Chest (0.1%), Grandmaster Scrolls (0.81%), Relic Forge (120 Relic RF), Nebula Chest (0.01%)
A28: Arirang Satillite | B28: Blue | C28: TECH | D28: 46 | J28: =D28+I28 -> 46 | L28: Lottery Machine #1 (0.03%), Wishing (1.1%), Nebula Chest (2%)
A31: MUSEUM LAYOUT | C31: Restriction | D31: Used | E31: Museum Score | F31: Medal Output | G31: Wish Coin Cost | H31: Btad Output
A32: 1 | B32: ALL | D32: Irises | E32: =K13 -> 377 | H32: =H13 -> 3000
A33: 2 | B33: FTH | C33: King Dangun Statue | D33: King Dangun Statue | E33: =J16 -> 99 | G33: =G16 -> 30
A34: 3 | B34: FAME | C34: Hun Min Jong Um | D34: Hun Min Jong Um | E34: =J11 -> 45
A35: 4 | B35: FAME | C35: Annals of Joseon | D35: Annals of Joseon | E35: =J10 -> 45
A36: 5 | B36: FAME | D36: Ordinary Casket | E36: =J4 -> 119 | F36: =F4 -> 30
A37: 6 | B37: ART | D37: King's Gayageum | E37: =J12 -> 122
A38: 7 | B38: ART | D38: FILLER | E38: 100
A39: 8 | B39: ART | D39: FILLER | E39: 100
A40: 9 | B40: FTH | D40: FILLER | E40: 100
A41: 10 | B41: FTH | D41: FILLER | E41: 100
A42: 11 | B42: CIV | D42: Aries | E42: =J20 -> 110
A43: 12 | B43: CIV | D43: Divine Comedy | E43: =J21 -> 106 | F43: =F21 -> 30
A44: 13 | B44: CIV | D44: FILLER | E44: 100
A45: 14 | B45: TECH | D45: Energy Missile | E45: =J25 -> 124
A46: 15 | B46: TECH | D46: Devol's Robot | E46: =J26 -> 112
A47: 16 | B47: TECH | D47: Artificial Blackhole | E47: =J27 -> 106
D48: TOTAL | E48: =SUM(E32:E47) -> 1865 | F48: =SUM(F32:F47) -> 60 | G48: =SUM(G32:G47) -> 30 | H48: =SUM(H32:H47) -> 3000
D62: Main AFFCT | E62: Total AFFCT | F62: Medal Output | G62: Wish Coin Cost | H62: Btad Output | I62: AFFCT Boost | J62: Effective AFFCT | K62: Total Effective AFFCT | L62: Source
A63: YAMATO
A64: INDIVIDUAL RELICS
A65: Metchnikoff's Manuscripts | B65: SSS | C65: FAME | D65: 107 | E65: 362 | H65: 3000 | I65: 15 | J65: =D65+I65 -> 122 | K65: =E65+I65 -> 377 | L65: 3/8 Voucher Shop Reward, Lottery Machine #2 (?%)
A66: Manga Manuscript | B66: SSS | C66: FAME | D66: 106 | E66: =106+62+49+69+76 -> 362 | F66: 30 | J66: =D66+I66 -> 106 | K66: =E66+I66 -> 362 | L66: Daily Pack Relic #20
A67: Cross of Lorraine | B67: SS | C67: FAME | D67: 104 | E67: =104+57+52+68+66 -> 347 | J67: =D67+I67 -> 104 | K67: =E67+I67 -> 347 | L67: Lottery Machine #2 (0.23%)
A68: Costa Rica Stone | B68: Blue | C68: FAME | D68: 48 | J68: =D68+I68 -> 48 | L68: Lottery Machine #1 (0.36%), Wishing (15.5%), Novice Scrolls (5%)
A69: Taurus | B69: SSS | C69: ART | D69: 110 | E69: 363 | J69: =D69+I69 -> 110 | K69: =E69+I69 -> 363 | L69: Supreme Relic ($4k)
A70: Sistine Madonna | B70: SSS | C70: ART | D70: 109 | E70: 362 | J70: =D70+I70 -> 109 | K70: =E70+I70 -> 362 | L70: Lottery Machine #1 (0.09%), Wishing (0.08%), Grandmaster Scrolls (0.81%), Relic Forge (120 Relic RF)
A71: Veiled Lady | B71: SS | C71: ART | D71: 103 | E71: =52+103+67+70+55 -> 347 | I71: 15 | J71: =D71+I71 -> 118 | K71: =E71+I71 -> 362 | L71: Lottery Machine #2 (0.47%), Indigent Nobleman (570K B-tads)
A72: Nishijin Fabric | B72: AAA | C72: ART | D72: 73 | I72: 10 | J72: =D72+I72 -> 83 | K72: =E72+I72 -> 10 | L72: Lottery Box Relic #8
A73: Pine Trees Screen | B73: AA | C73: ART | D73: 67 | J73: =D73+I73 -> 67 | L73: Fragment Crafting (3.9%), Lottery Machine #1 (0.08%), Wishing (0.36%), Yamato Treasure Maps (10%), Expert Scrolls (0.95%)
A74: Great Wave | B74: Blue | C74: ART | D74: 48 | J74: =D74+I74 -> 48 | L74: Lottery Machine #1 (0.07%), Wishing (3%), Yamato Treasure Maps (20%)
A75: Universe Bowl | B75: Blue | C75: ART | D75: 48 | J75: =D75+I75 -> 48 | L75: Lottery Machine #1 (0.07%), Wishing (3%), Fungus Chest (2%), Novice Scrolls (1%)
A76: Cuckoo Clock | B76: Blue | C76: ART | D76: 47 | J76: =D76+I76 -> 47 | L76: Lottery Machine #1 (0.07%), Wishing (3%), Time Chest (2%), Novice Scrolls (1%)
A77: Medium Rune | B77: SSS | C77: FTH | D77: 106 | E77: =63+74+106+50+69 -> 362 | F77: 30 | I77: 15 | J77: =D77+I77 -> 121 | K77: =E77+I77 -> 377 | L77: Halloween Event, Lottery Machine #2 (0.12%)
A78: Bhagavata Purana | B78: SS | C78: FTH | D78: 103 | E78: =61+64+103+55+64 -> 347 | J78: =D78+I78 -> 103 | K78: =E78+I78 -> 347 | L78: Lottery Machine #2 (0.47%)
A79: Golden Finger | B79: S | C79: FTH | D79: 100 | E79: 332 | J79: =D79+I79 -> 100 | K79: =E79+I79 -> 332 | L79: Fragment Crafting (15.1%), Lottery Machine #1 (0.81%), Wishing (0.53%), Master Scrolls (6.5%), FTH Master Scrolls (31.5%), Relic Forge (90 Relic RF)
A80: Yamato Mirror | B80: AAA | C80: FTH | D80: 75 | J80: =D80+I80 -> 75 | L80: Fragment Crafting (1.5%), Lottery Machine #1 (0.03%), Wishing (0.14%), Relic Forge (80 Relic RF)
A81: Kani Jade | B81: AA | C81: FTH | D81: 79 | I81: 10 | J81: =D81+I81 -> 89 | L81: Yamato INTEL, Yamato Treasure Maps (10% chance)
A82: Lion-dogs Statue | B82: AA | C82: FTH | D82: 66 | J82: =D82+I82 -> 66 | L82: Museum Operation Reward
A83: Ranjyatai Incense | B83: Blue | C83: FTH | D83: 45 | J83: =D83+I83 -> 45 | L83: Lottery Machine #1 (0.07%), Wishing (2.1%), Novice Scrolls (1%)
A84: Aladdin Carpet | B84: SSS | C84: CIV | D84: 109 | E84: 362 | F84: 30 | I84: 15 | J84: =D84+I84 -> 124 | K84: =E84+I84 -> 377 | L84: Daily Silver Pack Relic #1
A85: Eight Proposals | B85: SS | C85: CIV | D85: 104 | E85: =64+66+60+104+53 -> 347 | J85: =D85+I85 -> 104 | K85: =E85+I85 -> 347 | L85: Lottery Machine #2 (0.23%)
A86: The Tale of Genji | B86: S | C86: CIV | D86: 100 | E86: 332 | J86: =D86+I86 -> 100 | K86: =E86+I86 -> 332 | L86: Fragment Crafting (18.8%), Lottery Machine #1 (0.81%), Wishing (0.69%), Yamoto Treasure Map (5%), Master Scroll (6.5%), CIV Master Scroll (37.5%), Relic Forge (90 Relic RF)
A87: Paradise Lost | B87: S | C87: CIV | D87: 96 | E87: 332 | J87: =D87+I87 -> 96 | K87: =E87+I87 -> 332 | L87: Fragment Crafting (18.8%), Lottery Machine #1 (0.81%), Wishing (0.69%), Super Treasure Maps (15%), Master Scrolls (6.5%), CIV Master Scrolls (34.7%), Relic Forge (90 Relic RF)
A88: Rashomon | B88: AAA | C88: CIV | D88: 71 | J88: =D88+I88 -> 71 | L88: Gastric Pouch
A89: Art of Ninja | B89: Blue | C89: CIV | D89: 48 | J89: =D89+I89 -> 48 | L89: Yamato Treasure Maps (20%)
A90: Mendel's Law | B90: SSS | C90: TECH | D90: 109 | E90: 362 | I90: 15 | J90: =D90+I90 -> 124 | K90: =E90+I90 -> 377 | L90: Maneater Sunny Feed
A91: Species Plantarum | B91: SSS | C91: TECH | D91: 106 | E91: 362 | H91: 3000 | I91: 15 | J91: =D91+I91 -> 121 | K91: =E91+I91 -> 377 | L91: Star Chart Shop
A92: SC Energy Storage Unit | B92: SS | C92: TECH | D92: 103 | E92: 347 | J92: =D92+I92 -> 103 | K92: =E92+I92 -> 347 | L92: Lottery Machine #2 (0.47%)
A93: Sputnik 1 | B93: SS | C93: TECH | D93: 104 | E93: 347 | J93: =D93+I93 -> 104 | K93: =E93+I93 -> 347 | L93: Fragment Crafting (3.9%), Lottery Machine #1 (0.18%), Wishing (0.14%), Club Chest (1%), Grandmaster Scrolls (1.5%)
A94: 5th Element | B94: SS | C94: TECH | D94: 103 | E94: 347 | J94: =D94+I94 -> 103 | K94: =E94+I94 -> 347 | L94: Fragment Crafting (5.2%), Lottery Machine #1 (0.24%), Wishing (0.19%), Master Scrolls (1.9%), Grandmaster Scrolls (2.1%), TECH Master Scrolls (9.2%)
A95: Tokamak | B95: SS | C95: TECH | D95: 102 | E95: 347 | J95: =D95+I95 -> 102 | K95: =E95+I95 -> 347 | L95: Fragment Crafting (5.2%), Lottery Machine #1 (0.24%), Wishing (1.9%), Master Scrolls (1.9%), Grandmaster Scrolls (2.1%), TECH Master Scrolls (9.2%)
A96: Diffraction Device | B96: S | C96: TECH | D96: 97 | E96: =63+56+62+54+97 -> 332 | J96: =D96+I96 -> 97 | K96: =E96+I96 -> 332 | L96: Lottery Machine #2 (1.59%)
A97: Mars Rover | B97: AAA | C97: TECH | D97: 75 | J97: =D97+I97 -> 75 | L97: Fragment Crafting (1.6%), Lottery Machine #1(0.03%), Wishing (0.14%), Evolution Chest (1.5%), Relic Forge (80 Relic RF)
A98: Tesla Coil | B98: AAA | C98: TECH | D98: 73 | J98: =D98+I98 -> 73 | L98: Fragment Crafting (1.6%), Lottery Machine #1 (0.03%), Wishing (0.14%), Tool Chest (1.5%), Relic Forge (80 Relic RF)
A99: Klein Bottle | B99: Blue | C99: TECH | D99: 48 | J99: =D99+I99 -> 48 | L99: Lottery Machine #1 (0.07%), Wishing (2.6%), Novice Scrolls (1%)
A102: MUSEUM LAYOUT | C102: Restriction | D102: Used | E102: Museum Score | F102: Medal Output | G102: Wish Coin Cost | H102: Btad Output
A103: 1 | B103: ALL | D103: Species Plantarum | E103: =K91 -> 377 | H103: =H91 -> 3000
A104: 2 | B104: CIV | C104: Tales of Genji | D104: Tales of Genji | E104: =J86 -> 100
A105: 3 | B105: FTH | C105: Kani Jade | D105: Kani Jade | E105: =J81 -> 89
A106: 4 | B106: ART | C106: Great Wave | D106: Great Wave | E106: =J74 -> 48
A107: 5 | B107: FAME | D107: Metchnikoff's Manuscripts | E107: =J65 -> 122 | H107: =H65 -> 3000
A108: 6 | B108: FAME | D108: Manga Manuscript | E108: =J67 -> 104 | F108: =F66 -> 30
A109: 7 | B109: FAME | D109: Cross of Lorraine | E109: =J68 -> 48
A110: 8 | B110: ART | D110: Veiled Lady | E110: =J71 -> 118
A111: 9 | B111: ART | D111: Taurus | E111: =J69 -> 110
A112: 10 | B112: FTH | D112: Medium Rune | E112: =J77 -> 121 | F112: =F77 -> 30
A113: 11 | B113: FTH | D113: Bhagawata Purana | E113: =J78 -> 103
A114: 12 | B114: CIV | D114: Aladdin Carpet | E114: =J84 -> 124 | F114: =F84 -> 30
A115: 13 | B115: CIV | D115: Eight Proposals | E115: =J85 -> 104
A116: 14 | B116: TECH | D116: Mendel's Law | E116: =J90 -> 124
A117: 15 | B117: TECH | D117: Sputnik 1 | E117: =J93 -> 104
...

Sheet Rocket Cabin Effects
B1: Rarity | C1: Type | D1: Base Effect | E1: Base Effect (Awakened) | F1: Source
A4: REBEL CABIN
A5: Jiuzhang | B5: SSS | C5: TECH | D5: 12 | F5: Lottery Machine #2 (0.12%)
A7: Resonance: Orange | D7: 10
A8: Mysterious Relic | B8: SSS | F8: Unknown
A9: Atlantis Crystal | B9: SSS | C9: FTH | F9: Lottery Machine #2 (0.12%), Relic Forge (120 RF)
A10: Lawrence's Cyclotron | B10: SSS | C10: TECH | F10: Lottery Machine #2 (0.12%)
A11: Science Magazine Vol.1 | B11: SSS | C11: FAME | F11: Lottery Machine #2 (0.12%)
A12: Phaistos Disc | B12: SSS | C12: CIV | F12: Lottery Machine #2 (0.12%), Relic Forge (120 RF)
A13: MAX REBEL CABIN | D13: =sum(D5:E12) -> 22
A16: Photonic Communicator (Angel)
A17: Cross of Lorraine | B17: SS | C17: FAME | D17: 88 | F17: Lottery Machine #2 (?%)
A18: Akebono | B18: Blue | C18: TECH | D18: 40 | E18: 40 | F18: Lottery Machine #2 (?%)
A20: Resonance: Orange | D20: 56
A21: Rutherford Model | B21: SS | C21: TECH | F21: Lottery Machine #2 (0.23%)
A22: SC Energy Storage Unit | B22: SS | C22: TECH | F22: Lottery Machine #2 (0.47%)
A23: MAX PHOTONIC COMMUNICATOR | D23: =sum(D17:E22) -> 224
A26: Prismatic Armor (Mecha)
A27: Eight Proposals | B27: SS | C27: CIV | D27: 88 | F27: Lottery Machine #2 (0.23%)
A28: Model G Loom | B28: Blue | C28: FAME | D28: 40 | E28: 40 | F28: Lottery Machine #2 (0.03%)
A30: Resonance: Orange | D30: 56
A31: Crime and Punishment | B31: SSS | C31: CIV | F31: Lottery Machine #2 (0.12%)
A32: Palermo Stone | B32: SSS | C32: TECH | F32: Lottery Machine #2 (1.59%), Rift Treasure Maps (5%)
A33: MAX PRISMATIC ARMOR | D33: =sum(D27:E32) -> 224
A36: Auto-reload Device (Demon)
A37: Eight Proposals | B37: SS | C37: CIV | D37: 88 | F37: Lottery Machine #2 (0.23%)
A38: The Knotted Pistol | B38: Blue | C38: FAME | D38: 40 | E38: 40 | F38: Lottery Machine #2 (0.03%)
A39: MAX AUTO-RELOAD DEVICE | D39: =sum(D37:E38) -> 168
A42: Biochemical MOD Module (Zombie)
A43: Swimming Reindeer | B43: SS | C43: ART | D43: 88 | F43: Lottery Machine #2 (0.35%)
A44: Bastet Bronze Statue | B44: Blue | C44: FTH | D44: 40 | E44: 40 | F44: Lottery Machine #2 (0.03%), Indigent Nobleman (72K B-tads)
A45: MAX BIOCHEMICAL MOD MODULE | D45: =sum(D43:E44) -> 168
A48: Anti-gravity Device (Mecha)
A49: Oxus Treasure | B49: SSS | C49: ART | D49: 96 | F49: Lottery Machine #2 (0.12%), Relic Forge (120 RF)
A50: DNA Microarray | B50: AA | C50: TECH | D50: 64 | E50: 56 | F50: Lottery Machine #2 (0.12%)
A52: Resonance: Orange | D52: 64
A53: Hevelius Chart | B53: SSS | C53: CIV | F53: Star Chart Shop
A54: Veiled Lady | B54: SS | C54: ART | F54: Lottery Machine #2 (0.47%), Indigent Nobleman (570K B-tads)
A55: The Kiss | B55: S | C55: FAME | F55: Lottery Machine #2 (1.59%)
A56: MAX ANTI-GRAVITY DEVICE | D56: =sum(D49:E55) -> 280
A59: Dark Matter Reactor (Zombie)
A60: Black Body | B60: SSS | C60: TECH | D60: 96 | F60: Lottery Machine #2 (0.12%)
A61: Mother and Daughter | B61: AA | C61: ART | D61: 64 | E61: 56 | F61: Lottery Machine #2 (0.12%)
A63: Resonance: Orange | D63: 64
A64: Stockholm Declaration | B64: SS | C64: FAME | F64: Lottery Machine #2 (0.47%), Indigent Nobleman (570K B-tads)
A65: Last Self Portrait | B65: SSS | C65: ART | F65: Daily Pack Relic #15
A66: Tao Te Ching | B66: SSS | C66: CIV | F66: Lottery Machine #2 (0.12%)
A67: MAX DARK MATTER REACTOR | D67: =sum(D60:E66) -> 280
A70: Steel Hall (All)
A71: Atlantis Crystal | B71: SSS | C71: FTH | D71: 96 | F71: Lottery Machine #2 (0.12%), Relic Forge (120 RF)
A72: Le Verrier's Scripts | B72: AAA | C72: TECH | D72: 72 | E72: 56 | F72: Lottery Machine #2 (0.06%)
A73: MAX STEEL HALL | D73: =sum(D71:E72) -> 224
A76: Silence Hall (All)
A77: Atlantis Crystal | B77: SSS | C77: FTH | D77: 96 | F77: Lottery Machine #2 (0.12%), Relic Forge (120 RF)
A78: Solar Sail | B78: AAA | C78: TECH | D78: 72 | E78: 56 | F78: Lottery Machine #2 (0.06%), Rift Treasure Maps (10%)
A79: MAX SILENCE HALL | D79: =sum(D77:E78) -> 224
B82: Base Effect
A83: =A16 -> Photonic Communicator (Angel) | B83: =D23+D13 -> 246
A84: =A26 -> Prismatic Armor (Mecha) | B84: =D33+D13 -> 246
A85: =A36 -> Auto-reload Device (Demon) | B85: =D39+D13 -> 190
A86: =A42 -> Biochemical MOD Module (Zombie) | B86: =D45+D13 -> 190
A87: =A48 -> Anti-gravity Device (Mecha) | B87: =D56+D13 -> 302
A88: =A59 -> Dark Matter Reactor (Zombie) | B88: =D67+D13 -> 302
A89: =A70 -> Steel Hall (All) | B89: =D73+D13 -> 246
A90: =A76 -> Silence Hall (All) | B90: =D79+D13 -> 246
A96: DEMON GOD CABIN
A98: Resonance: Orange | D98: 10
A99: Mysterious Relic | B99: SSS | F99: Unknown
A100: Orphic Egg | B100: SSS | C100: FTH | F100: Lottery Machine #2 (0.12%), Relic Forge (120 RF)
A101: Two-headed Serpent | B101: SSS | C101: ART | F101: Lottery Machine #2 (0.12%), Relic Forge (120 RF)
A102: Antarctic Treaty | B102: SSS | C102: FAME | F102: Lottery Machine #2 (0.12%)
A103: Black Body | B103: SSS | C103: TECH | F103: Lottery Machine #2 (0.12%)
A104: MAX DEMON GOD CABIN | D104: =sum(D97:E103) -> 10
A107: Particle Accelerator (Demon)
A108: Rutherford Model | B108: SS | C108: TECH | D108: 88 | F108: Lottery Machine #2 (0.23%)
A109: Lissajous Figure | B109: Blue | C109: TECH | D109: 40 | E109: 40 | F109: Lottery Machine #2 (0.03%)
A111: Resonance: Orange | D111: 56
A112: Lawrence's Cyclotron | B112: SSS | C112: TECH | F112: Lottery Machine #2 (0.12%)
A113: AMS | B113: SS | C113: TECH | F113: Lottery Machine #2 (0.47%), Indigent Nobleman (570K B-tads)
A114: MAX PARTICLE ACCELERATOR | D114: =sum(D108:E113) -> 224
A117: Assist System (Dragon)
A118: Grimmy Award | B118: SS | C118: FAME | D118: 88 | F118: Lottery Machine #2 (0.35%)
A119: The Prayer | B119: Blue | C119: ART | D119: 40 | E119: 40 | F119: Lottery Machine #2 (0.03%)
A121: Resonance: Orange | D121: 56
A122: Pride & Prejudice | B122: S | C122: CIV | F122: Lottery Machine #2 (1.59%)
A123: Grimmy Award | B123: SS | C123: FAME | F123: Lottery Machine #2 (0.35%)
A124: MAX ASSIST SYSTEM | D124: =sum(D118:E123) -> 224
A127: Orbit Assimilator (Mecha)
A128: Ruska's Microscope | B128: SS | C128: TECH | D128: 88 | F128: Lottery Machine #2 (0.35%)
A129: Montgolfier Balloon | B129: Blue | C129: FAME | D129: 40 | E129: 40 | F129: Lottery Machine #2 (0.03%)
A130: MAX ORBIT ASSIMILATOR | D130: =sum(D128:E129) -> 168
A133: Gravity Propeller (Mutant)
A134: Zircon of Jack Hills | B134: SS | C134: FAME | D134: 88 | F134: Lottery Machine #2 (0.47%)
A135: The Fall of Phaethon | B135: Blue | C135: ART | D135: 40 | E135: 40 | F135: Lottery Machine #2 (0.03%), Indigent Nobleman (72K B-tads)
A136: MAX GRAVITY PROPELLER | D136: =sum(D134:E135) -> 168
A139: Demon God Matrix (Demon)
A140: The Silver Key | B140: SSS | C140: FTH | D140: 96 | F140: Rift Treasure Maps (0.01%), Lottery Machine #2 (0.12%)
A141: Celaeno Fragments | B141: AA | C141: FTH | D141: 64 | E141: 56 | F141: Lottery Machine #2 (0.12%)
A143: Resonance: Orange | D143: 64
A144: L'Art de la Guerre | B144: SSS | C144: FAME | F144: Star Chart Shop
...

Sheet Minion Boosts
A1: GENERAL
A2: HP | B2: Rarity | C2: Type | D2: Base | E2: Awakening Base | F2: Percentage | G2: Awakening Percentage | H2: Per Minion | I2: Per Minion Boost | J2: Source | O2: HP (Per Minion) | P2: HP (%) | Q2: ATK (Per Minion) | R2: ATK (%) | S2: RUSH (Per Minion) | T2: RUSH (%) | U2: DEF (Per Minion) | V2: DEF (%) | W2: HARD (Per Minion) | X2: HARD (%)
A3: Last Self Portrait | B3: SSS | C3: ART | D3: 900 | E3: 900 | H3: 60 | I3: =(D3+E3)/H3 -> 30 | J3: Daily Pack Relic #15 | N3: General | O3: =I37 -> 219.33333 | P3: =F37 -> 19.8 | Q3: =I91 -> 31.783333 | R3: =F91 -> 14.8 | S3: =I131 -> 18.8 | T3: =F131 -> 10.2 | U3: =I167 -> 17.516667 | V3: =F167 -> 9 | W3: =I201 -> 12.533333 | X3: =F201 -> 1.2
A4: Wild Pansy's Juice | B4: AAA | C4: FTH | D4: 360 | E4: 280 | H4: 30 | I4: =(D4+E4)/H4 -> 21.333333 | J4: Gastric Pouch | N4: Zombie | O4: =I227 -> 58.5 | P4: =F227 -> 68 | Q4: =I254 -> 12.516667 | R4: =F254 -> 60 | S4: =I275 -> 4.7 | T4: =F275 -> 82 | U4: =I294 -> 6.5666667 | V4: =F294 -> 56 | W4: =I308 -> 5.2166667 | X4: =F308 -> 4.8
A5: Arianrhod's Wheel | B5: SSS | C5: FTH | D5: 1200 | H5: 60 | I5: =(D5+E5)/H5 -> 20 | J5: Daily Pack Relic #47
A6: Treasure Island | B6: AAA | C6: CIV | D6: 320 | E6: 280 | H6: 30 | I6: =(D6+E6)/H6 -> 20 | J6: Time Beacon Reward | N6: Demon | O6: =I332 -> 57.333333 | P6: =F332 -> 58 | Q6: =I358 -> 12.733333 | R6: =F358 -> 61 | S6: =I380 -> 5.5 | T6: =F380 -> 85 | U6: =I399 -> 4.9333333 | V6: =F399 -> 56 | W6: =I414 -> 8.2166667 | X6: =F414 -> 4.8
A7: Cancer | B7: SSS | C7: ART | D7: 1600 | H7: 100 | I7: =(D7+E7)/H7 -> 16 | J7: Supreme Relic #12 | N7: Angel | O7: =I439 -> 60 | P7: =F439 -> 69 | Q7: =I467 -> 10.366667 | R7: =F467 -> 100 | S7: =I487 -> 5.6333333 | T7: =F487 -> 60 | U7: =I507 -> 5.0666667 | V7: =F507 -> 66 | W7: =I522 -> 6.2833333 | X7: =F522 -> 4.8
A8: Pisces | B8: SSS | C8: FAME | D8: 1600 | H8: 100 | I8: =(D8+E8)/H8 -> 16 | J8: Supreme Relic #20 | N8: Mutant | O8: =I546 -> 45 | P8: =F546 -> 58 | Q8: =I572 -> 8.8666667 | R8: =F572 -> 81 | S8: =I590 -> 4 | T8: =F590 -> 49 | U8: =I610 -> 3.2 | V8: =F610 -> 69 | W8: =I624 -> 5.2166667 | X8: =F624 -> 4.8
A9: Scorpio | B9: SSS | C9: CIV | D9: 1600 | H9: 100 | I9: =(D9+E9)/H9 -> 16 | J9: Supreme Relic #16 | N9: Mecha | O9: =I649 -> 75.666667 | P9: =F649 -> 58 | Q9: =I675 -> 16.766667 | R9: =F675 -> 60 | S9: =I697 -> 7.8 | T9: =F697 -> 84 | U9: =I715 -> 2.9333333 | V9: =F610 -> 69 | W9: =I733 -> 6.8833333 | X9: =F733 -> 4.8
A10: Ludovisi Ares | B10: SSS | C10: FTH | D10: 900 | H10: 60 | I10: =(D10+E10)/H10 -> 15 | J10: Star Chart Shop | N10: Dragon | O10: =I762 -> 41.333333 | P10: =F762 -> 60 | Q10: =I792 -> 12.6 | R10: =F792 -> 61 | S10: =I819 -> 7.9666667 | T10: =F819 -> 84 | U10: =I842 -> 7.3333333 | V10: =F842 -> 51 | W10: =I867 -> 7.8833333 | X10: =F867 -> 4.8
A11: Scales of Astraea | B11: SSS | C11: FTH | D11: 900 | H11: 60 | I11: =(D11+E11)/H11 -> 15 | J11: Star Chart Shop
A12: Trojan Horse | B12: SSS | C12: FAME | D12: 900 | H12: 60 | I12: =(D12+E12)/H12 -> 15 | J12: Lottery Machine #1 (0.09%), Wishing (0.09%), Grandmaster Scrolls (0.81%), Relic Forge (120 Relic RF)
A13: Ebers Papyrus | B13: SSS | C13: TECH | F13: 2.4 | G13: 2 | J13: Wish Box Album Relic #2
A14: Ink Chrysanths | B14: SSS | C14: ART | F14: 2.4 | G14: 2 | J14: Lottery Machine #2 (0.11%)
A15: La Marseillaise | B15: SSS | C15: ART | F15: 2.4 | G15: 2 | J15: Star Chart Shop
A16: Discobolus | B16: SSS | C16: ART | F16: 2.4 | J16: Lottery Machine #2 (?%)
A17: Orphic Egg | B17: SSS | C17: FTH | F17: 2.4 | J17: Lottery Machine #2 (0.12%), Relic Forge (120 RF)
A19: Resonance: Orange | D19: 630 | H19: 60 | I19: =(D19+E19)/H19 -> 10.5
A20: Shahnameh | B20: SSS | C20: CIV | J20: Lottery Machine #2 (0.12%)
A21: The Art of War | B21: SSS | C21: CIV | J21: Wish Box, Lottery Machine #1 (0.09%), Wishing (0.08%), Grandmaster Scrolls (0.81%), Relic Forge (120 Relic RF)
A22: Resonance: Orange | D22: 630 | H22: 60 | I22: =(D22+E22)/H22 -> 10.5
A23: Smug's Chalice | B23: SS | C23: FAME | J23: T7.5 Dragon Gene Research
A24: Imperial Jade | B24: S | C24: FAME | J24: Fragment Crafting (20.7%), Lottery Machine #1 (0.81%), Wishing (0.75%), Cathay Treasure Maps (5%), Relic Forge (90 Relic RF)
A25: Resonance: Purple | D25: 240 | H25: 30 | I25: =(D25+E25)/H25 -> 8
A26: Prehistoric Fossil | B26: AAA | C26: CIV | J26: Fragment Crafting (1.5%), Lottery Machine #1 (0.03%), Wishing (0.14%), Time Chest (1.5%), Relic Forge (80 Relic RF)
A27: Koryeon Sutra | B27: AAA | C27: CIV | J27: Fragment Crafting (1.5%), Lottery Machine #1 (0.03%), Wishing (0.14%), Koryeon Treasure Maps (10%), Relic Forge (80 Relic RF)
A28: Resonance: Blue | D28: 60 | H28: 10 | I28: =(D28+E28)/H28 -> 6
A29: Matsushima Pot | B29: Blue | C29: CIV | J29: Lottery Machine #2 (0.07%)
A30: Pompeii | B30: Blue | C30: ART | J30: Lottery Machine #2 (0.03%)
A31: The Moon and Sixpence | B31: Blue | C31: CIV | J31: Lottery Machine #2 (0.03%)
A32: Resonance: Orange | F32: 1.8
A33: Grimmy Award | B33: SS | C33: FAME | J33: Lottery Machine #2 (0.35%)
A34: Mysterious Relic | B34: SSS | J34: Unknown
A35: Mysterious Relic | B35: SSS | J35: Unknown
A36: Species Plantarum | B36: SSS | C36: TECH | J36: Star Chart Shop
A37: TOTAL HP | F37: =sum(F3:G36) -> 19.8 | I37: =sum(I3:I36) -> 219.33333
A40: ATK | B40: Rarity | C40: Type | D40: Base | E40: Awakening Base | F40: Percentage | G40: Awakening Percentage | H40: Per Minion | I40: Per Minion Boost | J40: Source
A41: EPR Paradox | B41: SSS | C41: TECH | D41: 120 | E41: 100 | H41: 60 | I41: =(D41+E41)/H41 -> 3.6666667 | J41: Wish Box Relic #8
A42: Infin. Improb. Eng. | B42: SSS | C42: TECH | D42: 120 | E42: 100 | H42: 60 | I42: =(D42+E42)/H42 -> 3.6666667 | J42: Daily Pack Relic #51
A43: Capricorn | B43: SSS | C43: TECH | D43: 160 | H43: 100 | I43: =(D43+E43)/H43 -> 1.6 | J43: Supreme Relic #18
A44: Virgo | B44: SSS | C44: FTH | D44: 160 | H44: 100 | I44: =(D44+E44)/H44 -> 1.6 | J44: Supreme Relic #14
A45: Taurus | B45: SSS | C45: ART | D45: 160 | H45: 100 | I45: =(D45+E45)/H45 -> 1.6 | J45: Supreme Relic #10
A46: Dead Sea Scrolls | B46: SSS | C46: CIV | D46: 90 | H46: 60 | I46: =(D46+E46)/H46 -> 1.5 | J46: Daily Pack Relic #13
A47: Gutenberg Press | B47: SSS | C47: CIV | D47: 90 | H47: 60 | I47: =(D47+E47)/H47 -> 1.5 | J47: Daily Pack Relic #9
A48: Modern Times | B48: SSS | C48: FAME | D48: 90 | H48: 60 | I48: =(D48+E48)/H48 -> 1.5 | J48: Badge Shop
A49: King's Gayageum | B49: SSS | C49: ART | D49: 90 | H49: 60 | I49: =(D49+E49)/H49 -> 1.5 | J49: Daily Pack Relic #7
A50: Terracotta Warrior | B50: SSS | C50: FAME | D50: 90 | H50: 60 | I50: =(D50+E50)/H50 -> 1.5 | J50: Lottery Machine #2 (0.12%), Relic Forge (120 RF)
A51: Trojan Horse | B51: SSS | C51: FAME | D51: 90 | H51: 60 | I51: =(D51+E51)/H51 -> 1.5 | J51: Lottery Machine #1 (0.09%), Wishing (0.09%), Grandmaster Scrolls (0.81%), Relic Forge (120 Relic RF)
A52: Scales of Astraea | B52: SSS | C52: FTH | D52: 90 | H52: 60 | I52: =(D52+E52)/H52 -> 1.5 | J52: Star Chart Shop
A53: Ludovisi Ares | B53: SSS | C53: FTH | D53: 90 | F53: 2.4 | G53: 2 | H53: 60 | I53: =(D53+E53)/H53 -> 1.5 | J53: Star Chart Shop
A54: War and Peace | B54: SSS | C54: FTH | F54: 3.6 | J54: Daily Silver Pack Relic #5
A55: Olympic Torch | B55: SSS | C55: FAME | F55: 2.4 | J55: Wish Box Relic #3
A56: Beowulf | B56: SSS | C56: CIV | F56: 2.4 | J56: Lottery Machine #2 (0.12%)
A58: Resonance: Orange | D58: 63 | H58: 60 | I58: =(D58+E58)/H58 -> 1.05
A59: Pillars of Creation | B59: SSS | C59: FAME | J59: Lottery Machine #2 (0.12%)
A60: Mysterious Relic | B60: SSS | J60: Unknown
A61: Resonance: Orange | D61: 63 | H61: 60 | I61: =(D61+E61)/H61 -> 1.05
A62: Energy Missile | B62: SSS | C62: TECH | J62: Lucky Box Reward Batch no. 1-7
A63: Parker Solar Probe | B63: SSS | C63: TECH | J63: Indigent Nobleman (810K B-tads), Lottery Machine #2 (0.11%)
A64: Resonance: Orange | D64: 63 | H64: 60 | I64: =(D64+E64)/H64 -> 1.05
A65: Bronze Shiva Statue | B65: SSS | C65: ART | J65: Daily Silver Pack Relic #3
A66: Creation of Adam | B66: SSS | C66: CIV | J66: Lottery Machine #1 (0.09%), Wishing (0.08%), Grandmaster Scrolls (0.77%)
A67: Resonance: Orange | D67: 63 | H67: 60 | I67: =(D67+E67)/H67 -> 1.05
A68: War and Peace | B68: SSS | C68: FTH | J68: Daily Silver Pack Relic #5
A69: 1001 Nights | B69: SSS | C69: CIV | J69: Wish Box, Lottery Machine #1 (0.09%), Wishing (0.08%), Bharata Treasure Maps(%), Grandmaster Scrolls (0.81%), Relic Forge (120 Relic RF)
A70: Resonance: Orange | D70: 63 | H70: 60 | I70: =(D70+E70)/H70 -> 1.05
A71: The Augustus Statue | B71: SSS | C71: CIV | J71: Lucky Stars Reward
A72: Alexander the Great | B72: SSS | C72: ART | J72: Lucky Stars Reward
A73: Resonance: Purple | D73: 24 | H73: 30 | I73: =(D73+E73)/H73 -> 0.8
A74: Turing Machine | B74: AA | C74: TECH | J74: Fragment Crafting (3.9%), Lottery Machine #1 (0.08%), Wishing (0.36%), Tool Chest (1.5%), Expert Scrolls (0.95%)
A75: Tree of Life | B75: AAA | C75: FTH | J75: Fragment Crafting (1.5%), Wishing (0.03%), Lottery Machine #1 (0.14%), Fungus chest (1.5%), Relic Forge (80 Relic RF), Home Value Pack II ($4.99)
A76: Resonance: Purple | D76: 24 | H76: 30 | I76: =(D76+E76)/H76 -> 0.8
A77: Figaro Marriage | B77: AAA | C77: ART | J77: Fragment Crafting (1.6%), Lottery Machine #1 (0.03%), Wishing (0.14%), Relic Forge (80 Relic RF)
A78: Mermaid Statue | B78: AAA | C78: ART | J78: Fragment Crafting (1.6%), Lottery Machine #1 (0.03%), Wishing (0.14%), Relic Forge (80 Relic RF)
A79: Resonance: Blue | D79: 8 | H79: 10 | I79: =(D79+E79)/H79 -> 0.8
A80: Statue of Gudea | B80: Blue | C80: ART | J80: Lottery Machine #2 (0.03%)
A81: Diesel Engine | B81: Blue | C81: FAME | J81: Lottery Machine #2 (0.03%)
A82: Warren Cup | B82: Blue | C82: FTH | J82: Lottery Machine #2 (0.07%)
A83: Orichalcum | B83: Blue | C83: FTH | J83: Lottery Machine #2 (0.07%)
A84: Crookes Tube | B84: Blue | C84: TECH | J84: Lottery Machine #2 (0.03%)
A85: Resonance: Orange | F85: 2
A86: The Prince | B86: SSS | C86: FAME | J86: Lottery Machine #2 (0.12%)
A87: Beowulf | B87: SSS | C87: CIV | J87: Lottery Machine #2 (0.12%)
A88: Enuma Elish | B88: SSS | C88: FTH | J88: Lottery Machine #2 (0.12%), Indigent Nobleman (810K B-tads)
A89: Oxus Treasure | B89: SSS | C89: ART | J89: Lottery Machine #2 (0.12%), Relic Forge (120 RF)
A90: Jiuzhang | B90: SSS | C90: TECH | J90: Lottery Machine #2 (0.12%)
A91: TOTAL ATK | F91: =sum(F41:G90) -> 14.8 | I91: =sum(I41:I90) -> 31.783333
A94: RUSH | B94: Rarity | C94: Type | D94: Base | E94: Awakening Base | F94: Percentage | G94: Awakening Percentage | H94: Per Minion | I94: Per Minion Boost | J94: Source
A95: EPR Paradox | B95: SSS | C95: TECH | D95: 120 | H95: 60 | I95: =(D95+E95)/H95 -> 2 | J95: Wish Box Relic #8
A96: Cancer | B96: SSS | C96: ART | D96: 160 | H96: 100 | I96: =(D96+E96)/H96 -> 1.6 | J96: Supreme Relic #12
A97: Pisces | B97: SSS | C97: FAME | D97: 160 | H97: 100 | I97: =(D97+E97)/H97 -> 1.6 | J97: Supreme Relic #20
A98: Scorpio | B98: SSS | C98: CIV | D98: 160 | H98: 100 | I98: =(D98+E98)/H98 -> 1.6 | J98: Supreme Relic #16
A99: Maya Mural | B99: SSS | C99: CIV | D99: 90 | H99: 60 | I99: =(D99+E99)/H99 -> 1.5 | J99: Star Chart Shop
A100: Napoleonic Code | B100: SSS | C100: FAME | D100: 90 | H100: 60 | I100: =(D100+E100)/H100 -> 1.5 | J100: Daily Pack Relic #11
A101: Head of Bhairava | B101: SSS | C101: FTH | D101: 90 | H101: 60 | I101: =(D101+E101)/H101 -> 1.5 | J101: Daily Pack Relic #17
A102: King's Gayageum | B102: SSS | C102: ART | D102: 90 | H102: 60 | I102: =(D102+E102)/H102 -> 1.5 | J102: Daily Pack Relic #7
A103: Terracotta Warrior | B103: SSS | C103: FAME | D103: 90 | H103: 60 | I103: =(D103+E103)/H103 -> 1.5 | J103: Lottery Machine #2 (0.12%), Relic Forge (120 RF)
A104: War and Peace | B104: SSS | C104: FTH | F104: 3.6 | J104: Daily Silver Pack Relic #5
A105: Hugo Award | B105: SSS | C105: FAME | F105: 2.4 | J105: Traveler's Pack Relic #4
A106: Lawrence's Cyclotron | B106: SSS | C106: TECH | F106: 2.4 | J106: Lottery Machine #2 (0.12%)
...

Sheet Leadership
A1: BASE | B1: (Credit FunFreddyBon)
A2: Base Leadership | D2: 10 | F2: Starter leadership
A3: MAX BASE LEADERSHIP | D3: =SUM(D2) -> 10
A6: INDIVIDUAL RELICS
A7: Pisces | B7: SSS | C7: FAME | D7: 20 | E7: 20 | F7: Supreme Relic #20
A8: Bill of Rights | B8: SSS | C8: FAME | D8: 15 | E8: 10 | F8: Daily Silver Pack #8
A9: Apollo Program | B9: SSS | C9: FAME | D9: 15 | E9: 10 | F9: Daily Silver Pack #11
A10: Trojan Horse | B10: SSS | C10: FAME | D10: 12 | E10: 5 | F10: Lottery Machine No.1 (0.09%), Alchemy Furnace (0.08%), Grandmaster Scrolls (0.75%), Relic Forge (120)
A11: Terracotta Warrior | B11: SSS | C11: FAME | D11: 12 | E11: 5 | F11: Lottery Machine No.2 (0.11%), Relic Forge 2 (120)
A12: The Prince | B12: SSS | C12: FAME | D12: 12 | E12: 5 | F12: Lottery Machine No.2 (0.11%)
A13: Nightingale Medal | B13: SSS | C13: FAME | D13: 12 | E13: 5 | F13: Lottery Machine No.2 (0.11%)
A14: Cross of Will | B14: SSS | C14: FAME | D14: 12 | E14: 5 | F14: Secret Mission (Bird)
A15: Napoleonic Code | B15: SSS | C15: FAME | D15: 12 | E15: 5 | F15: Daily Pack #11
A16: Hugo Award | B16: SSS | C16: FAME | D16: 12 | E16: 5 | F16: Travelers Pack #4
A17: Modern Times | B17: SSS | C17: FAME | D17: 12 | E17: 5 | F17: Badge Shop #4
A18: Bust of Hammurabi | B18: SSS | C18: FAME | D18: 12 | E18: 5 | F18: Lottery Machine No.3 (?%)
A19: Convention on the Rights of the Child | B19: SSS | C19: FAME | D19: 12 | F19: Lottery Machine No.2 (?%)
A20: Woman at Her Toilette | B20: SSS | C20: ART | D20: 20 | E20: 20 | F20: Minion Skin Lottery
A21: Golden Chan-hee | B21: SSS | C21: ART | D21: 15 | E21: 10 | F21: 4th Anniversary Event, Badge Shop (1000 medals) starting 5th year of launch
A22: Seated Voltaire | B22: SSS | C22: ART | D22: 12 | E22: 5 | F22: Wish Relic #1
A23: Capitoline Wolf | B23: SSS | C23: ART | D23: 12 | E23: 5 | F23: Lottery Machine No.2(0.11%)
A24: Woman with a Veil | B24: SSS | C24: ART | D24: 12 | E24: 5 | F24: Lottery Machine No.3 (?%)
A25: Han Hee-Jae's Night Banquet | B25: SSS | C25: ART | D25: 12 | E25: 5 | F25: Lottery Machine No.3 (?%)
A26: Apollo & Daphne | B26: SSS | C26: ART | D26: 12 | E26: 5 | F26: Daily Pack #27
A27: Arnolfini Portrait | B27: SSS | C27: ART | D27: 12 | E27: 5 | F27: Unknown
A28: Grace of Divine Dragon | B28: SSS | C28: ART | D28: 12 | E28: 5 | F28: Unknown
A29: Aurelius on Horse | B29: SSS | C29: ART | D29: 12 | F29: Unknown
A30: Laocoon | B30: SSS | C30: ART | D30: 12 | F30: Lottery Machine No.3 (?%)
A31: The Bronze Age | B31: SSS | C31: ART | D31: 12 | F31: Daily Pack #31
A32: Water Lilies | B32: SSS | C32: ART | D32: 12 | F32: Travelers Relic #9
A33: The Yellow Christ | B33: SSS | C33: ART | D33: 12 | F33: Travelers Pack #?
A34: Tyet | B34: SSS | C34: FTH | D34: 15 | E34: 10 | F34: Unknown
A35: Golden Snail | B35: SSS | C35: FTH | D35: 15 | E35: 10 | F35: 1st Anniversary Event, Badge Shop (1000 medals) starting 2nd year of launch
A36: The Silver Key | B36: SSS | C36: FTH | D36: 12 | E36: 5 | F36: Lottery Machine No.2 (0.11%), Rift Treasure Maps (0.01%)
A37: Holy Grail | B37: SSS | C37: FTH | D37: 12 | E37: 5 | F37: Lottery Machine No.2 (0.11%)
A38: Colossus of Rhodes | B38: SSS | C38: FTH | D38: 12 | E38: 5 | F38: Badge Shop
A39: Emerald Tablet | B39: SSS | C39: FTH | D39: 12 | E39: 5 | F39: Daily Pack #24
A40: Jerusalem Walls | B40: SSS | C40: FTH | D40: 12 | E40: 5 | F40: Lottery Machine No.3 (?%)
A41: Ra's Solar Barque | B41: SSS | C41: FTH | D41: 12 | E41: 5 | F41: Unknown
A42: Atenism | B42: SSS | C42: FTH | D42: 12 | E42: 5 | F42: Unknown
A43: Hetu Luoshu | B43: SSS | C43: FTH | D43: 12 | E43: 5 | F43: Unknown
A44: Primavera | B44: SSS | C44: FTH | D44: 12 | E44: 5 | F44: Lottery Machine No.3 (?%)
A45: Washington Portrait | B45: SSS | C45: FTH | D45: 12 | F45: Unknown
A46: Volsunga Saga | B46: SSS | C46: CIV | D46: 20 | E46: 20 | F46: Daily Golden Pack #6
A47: War and Peace | B47: SSS | C47: CIV | D47: 15 | E47: 10 | F47: Daily Silver Pack #5
A48: Golden Monkey | B48: SSS | C48: CIV | D48: 15 | E48: 10 | F48: 3rd Anniversary Event, Badge Shop (1000 medals) starting 4th year of launch
A49: Gutenberg's Press | B49: SSS | C49: CIV | D49: 12 | E49: 5 | F49: Daily Pack #9
A50: Beowulf | B50: SSS | C50: CIV | D50: 12 | E50: 5 | F50: Lottery Machine No.2 (0.11%)
A51: Cyrus Cylinder | B51: SSS | C51: CIV | D51: 12 | E51: 5 | F51: Lottery Machine No.2 (0.11%)
A52: Fenian Legends | B52: SSS | C52: CIV | D52: 12 | E52: 5 | F52: Daily Pack #34
A53: Anna Karenina | B53: SSS | C53: CIV | D53: 12 | E53: 5 | F53: Unknown
A54: The Poetics Edda | B54: SSS | C54: CIV | D54: 12 | E54: 5 | F54: Lottery Machine No.3 (?%)
A55: Copper Galloping Horse | B55: SSS | C55: CIV | D55: 12 | F55: Lottery Machine No.3 (?%)
A56: Brave New World | B56: SSS | C56: CIV | D56: 12 | F56: Daily Pack #16
A57: The Ultimate Manual | B57: SSS | C57: CIV | E57: 5 | F57: Lottery Machine No.3 Unlock Reward
A58: Higgs Boson | B58: SSS | C58: TECH | D58: 20 | E58: 20 | F58: Daily Gold Pack #3
A59: Gold-plated Bird | B59: SSS | C59: TECH | D59: 15 | E59: 10 | F59: 2nd Anniversary Event, Badge Shop (1000 medals) starting 3rd year of launch
A60: Black Body | B60: SSS | C60: TECH | D60: 12 | E60: 5 | F60: Lottery Machine No.2(0.11%)
A61: Jiuzhang | B61: SSS | C61: TECH | D61: 12 | E61: 5 | F61: Lottery Machine No.2(0.11%)
A62: Energy Missile | B62: SSS | C62: TECH | D62: 12 | E62: 5 | F62: Lucky Clover Vendor Reward (batch 1-7)
A63: Species Plantarum | B63: SSS | C63: TECH | D63: 12 | E63: 5 | F63: Star Chart Shop Maneater Pack (2000 star tickets)
A64: Mathematical Principles of Natural Philosophy | B64: SSS | C64: TECH | D64: 12 | E64: 5 | F64: Daily Pack #38
A65: Philosophie Zoologique | B65: SSS | C65: TECH | D65: 12 | E65: 5 | F65: Badge Shop
A66: Avogadro's Law | B66: SSS | C66: TECH | D66: 12 | E66: 5 | F66: Travelers Relic #5
A67: Webb Space Telescope | B67: SSS | C67: TECH | D67: 12 | E67: 5 | F67: Lottery Machine No.3 (?%)
A68: Antimatter Thruster | B68: SSS | C68: TECH | D68: 12 | E68: 5 | F68: Lottery Machine No.3 (?%)
A69: General Guide to Governance | B69: SSS | D69: 12 | F69: Wish Box Album #5
A70: Alexander's Anabasis | B70: Green | C70: CIV | D70: 15 | F70: Effect activates after conquering Bharata; Obtained from Hellas Exploration
A71: Certificate of Courage | B71: Green | C71: FAME | D71: 3 | F71: Cross of Will Mirage Reward
A72: Dark Lord's Dairy | B72: Green | C72: CIV | D72: 3 | F72: Hellenic Domain
A73: Father's Photo | B73: Green | C73: CIV | D73: 3 | F73: Laser Pig with Incense (10 shots)
A74: The Astrology | B74: Green | C74: CIV | D74: 3 | F74: Star Chart Shop Solo Relic #3 (1000 star tickets)
A75: Effective Manager | B75: Green | C75: CIV | D75: 3 | F75: Hatching Room Admin
A76: MAX INDIVIDUAL RELICS | D76: =SUM(D10:E75) -> 1105
A78: PARTNER
A79: Athena | D79: 30 | F79: Max LV = 30; Per level: +1 leadership
A81: TACTICAL LOGS
A82: Wildhammer | B82: Demon | C82: Other | D82: 2 | F82: Sim Shop Special Tactical Log #1
A83: Chief General Witte | B83: Dragon | C83: Dung Beetle | D83: 3 | F83: Unknown Log (0.03%), Precious Log (0.86%)
A84: Sergeant Jurgen | B84: Demon | C84: Dung Beetle | D84: 3 | F84: Unknown Log (0.03%), Precious Log (0.86%)
A85: Logistics Officer Uman | B85: Mecha | C85: Dung Beetle | D85: 2 | F85: Unknown Log (0.05%), Precious Log (1.71%)
A86: Military Scientist | B86: Demon | C86: Dung Beetle | D86: 2 | F86: Unknown Log (0.05%), Precious Log (1.71%)
A87: Senator Marius | B87: Zombie | C87: Dung Beetle | D87: 2 | F87: Unknown Log (0.05%), Precious Log (1.71%)
A88: Priest School Director | B88: Zombie | C88: Dung Beetle | D88: 2 | F88: Unknown Log (0.05%), Precious Log (1.71%)
A89: Blade SWAT Team | B89: Dragon | C89: Dung Beetle | D89: 2 | F89: Unknown Log (0.05%), Precious Log (1.71%)
A90: Chief's Guard | B90: Angel | C90: Dung Beetle | D90: 2 | F90: Unknown Log (0.05%), Precious Log (1.71%)
A91: Marshal Halder | B91: Angel | C91: Dung Beetle | D91: 2 | F91: Unknown Log (0.05%), Precious Log (1.71%)
A92: Engineer CDR Reinhardt | B92: Mutant | C92: Dung Beetle | D92: 2 | F92: Unknown Log (0.05%), Precious Log (1.71%)
A93: Intel. Director Sorge | B93: Mutant | C93: Dung Beetle | D93: 2 | F93: Unknown Log (0.05%), Precious Log (1.71%)
... A149: Monkey King | B149: Other | C149: Other | D149: 3 | F149: Xmas Tree Bonus 2024 (1230 Draws)
A150: MAX TACTICAL LOGS | D150: =sum(D82:D144) -> 128
A153: ANOMALY RECORDS
A154: X-4 | D154: 10 | F154: Anomaly Record #4
A155: D-9 | D155: 10 | F155: Anomaly Record #9
A156: U-13 | D156: 10 | F156: Anomaly Record #13
A157: H-19 | D157: 10 | F157: Anomaly Record #19
A158: N-23 | D158: 10 | F158: Anomaly Record #23
A159: K-29 | D159: 10 | F159: Anomaly Record #29
A160: Z-33 | D160: 10 | F160: Anomaly Record #33
A161: Q-39 | D161: 10 | F161: Anomaly Record #39
...

Sheet Tadpole Pond
A1: Name | B1: Rarity | C1: Type | D1: Base Output | E1: Awakening Output | F1: Base Cap | G1: Awakening Cap | H1: W-tad Generation | I1: Awakening W-tad Gen | J1: AFFECT Boost | K1: Source
A2: INDIVIDUAL RELICS
A3: Faust | B3: SSS | C3: CIV | D3: 24 | E3: 20 | H3: 24 | K3: Wish Box, Lottery Machine #1 0.09%), Wishing (0.08%), Grandmaster Scrolls (0.81%), Relic Forge (120 Relic RF)
A4: Golden Wheat | B4: SSS | C4: ART | D4: 24 | E4: 20 | K4: Wish Pack, Lottery Machine #1 (0.09%), Wishing (0.08%), Yamato Treasure Maps (0.01%), Grandmaster Scrolls (0.81%), Relic Forge (120 Relic RF)
A5: King Dangun Statue | B5: S | C5: FTH | D5: 20 | E5: 20 | K5: Fragment Crafting (15.1%), Lottery Machine #1 (0.81%), Wishing (0.81%), Koryeo Treasure Map (5%), Relic Forge (90 Relic RF), Museum Value Pack I ($14.99)
A6: Sunflowers | B6: SS | C6: ART | D6: 22 | K6: Lottery Machine #1 (0.12%), Wishing (0.1%), Fungus Chest (1%), Grandmaster Scrolls (1%), Relic Forge (100 Relic RF)
A7: The Song of Roland | B7: SS | C7: CIV | F7: 22 | G7: 20 | K7: Fragment Crafting (5.5%), Lottery Machine #1 (0.24%), Wishing (0.2%), Master Scroll (1.9%), Grandmaster Scroll (2.1%), CIV Master Scroll (10.2%)
A8: Haulers on Volga | B8: AAA | C8: ART | H8: 18 | I8: 14 | K8: Fragment Crafting (1.6%), Lottery Machine #1 (0.03%), Wishing (0.14%), Relic Forge (Relic RF 80), Indigent Nobleman (120K B-tads)
A9: Crystal Piano | B9: AAA | C9: CIV | D9: 18 | E9: 14 | F9: 18 | K9: Fragment Crafting (1.5%), Lottery Machine #1 (0.03%), Wishing (0.14%), Relic Forge (80 Relic RF), Indigent Nobleman (120K B-tads)
A10: Peacock Throne | B10: AAA | C10: ART | D10: 5 | E10: 5 | K10: Supreme Relic
A11: Universe Bowl | B11: Blue | C11: ART | F11: 10 | G11: 10 | K11: Lottery Machine #1 (0.07%), Wishing (3%), Fungus Chest (2%), Trainee Scrolls (1%)
A12: Rainbow Tadpole | B12: Green | C12: FTH | H12: 6 | K12: Tadpole pond after acquiring alchemy furnace
A13: Gold Fishing Rod | B13: Green | C13: FAME | H13: 6 | K13: Defeat Assassin Eve (Racoon Storyline)
A14: B-Tadpole XL | B14: Green | C14: ART | D14: 6 | K14: Intercept Hitman No.16
A15: Electric Fishing Net | B15: Green | C15: TECH | F15: 6 | K15: Bought from the Salesman
A16: MAX INDIVIDUAL RELICS | D16: =SUM(D3:E15) -> 198 | F16: =SUM(F3:G15) -> 86 | H16: =SUM(H3:I15) -> 68
A18: PARTNER
A19: Kim Chi-yum | D19: 9 | K19: lv30
A21: ORGAN
A22: Warp Horn | D22: 10 | F22: 10 | K22: lv20
A23: Alveolus of Gaia | D23: 20 | F23: 20 | K23: lv40
A24: MAX ORGAN | D24: =sum(D22:D23) -> 30 | F24: =sum(F22:F23) -> 30 | H24: =sum(H22:H23) -> 0
A26: BUBBLE FRAMES
A27: Whale Power III | D27: 12 | K27: 5M W-tads Spent
A29: COLLECTORS TALENTS
A30: Tadpole Raising | D30: 25 | F30: 25 | K30: 10 Purple Talent Points
A32: ROBOTS
A33: Pure White Doc | D33: 3 | K33: Wormhole Refiner (0.03%)
A35: ROCKET UPGRADES
A36: Eternal Hall | D36: 10 | F36: 10 | K36: Lv5
A38: AVATARS
A39: Mirage Avatar I Bonus | D39: 20 | F39: 40
A41: STAMPS
A42: Golden Wheat | B42: SSS | C42: ART | D42: 30 | H42: 30 | J42: 15 | K42: Wish Pack, Lottery Machine #1 (0.09%), Wishing (0.08%), Yamato Treasure Maps (0.01%), Grandmaster Scrolls (0.81%), Relic Forge (120 Relic RF)
A43: Alexander The Great | B43: SSS | C43: ART | D43: 30 | F43: 30 | J43: 15 | K43: Lucky Stars Event Reward
A44: Swan Lake | B44: SS | C44: ART | D44: 30 | J44: 15 | K44: Lottery Machine #1 (0.12%), Wishing (0.1%), Grandmaster Scrolls (1%), Relic Forge (100 Relic RF)
A45: Lotus Chalice | B45: SSS | C45: ART | D45: 30 | F45: 30 | H45: 30 | K45: Wish Pack, Lottery Machine #1 (0.09%), Wishing (0.08%), Kemetic Treasure Chests (0.01%), Grandmaster Scrolls (0.81%), Relic Forge (120 Relic RF)
A46: Ship in a Bottle | B46: SS | C46: ART | D46: 30 | H46: 30 | K46: Fragment Crafting (4%), Lottery Machine #1 (0.18%), Wishing (0.15%), Grandmaster Scrolls (1.6%)
A47: Parthenon Marbles | B47: SS | C47: ART | D47: 30 | K47: Hellas Costume Lottery Reward
A48: Sunflowers | B48: SS | C48: ART | H48: 30 | J48: 15 | K48: Lottery Machine #1 (0.12%), Wishing (0.1%), Fungus Chest (1%), Grandmaster Scrolls (1%), Relic Forge (100 Relic RF)
A49: The Last Supper | B49: S | C49: ART | D49: 30 | K49: Fragment Crafting (18.1%), Lottery Machine #1 (0.81%), Wishing (0.68%), Relic Forge (90 Relic RF)
A50: Mona Lisa | B50: S | C50: ART | J50: 15 | K50: Fragment Crafting (18.1%), Lottery Machine #1 (0.81%), Wishing (0.68%), Relic Forge (90 Relic RF)
A51: Golden Scarab | B51: S | C51: FTH | H51: 30 | K51: Fragment Crafting (15.1%), Lottery Machine #1 (0.81%), Wishing (0.53%), Kemetic Treasure Maps (5%), Master Scrolls (6.5%), FTH Master Scrolls (31.5%), Relic Forge (90 Relic RF)
A52: Tetromino | B52: S | C52: FAME | J52: 15 | K52: Fragment Crafting (20.7%), Lottery Machine #1 (0.81%), Wishing (0.75%), Master Scrolls (6.5%), FAME Master Scrolls (31.5%), Relic Forge (90 Relic RF)
A53: Boltzmann Brain | B53: S | C53: TECH | J53: 15 | K53: Fragment Crafting (17.8%), Lottery Machine #1 (0.81%), Wishing (0.65%), Master Scrolls (6.5%), TECH Master Scrolls (31.5%), Relic Forge (90 Relic RF)
A54: Buddha Finger Sarira | B54: SS | C54: FTH | F54: 30 | K54: Fragment Crafting (3.3%), Lottery Machine #1 (0.18%), Wishing (0.12%), Bharata Treasure Maps (%), Grandmaster Scrolls (1.6%)
A55: Cairo Declaration | B55: SS | C55: FAME | F55: 30 | K55: Fragment Crafting (4.6%), Lottery Machine #1 (0.18%), Wishing (0.17%), Grandmaster Scrolls (1.6%)
A56: Leaf of Yggdrassil | B56: S | C56: FAME | F56: 30 | K56: Fragment Crafting (20.7%), Lottery Machine #1 (0.81%), Wishing (0.75%), Super Treasure Map (15%), Master Scrolls (6.5%), FAME Master Scrolls (31.5%), Relic Forge (90 Relic RF)
A57: Hammurabi Code | B57: SS | C57: FAME | F57: 30 | K57: Fragment Crafting (4.6%), Lottery Machine #1 (0.18%), Wishing (0.17%), Demon God Chest (5%), Grandmaster Scrolls (1.6%)
A58: MAX POND STAMPS | D58: =D42+D43+D44 -> 90 | F58: =F42+F43+F44 -> 30 | H58: =H42+H43+H44 -> 30 | J58: =J42+J43+J44 -> 45
A60: RESONANCE
A61: BLUE
A62: Output | D62: 10
A63: Kilogram Prototype | B63: Blue | C63: TECH | K63: Lottery Machine #1 (0.03%), Wishing (1.1%), Fungus Chest (2%)
A64: Aztec Calendar | B64: Blue | C64: TECH | K64: Lottery Machine #1 (0.03%), Wishing (1.1%), Time Chest (2%)
A65: W-tad | H65: 12
A66: Bach Concerto | B66: Blue | C66: ART | K66: Lottery Machine #1 (0.03%), Wishing (1.2%), Club Chest (2%)
A67: Tetrabiblos | B67: Blue | C67: FTH | K67: Lottery Machine #1 (0.03%), Wishing (0.85%), Nebula Chest (2%), Peter Jr. Rent
A68: Persian Star Chart | B68: Blue | C68: TECH | K68: Lottery Machine #1 (0.36%), Wishing (13.2%), Novice Scrolls (5%), Nebula Chest (2%)
A69: PURPLE
A70: Output | D70: 12
A71: Hannibal's Cup | B71: AA | C71: FAME | K71: Fragment Crafting (3.9%), Lottery Machine #1 (0.08%), Wishing (0.35%), Expert Scrolls (0.95%)
A72: Rosetta Stone | B72: A | C72: FAME | K72: Fragment Crafting (31%), Lottery Machine#1 (0.66%), Wishing (2.8%), Kemetic Treasure Maps (10%), Expert Scrolls (7.6%)
A73: W-tad | H73: 12
A74: The Starry Night | B74: AA | C74: ART | K74: Fragment Crafting (3.9%), Lottery Machine #1 (0.08%), Wishing (0.36%), Expert Scrolls (0.95%), Nebula Chest (1.5%)
A75: Napoleon Painting | B75: AAA | C75: ART | K75: Fragment Crafting (1.6%), Lottery Machine #1 (0.03%), Wishing (0.14%), Relic Forge (Relic RF x80)
A76: ORANGE
A77: Output | D77: 16
A78: Agamemnon Mask | B78: SS | C78: ART | K78: Fragment Crafting (4%), Lottery Machine #1 (0.18%), Wishing (0.15%), Grandmaster Scrolls (1.6%)
A79: Morse's Telegraph | B79: SS | C79: TECH | K79: Fragment Crafting (5.2%), Lottery Machine #1 (0.24%), Wishing (0.19%), Tool Chest (1%), Master Scrolls (1.9%), Grandmaster Scrolls (2.1%), TECH Master Scrolls (9.2%)
A80: The Key of Solomon | B80: SS | C80: FTH | K80: T7.5 Demon Gene Research
A81: W-tad | H81: 14
A82: Aladdin Carpet | B82: SSS | C82: CIV | K82: Daily Silver Pack Relic #1
A83: Royal Celtic Harp | B83: SSS | C83: FTH | K83: Lottery Machine #1 (0.09%), Wishing (0.06%), Grandmaster Scrolls (0.76%)
A84: MAX RESONANCE | D84: =SUM(D61:D83) -> 38 | F84: =SUM(F61:F83) -> 0 | H84: =SUM(H61:H83) -> 38
A87: Total B-tad Output | B87: =D16+D19+D58+D84+D30+D24+D39+D27+D36+D33 -> 435
A88: Total B-tad Cap | B88: =F16+F19+F58+F84+F30+F24+F39+F36 -> 221
A89: Total W-tad Gen | B89: =H16+H58+H84+H19+H30+H39 -> 136

Sheet Fungus Farm
A1: Name | B1: Rarity | C1: Type | D1: Base Output | E1: Awakening Output | F1: Base Cap | G1: Awakening Cap | H1: Wonder Fungus | I1: Awakening Wonder Fungus | J1: AFFECT Boost | K1: Source
A2: INDIVIDUAL RELICS
A3: The Last Supper | B3: S | C3: ART | D3: 20 | E3: 20 | F3: 20 | K3: Fragment Crafting (18.1%), Lottery Machine #1 (0.81%), Wishing (0.68%), Relic Forge (90 Relic RF)
A4: Sunflowers | B4: SS | C4: ART | D4: 22 | E4: 20 | K4: Lottery Machine #1 (0.12%), Wishing (0.1%), Fungus Chest (1%), Grandmaster Scrolls (1%), Relic Forge (100 Relic RF)
A5: Golden Wheat | B5: SSS | C5: ART | D5: 24 | K5: Wish Pack, Lottery Machine #1 (0.09%), Wishing (0.08%), Yamato Treasure Maps (0.01%), Grandmaster Scrolls (0.81%), Relic Forge (120 Relic RF)
A6: Edict of Milan | B6: AAA | C6: FAME | H6: 18 | I6: 14 | K6: Fragment Crafting (1.6%), Lottery Machine #1 (0.03%), Wishing (0.14%), Relic Forge (80 Relic RF)
A7: The Goodbye Kiss | B7: AAA | C7: ART | H7: 9 | I7: 7 | K7: Lottery Box Relic #2
A8: Frigga's Wheel | B8: AAA | C8: FTH | D8: 14 | F8: 14 | G8: 14 | K8: Fragment Crafting (30.8%), Lottery Machine #1 (0.66%), Wishing (2.8%), Expert Scrolls (7.6%)
A9: Peacock Throne | B9: AAA | C9: ART | D9: 5 | E9: 5 | K9: Supreme Relic
A10: Leo's Plant | B10: Blue | C10: CIV | D10: 10 | E10: 10 | K10: Lottery Machine #1 (0.36%), Wishing (10.3%), Fungus Chest (2%), Trainee Scrolls (5%)
A11: Portland Vase | B11: Blue | C11: ART | F11: 10 | G11: 10 | K11: Lottery Machine #1 (0.03%), Wishing (1.2%), Fungus Chest (2%)
A12: Earthworm Codex | B12: Green | C12: FAME | H12: 6 | K12: Earth Worm Reactor (Species War Cabin) Reward
A13: Isle Turnip | B13: Green | C13: CIV | H13: 6 | K13: Racoon Storyline
A14: Mutant Fungus | B14: Green | C14: FTH | H14: 6 | K14: Buried in the Farm
A15: Shinkage Ryu: Shift | B15: Green | C15: TECH | D15: 6 | K15: Yamato Domain
A16: MAX INDIVIDUAL RELICS | D16: =sum(D3:E15) -> 156 | F16: =sum(F3:G15) -> 68 | H16: =sum(H3:I15) -> 66
A18: ORGAN
A19: Warp Horn | D19: 10 | F19: 10 | K19: lv20
A20: Alveolus of Gaia | D20: 20 | F20: 20 | K20: lv40
A21: MAX ORGAN | D21: =sum(D19:D20) -> 30 | F21: =sum(F19:F20) -> 30 | H21: =sum(H19:H20) -> 0
A23: BUBBLE FRAMES
A24: Whale Power III | D24: 12 | K24: 5M W-tads Spent
A26: COLLECTORS TALENTS
A27: Fungus Growth | D27: 25 | F27: 25 | K27: 10 Blue Talent Points
A29: ROCKET UPGRADES
A30: Eternal Hall | D30: 10 | F30: 10 | K30: Lv5
A32: AVATARS
A33: Mirage Avatar I Bonus | D33: 20 | F33: 40
A35: STAMPS
A36: 1001 Nights | B36: SSS | C36: CIV | D36: 30 | H36: 30 | J36: 15 | K36: Wish Pack, Lottery Machine #1 (0.09%), Wishing (0.08%), Bharata Treasure Maps(%), Grandmaster Scrolls (0.81%), Relic Forge (120 Relic RF)
A37: Creation of Adam | B37: SSS | C37: CIV | F37: 30 | H37: 30 | J37: 15 | K37: Lottery Machine #1 (0.09%), Wishing (0.08%), Grandmaster Scrolls (0.77%)
A38: Cyrus Cylinder | B38: SSS | C38: CIV | D38: 30 | F38: 30 | J38: 15 | K38: Lottery Machine #2 (?%)
A39: The Song of Roland | B39: SS | C39: CIV | D39: 30 | F39: 30 | K39: Fragment Crafting (5.5%), Lottery Machine #1 (0.24%), Wishing (0.2%), Master Scroll (1.9%), Grandmaster Scroll (2.1%), CIV Master Scroll (10.2%)
A40: Das Kapital | B40: SS | C40: CIV | D40: 30 | F40: 30 | K40: Lottery Machine #1 (0.12%), Wishing (0.1%), Britland Treasure Maps (5%), Grandmaster Scrolls (1%), Relic Forge (100 Relic RF), beat Mr. Raccoon in combat
A41: Plato's Republic | B41: SS | C41: CIV | H41: 30 | J41: 15 | K41: Lottery Machine #1 (0.12%), Wishing (0.1%), Grandmaster Scrolls (1%), Relic Forge (100 Relic RF), Home Value Pack III ($14.99)
A42: Pride & Prejudice | B42: S | C42: CIV | H42: 30 | K42: Lottery Machine #2 (1.59%)
A43: Julian Calendar | B43: SS | C43: CIV | F43: 30 | K43: Fragment Crafting (5.5%), Lottery Machine #1 (0.24%), Wishing (0.2%), Master Scrolls (1.9%), Grandmaster Scrolls (2.1%), CIV Master Scrolls (10.2%)
A44: Boat of St. Peter | B44: SS | C44: FTH | H44: 30 | K44: Fragment Crafting (4%), Lottery Machine #1 (0.18%), Wishing (0.15%), Grandmaster Scrolls (1.6%)
A45: Golden Scarab | B45: S | C45: FTH | H45: 30 | K45: Fragment Crafting (15.1%), Lottery Machine #1 (0.81%), Wishing (0.53%), Kemetic Treasure Maps (5%), Master Scrolls (6.5%), FTH Master Scrolls (31.5%), Relic Forge (90 Relic RF)
A46: Holy Loaves | B46: SS | C46: FTH | D46: 30 | K46: Lottery Machine #1 (0.12%), Wishing (0.08%), Evolution Chest (1%), Grandmaster Scrolls (1%), Relic Forge (100 Relic RF)
A47: The Last Supper | B47: S | C47: ART | J47: 15 | K47: Fragment Crafting (18.1%), Lottery Machine #1 (0.81%), Wishing (0.68%), Relic Forge (90 Relic RF)
A48: Leaf of Yggdrasil | B48: SS | C48: FAME | J48: 15 | K48: Fragment Crafting (20.7%), Lottery Machine #1 (0.81%), Wishing (0.75%), Super Treasure Map (15%), Master Scrolls (6.5%), FAME Master Scrolls (31.5%), Relic Forge (90 Relic RF)
A49: Forbidden Fruit | B49: SS | C49: FTH | J49: 15 | K49: Lottery Machine #1 (0.12%), Wishing (0.8%), Super Treasure Maps (5%), Grandmaster Scrolls (1%), Relic Forge (100 Relic RF)
A50: Swan Lake | B50: SS | C50: ART | J50: 15 | K50: Lottery Machine #1 (0.12%), Wishing (0.1%), Grandmaster Scrolls (1%), Relic Forge (100 Relic RF)
A51: The Key of Solomon | B51: SS | C51: FTH | F51: 30 | K51: T7.5 Demon Gene Research
A52: MAX FARM STAMPS | D52: =D36+D37+D38 -> 60 | F52: =F36+F37+F38 -> 60 | H52: =H36+H37+H38 -> 60 | J52: =J36+J37+J38 -> 45
A54: RESONANCE
A55: BLUE
A56: Output | D56: 14
A57: No. 1 Majesty | B57: Blue | C57: CIV | K57: Lottery Machine #1 (0.03%), Wishing (0.82%)
A58: Requiem | B58: Blue | C58: ART | K58: T2 Demon Gene Research
A59: Genesis | B59: Blue | C59: FTH | K59: Lottery Machine #1 (0.07%), Wishing (2.1%), Club Chest (2%), Trainee Scroll (1%)
A60: Klein Bottle | B60: Blue | C60: TECH | K60: Lottery Machine #1 (0.07%), Wishing (2.6%), Novice Scrolls (1%)
A61: Wonder Fungus | H61: 14
A62: Melcades' Prophecy | B62: Blue | C62: FTH | K62: Lottery Machine #1 (0.03%), Wishing (0.85%)
A63: Hillary's Pickaxe | B63: Blue | C63: CIV | K63: Lottery Machine #1 (0.07%), Wishing (2.1%), Trainee Scrolls (1%)
A64: Musketeer's Mask | B64: Blue | C64: CIV | K64: Lottery Machine #1 (0.36%), Wishing (10.3%), Trainee Scroll (5%)
A65: Universe Bowl | B65: Blue | C65: ART | K65: Lottery Machine #1 (0.07%), Wishing (3%), Fungus Chest (2%), Trainee Scrolls (1%)
A66: PURPLE
A67: Output | D67: 12
A68: Manneken Pis | B68: AAA | C68: ART | K68: Fragment Crafting (1.6%), Lottery Machine #1 (0.03%), Wishing (0.14%), Relic Forge (80 Relic RF)
A69: Boy with Goose | B69: A | C69: ART | K69: Fragment Crafting (31.2%), Lottery Machine #1 (0.66%), Wishing (2.8%), Expert Scrolls (7.6%)
A70: Wonder Fungus | H70: 12
A71: Gene Map | B71: AAA | C71: TECH | K71: Fragment Crafting (1.6%), Lottery Machine #1 (0.03%), Wishing (0.14%), Evolution Chest (1.5%), Relic Forge (80 Relic RF)
A72: Dolly Specimen | B72: A | C72: TECH | K72: Fragment Crafting (31.5%), Lottery Machine #1 (0.66%), Wishing (2.9%), Expert Scrolls (7.6%)
A73: ORANGE
A74: Output | D74: 14
A75: Ship in a Bottle | B75: SS | C75: ART | K75: Fragment Crafting (4%), Lottery Machine #1 (0.18%), Wishing (0.15%), Grandmaster Scrolls (1.6%)
A76: Boat of St. Peter | B76: SS | C76: FTH | K76: Fragment Crafting (4%), Lottery Machine #1 (0.18%), Wishing (0.15%), Grandmaster Scrolls (1.6%)
A77: Wonder Fungus | H77: 14
A78: Matrix System | B78: SS | C78: TECH | K78: T7.5 Mecha Gene Research
A79: Causality | B79: SS | C79: TECH | K79: Fragment Crafting (3.9%), Lottery Machine #1 (0.18%), Alchemy Furnace (0.14%), Grandmaster Scrolls (1.6%)
A80: MAX RESONANCE | D80: =sum(D55:D79) -> 40 | F80: =sum(F55:F79) -> 0 | H80: =sum(H55:H79) -> 40
A83: Total Food Output | B83: =D16+D27+D52+D80+D21+D33+D24+D30 -> 353
A84: Total Food Cap | B84: =F16+F27+F52+F80+F21+F33+F30 -> 233
A85: Total Wonder Fungus Gen | B85: =H16+H27+H52+H80+H33+H21 -> 166

Sheet Time Machine
A1: Name | B1: Rarity | C1: Type | D1: Base Output | E1: Awakening Output | F1: Base Cap | G1: Awakening Cap | H1: Time Chest | I1: Awakening Time Chest | J1: AFFECT Boost | K1: Source
A2: INDIVIDUAL RELICS
A3: Sputnik 1 | B3: SS | C3: TECH | D3: 22 | F3: 22 | H3: 22 | I3: 20 | K3: Fragment Crafting (3.9%), Lottery Machine #1 (0.18%), Wishing (0.14%), Club Chest (1%), Grandmaster Scrolls (1.6%)
A4: Artificial Black Hole | B4: SSS | C4: TECH | D4: 24 | E4: 20 | K4: Wish Box, Lottery Machine #1 (0.09%), Wishing (0.07%), Demon God Chest (0.1%), Grandmaster Scrolls (0.81%), Relic Forge (120 Relic RF), Nebula Chest (0.01%)
A5: Golden Wheat | B5: SSS | C5: ART | D5: 24 | K5: Wish Pack, Lottery Machine #1 (0.09%), Wishing (0.08%), Yamato Treasure Maps (0.01%), Grandmaster Scrolls (0.81%), Relic Forge (120 Relic RF)
A6: Morse's Telegraph | B6: SS | C6: TECH | D6: 22 | K6: Fragment Crafting (5.2%), Lottery Machine #1 (0.24%), Wishing (0.19%), Tool Chest (1%), Master Scrolls (1.9%), Grandmaster Scrolls (2.1%), TECH Master Scrolls (9.2%)
A7: Notre Dame Bell | B7: S | C7: CIV | F7: 20 | G7: 20 | K7: Fragment Crafting (18.8%), Lottery Machine #1 (0.81%), Wishing (0.69%), Relic Forge (90 Relic RF)
A8: Bell's Telephone | B8: AAA | C8: TECH | H8: 18 | I8: 14 | K8: Fragment Crafting (1.6%), Lottery Machine #1 (0.03%), Wishes (0.14%), Relic Forge (80 Relic RF)
A9: Kapa's Camera | B9: AAA | C9: CIV | D9: 18 | E9: 14 | F9: 18 | K9: Fragment Crafting (1.5%), Lottery Machine #1 (0.03%), Wishing (0.14%), Relic Forge (80 Relic RF)
A10: Yuan Calendar | B10: AAA | C10: TECH | H10: 16 | K10: Fragment Crafting (3.9%), Lottery Machine #1 (0.08%), Wishing (0.36%), Koryeon Treasure Maps (10%), Expert Scrolls (0.95%)
A11: Keyhole Satellite | B11: AAA | C11: TECH | E11: 15 | F11: 15 | K11: Fragment Crafting (1.6%), Lottery Machine #1 (0.03%), Wishing (0.14%), Relic Forge (80 Relic RF), Nebula Chest (1.5%)
A12: Peacock Throne | B12: AAA | C12: ART | D12: 5 | E12: 5 | K12: Supreme Relic
A13: Peacock Clock | B13: Blue | C13: ART | D13: 10 | E13: 10 | K13: Lottery Machine #1 (0.03%), Wishing (1.2%), Bharata Treasure Maps (%), Time Chest (2%)
A14: Cuckoo Clock | B14: Blue | C14: ART | F14: 10 | G14: 10 | K14: Lottery Machine #1 (0.07%), Wishing (3%), Time Chest (2%), Trainee Scrolls (1%)
A15: Sands of Time | B15: Green | C15: ART | H15: 6 | K15: Fissure Floor 1968
A16: Nuclear Fusion Battery | B16: Green | C16: TECH | D16: 6 | K16: Robot Guard
A17: Blower | B17: Green | C17: TECH | D17: 6 | K17: Defeat Pepper the Butcher
A18: MAX INDIVIDUAL RELICS | D18: =SUM(D4:E17) -> 179 | F18: =SUM(F4:G17) -> 93 | H18: =SUM(H4:I17) -> 54
A20: PARTNER
A21: Lee Gi-na | D21: 30 | K21: lv30
A23: COLLECTORS TALENTS
A24: Dimension Keeper | D24: 25 | F24: 25 | K24: 10 Orange Talent Points
A26: ROBOTS
A27: Hello Boxer | D27: 3 | K27: Wormhole Refiner (0.03%)
A29: INTEL
A30: Cathay | D30: 10
A32: BUBBLE FRAMES
A33: Whale Power III | D33: 12 | K33: 5M W-tads Spent
A35: ORGAN
A36: Alveolus of Gaia | D36: 20 | F36: 20 | K36: lv40
A37: Warp Horn | D37: 10 | F37: 10 | K37: lv20
A38: Universe Energy Cube | D38: 30 | K38: lv30
A39: MAX ORGAN | D39: =sum(D36:D38) -> 60 | F39: =sum(F36:F38) -> 30 | H39: =sum(H36:H38) -> 0
A41: ROCKET UPGRADES
A42: Eternal Hall | D42: 10 | F42: 10 | K42: Lv5
A44: AVATARS
A45: Mirage Avatar I Bonus | D45: 20 | F45: 40
A47: STAMPS
A48: Particle Collider | B48: SSS | C48: TECH | D48: 30 | H48: 30 | J48: 15 | K48: Wish Box, Lottery Machine #1 (0.09%), Wishing (0.07%), Tool Chest (0.01%), Grandmaster Scrolls (0.81%), Relic Forge (120 Relic RF)
A49: Quantum Radio | B49: SSS | C49: TECH | D49: 30 | F49: 30 | J49: 15 | K49: Super Species Chest (0.03%)
A50: Tokamak | B50: SS | C50: TECH | D50: 30 | J50: 15 | K50: Fragment Crafting (5.2%), Lottery Machine #1 (0.24%), Wishing (1.9%), Master Scrolls (1.9%), Grandmaster Scrolls (2.1%), TECH Master Scrolls (9.2%)
A51: Relativity Scripts | B51: SSS | C51: TECH | D51: 30 | F51: 30 | H51: 30 | K51: Wish Box, Lottery Machine #1 (0.09%), Wishing (0.07%), Time Chest (0.01%), Grandmaster Scrolls (0.81%), Relic Forge (120 Relic RF), Indigent Nobleman (810K B-tads)
A52: Matrix System | B52: SS | C52: TECH | D52: 30 | H52: 30 | K52: T7.5 Mecha Gene Research
A53: Sputnik 1 | B53: SS | C53: TECH | H53: 30 | K53: Fragment Crafting (3.9%), Lottery Machine #1 (0.18%), Wishing (0.14%), Club Chest (1%), Grandmaster Scrolls (1.6%)
A54: SkyWeb Hub | B54: SS | C54: TECH | F54: 30 | H54: 30 | K54: Koryeon Domain, Fragment Crafting (5.2%), Lottery Machine #1 (0.24%), Wishing (0.19%), Super Treasure Maps (5%), Master Scrolls (1.9%), Grandmaster Scrolls (2.1%), TECH Master Scrolls (9.2%)
A55: Edison's Kinetoscope | B55: S | C55: TECH | D55: 30 | K55: Ad Shop
A56: Babage Engine | B56: S | C56: TECH | J56: 15 | K56: Lottery Machine #1 (0.12%), Wishing (0.1%), Grandmaster Scrolls (1%), Relic Forge (100 Relic RF)
A57: Hubble Telescope | B57: S | C57: TECH | J57: 15 | K57: Fragment Crafting (17.8%), Lottery Machine #1 (0.80%), Wishing (0.65%), Super Treasure Maps (15%), Relic Forge (90 Relic RF)
A58: AMS | B58: SS | C58: TECH | H58: 30 | K58: Lottery Machine #2 (0.47%), Indigent Nobleman (570K B-tads)
A59: CRISPR | B59: S | C59: TECH | H59: 30 | K59: Lottery Machine #2 (1.59%)
A60: Morse's Telegraph | B60: SS | C60: TECH | F60: 30 | K60: Fragment Crafting (5.2%), Lottery Machine #1 (0.24%), Wishing (0.19%), Tool Chest (1%), Master Scrolls (1.9%), Grandmaster Scrolls (2.1%), TECH Master Scrolls (9.2%)
A61: Era Magazine Vol. 1 | B61: SS | C61: CIV | J61: 15 | K61: Lottery Machine #1 (0.12%), Wishing (0.1%), Ad Chest (1%), Grandmaster Scrolls (1%), Relic Forge (100 Relic RF)
A62: The School of Athens | B62: SS | C62: ART | J62: 15 | K62: Fragment Crafting (5.3%), Lottery Machine #1 (0.24%), Wishing (0.2%), Super Treasure Maps (5%), Master Scrolls (1.9%), Grandmaster Scrolls (2.1%), ART Master Scrolls (10.2%)
A63: Eye of Akamoddo | B63: SS | C63: FTH | J63: 15 | K63: Fragment Crafting (4.4%), Lottery Machine #1 (0.24%), Wishing (0.16%), Time Chest (1%), Master Scrolls (1.9%), Grandmaster Scrolls (2.1%), FTH Master Scrolls (9.2%)
A64: Ape's Footprint Fossil | B64: SS | C64: FAME | F64: 30 | K64: Super Species Chest (2.4%)
A65: Koh-i-Noor Diamond | B65: S | C65: ART | F65: 30 | K65: Fragment Crafting (18.1%), Lottery Machine #1 (0.81%), Wishing (0.68%), Master Scrolls (6.5%), ART Master Scrolls (34.7%), Relic Forge (90 Relic RF)
A66: Notre Dame Bell | B66: S | C66: CIV | F66: 30 | K66: Fragment Crafting (18.8%), Lottery Machine #1 (0.81%), Wishing (0.69%), Relic Forge (90 Relic RF)
A67: MAX MACHINE STAMPS | D67: =D50+D48+D49 -> 90 | F67: =F50+F48+F49 -> 30 | H67: =H50+H48+H49 -> 30 | J67: =J50+J48+J49 -> 45
A69: RESONANCE
A70: BLUE
A71: Output | D71: 18
A72: Star of David | B72: Blue | C72: FTH | K72: Angel Gene Research T2
A73: Benin Statue | B73: Blue | C73: ART | K73: Lottery Machine #1 (0.03%), Wishing (1.2%)
A74: Chronometer | B74: Blue | C74: TECH | K74: Lottery Machine #1 (0.03%), Wishing (1.1%), Tool Chest (2%)
A75: Sholes' Typewriter | B75: Blue | C75: CIV | K75: Lottery Machine #1 (0.03%), Wishing (0.82%)
A76: Churchill's Cigar | B76: Blue | C76: FAME | K76: Lottery Machine #1 (0.07%), Wishing (3.1%), Trainee Scrolls (1%)
A77: Traveler Manual | B77: Blue | C77: CIV | K77: Finish Traveler tasks (Tutorial)
A78: Time Chest | H78: 14
A79: Golden Fleece | B79: Blue | C79: FTH | K79: Lottery Machine #1 (0.03%), Wishing (0.85%)
A80: Bronze Bird | B80: Blue | C80: FAME | K80: Cathay Treasure Map (20%)
A81: Seismograph | B81: Blue | C81: TECH | K81: Lottery Machine #1 (0.07%), Wishing (2.1%), Novice Scroll (1%)
A82: Enigma Machine | B82: Blue | C82: TECH | K82: Lottery Machine #1 (0.03%), Wishing (1.1%)
A83: PURPLE
A84: Output | D84: 12
A85: Galileo's Ball | B85: AAA | C85: FAME | K85: Fragment Crafting (1.6%), Lottery Machine #1 (0.03%), Wishing (0.14%), Relic Forge (80 Relic RF)
A86: Armstrong's Footprint | B86: AA | C86: FAME | K86: Fragment Crafting (3.9%), Lottery Machine #1 (0.08%), Wishing (0.35%), Expert Scrolls (0.95%)
A87: Time Chest | H87: 12
A88: Prince's Rose | B88: AA | C88: CIV | K88: Fragment Crafting (3.7%), Lottery Machine #1 (0.8%), Wishing (0.34%), Fungus Chest (1.5%), Expert Scrolls (0.95%)
A89: Lennon's Guitar | B89: AAA | C89: CIV | K89: Fragment Crafting (1.5%), Lottery Machine #1 (0.03%), Wishing (0.14%), Relic Forge (80 Relic RF)
A90: ORANGE
A91: Output | D91: 16
A92: Artificial Black Hole | B92: SSS | C92: TECH | K92: Wish Box, Lottery Machine #1 (0.09%), Wishing (0.07%), Demon God Chest (0.1%), Grandmaster Scrolls (0.81%), Relic Forge (120 Relic RF), Nebula Chest (0.01%)
A93: Particle Collider | B93: SSS | C93: TECH | K93: Wish Box, Lottery Machine #1 (0.09%), Wishing (0.07%), Tool Chest (0.01%), Grandmaster Scrolls (0.81%), Relic Forge (120 Relic RF)
A94: Lotus Chalice | B94: SSS | C94: ART | K94: Wish Pack, Lottery Machine #1 (0.09%), Wishing (0.08%), Kemetic Treasure Chests (0.01%), Grandmaster Scrolls (0.81%), Relic Forge (120 Relic RF)
A95: Time Chest | H95: 16
A96: King Dangun Statue | B96: S | C96: FTH | K96: Fragment Crafting (15.1%), Lottery Machine #1 (0.81%), Wishing (0.81%), Koryeo Treasure Map (5%), Relic Forge (90 Relic RF), Museum Value Pack I ($14.99)
A97: Causality | B97: SS | C97: TECH | K97: Fragment Crafting (3.9%), Lottery Machine #1 (0.18%), Alchemy Furnace (0.14%), Grandmaster Scrolls (1.6%)
A98: Liberty Guide People | B98: SS | C98: ART | K98: Fragment Crafting (5.3%), Lottery Machine #1 (0.24%), Wishing (0.2%), Dragon Chest (5%), Master Scrolls (1.9%), Grandmaster Scrolls (2.1%), ART Master Scrolls (10.2%)
A99: MAX RESONANCE | D99: =SUM(D70:D98) -> 46 | F99: =SUM(F70:F98) -> 0 | H99: =SUM(H70:H98) -> 42
A102: Total Travel Speedup Output | B102: =D18+D21+D67+D99+D30+D39+D24+D45+D33+D42+D27 -> 485
A103: Total Travel Speedup Cap | B103: =F18+F21+F67+F99+F24+F30+F39+F45+F42 -> 228
A104: Total Time Chest Gen | B104: =H18+H67+H99+H21+H24+H30+H39+H45 -> 126

Sheet Lumber Camp
A1: Name | B1: Rarity | C1: Type | D1: Base Output | E1: Awakening Output | F1: Base Cap | G1: Awakening Cap | H1: Ancient Lumber | I1: Awakening Ancient Lumber | J1: AFFECT Boost | K1: Source
A2: INDIVIDUAL RELICS
A3: Julian Calendar | B3: SS | C3: CIV | D3: 22 | E3: 20 | F3: 22 | K3: Fragment Crafting (5.5%), Lottery Machine #1 (0.24%), Wishing (0.2%), Master Scrolls (1.9%), Grandmaster Scrolls (2.1%), CIV Master Scrolls (10.2%)
A4: Encyclopedia | B4: SSS | C4: FAME | D4: 24 | E4: 20 | K4: Wish Box, Lottery Machine #1 (0.09%), Wishing (0.09%), Grandmaster Scrolls (0.81%), Relic Forge (120 Relic RF)
A5: Das Kapital | B5: SS | C5: CIV | D5: 22 | F5: 22 | K5: Lottery Machine #1 (0.12%), Wishing (0.1%), Britland Treasure Maps (5%), Grandmaster Scrolls (1%), Relic Forge (100 Relic RF), beat Mr. Raccoon in combat
A6: Plato's Republic | B6: SS | C6: CIV | D6: 22 | K6: Lottery Machine #1 (0.12%), Wishing (0.1%), Grandmaster Scrolls (1%), Relic Forge (100 Relic RF)
A7: King Dangun Statue | B7: S | C7: FTH | D7: 20 | K7: Fragment Crafting (15.1%), Lottery Machine #1 (0.81%), Wishing (0.81%), Koryeo Treasure Map (5%), Relic Forge (90 Relic RF), Museum Value Pack I ($14.99)
A8: The Decameron | B8: AA | C8: CIV | D8: 16 | E8: 14 | F8: 16 | K8: Fragment Crafting (3.7%), Lottery Machine #1 (0.8%), Wishing (0.34%), Britland Treasure Maps (10%), Expert Scrolls (0.95%)
A9: Cavendish's Scale | B9: AAA | C9: TECH | H9: 18 | I9: 14 | K9: Fragment Crafting (1.6%), Lottery Machine #1 (0.03%), Wishing (0.14%), Relic Forge (80 Relic RF)
A10: Peacock Throne | B10: AAA | C10: ART | D10: 5 | E10: 5 | K10: Supreme Relic
A11: Klein Bottle | B11: Blue | C11: TECH | D11: 10 | E11: 10 | K11: Lottery Machine #1 (0.07%), Wishing (2.6%), Novice Scrolls (1%)
A12: Campbell's Sextant | B12: Blue | C12: TECH | F12: 10 | G12: 10 | K12: Lottery Machine #1 (0.7%), Wishing (2.6%), Tool Chest (2%), Novice Scrolls (1%)
A13: MAX INDIVIDUAL RELICS | D13: =SUM(D3:E12) -> 210 | F13: =SUM(F3:G12) -> 80 | H13: =SUM(H3:I12) -> 32
A15: PARTNER
A16: Advisor Zhuge | D16: 30 | K16: lv30
A18: COLLECTORS TALENTS
A19: Civil Engineering | D19: 25 | F19: 25 | K19: 10 Blue Talent Points
A21: ROBOTS
A22: Craftsman III | D22: 3 | K22: Wormhole Refiner (0.03%)
A24: ORGAN
A25: Warp Horn | D25: 10 | F25: 10 | K25: lv20
A26: Alveolus of Gaia | D26: 20 | F26: 20 | K26: lv40
A27: MAX ORGAN | D27: =SUM(D25:D26) -> 30 | F27: =SUM(F25:F26) -> 30 | H27: =SUM(H25:H26) -> 0
A29: INTEL
A30: Cathay | D30: 10
A32: ROCKET UPGRADES
A33: Eternal Hall | D33: 10 | F33: 10 | K33: Lv5
A35: AVATARS
A36: Mirage Avatar I Bonus | D36: 20 | F36: 40
A38: STAMPS
A39: Turing Award | B39: SSS | C39: FAME | D39: 30 | H39: 30 | J39: 15 | K39: Daily Pack Relic #26
A40: Prometheus Torch | B40: SSS | C40: FAME | D40: 30 | F40: 30 | H40: 30 | K40: Lottery Machine #1 (0.09%), Wishing (0.09%), Hellas Treasure Map, Grandmaster Scrolls (0.81%), Relic Forge (120 Relic RF)
A41: Nobel's Will | B41: SSS | C41: FAME | D41: 30 | F41: 30 | J41: 15 | K41: Lottery Machine #1 (0.09%), Wishing (0.08%), Grandmaster Scrolls (0.79%), Lottery Event 9/22/2023-9/28/2023
A42: Hammurabi Code | B42: SS | C42: FAME | H42: 30 | J42: 15 | K42: Fragment Crafting (4.6%), Lottery Machine #1 (0.18%), Wishing (0.17%), Demon God Chest (5%), Grandmaster Scrolls (1.6%)
A43: Zircon of Jack Hills | B43: SS | C43: FAME | H43: 30 | K43: Lottery Machine #2 (0.47%)
A44: Ape's Footprint Fossil | B44: SS | C44: FAME | D44: 30 | F44: 30 | K44: Super Species Chest (2.4%)
A45: Stockholm Declaration | B45: SS | C45: FAME | D45: 30 | F45: 30 | K45: Lottery Machine #2 (0.47%), Indigent Nobleman (570K B-tads)
A46: Tetromino | B46: S | C46: FAME | D46: 30 | K46: Fragment Crafting (20.7%), Lottery Machine #1 (0.81%), Wishing (0.75%), Master Scrolls (6.5%), FAME Master Scrolls (31.5%), Relic Forge (90 Relic RF)
A47: Proclamation 95 | B47: S | C47: FAME | J47: 15 | K47: Fragment Crafting (0.61), Lottery Machine #1 (0.24%), Wishing (0.22%), Master Scrolls (0.19%), Grandmaster Scrolls (2.1%), FAME Master Scroll (9.2%)
A48: Golden Finger | B48: S | C48: FTH | D48: 30 | K48: Fragment Crafting (15.1%), Lottery Machine #1 (0.81%), Wishing (0.53%), Master Scrolls (6.5%), FTH Master Scrolls (31.5%), Relic Forge (90 Relic RF), Rock in front of garage 999 taps, give Peter Jr. 42 0-star reviews in the same conversation
A49: Shroud of Turin | B49: S | C49: FTH | H49: 30 | K49: Fragment Crafting (15.1%), Lottery Machine #1 (0.81%), Wishing (0.53%), Relic Forge (90 Relic RF)
A50: Paradise Lost | B50: S | C50: CIV | J50: 15 | K50: Fragment Crafting (18.8%), Lottery Machine #1 (0.81%), Wishing (0.69%), Super Treasure Maps (15%), Master Scrolls (6.5%), CIV Master Scrolls (34.7%), Relic Forge (90 Relic RF)
A51: The Pieta | B51: S | C51: CIV | J51: 15 | K51: Fragment Crafting (18.8%), Lottery Machine #1 (0.81%), Wishing (0.69%), Relic Forge (90 Relic RF)
A52: The Last Supper | B52: S | C52: ART | J52: 15 | K52: Fragment Crafting (18.1%), Lottery Machine #1 (0.81%), Wishing (0.68%), Relic Forge (90 Relic RF)
A53: Ark of the Covenant | B53: S | C53: FTH | J53: 15 | K53: Fragment Crafting (15.1%), Lottery Machine #1 (0.81%), Wishing (0.53%), Relic Forge (90 Relic RF)
A54: Edison's Kinetoscope | B54: S | C54: TECH | F54: 30 | K54: Ad Shop
A55: MAX LUMBER STAMPS | D55: =D39+D40+D41 -> 90 | F55: =F39+F40+F41 -> 60 | H55: =H39+H40+H41 -> 60 | J55: =J39+J40+J41 -> 30
A57: RESONANCE
A58: BLUE
A59: Output | D59: 10
A60: Holmes' Pipe | B60: Blue | C60: CIV | K60: Lottery Machine #1 (0.36%), Wishing (10.3%), Novice Scrolls (5%)
A61: Sholes' Typewriter | B61: Blue | C61: CIV | K61: Lottery Machine #1 (0.03%), Wishing (0.82%)
A62: Ancient Lumber | H62: 10
A63: Imperial Lamp | B63: Blue | C63: ART | K63: Lottery Machine #1 (0.07%), Wishing (3%), Novice Scrolls (1%)
A64: Storyteller | B64: Blue | C64: ART | K64: Lottery Machine #1 (0.36%), Wishing (15%), Novice Scrolls (5%)
A65: PURPLE
A66: Output | D66: 12
A67: Meditations | B67: A | C67: CIV | K67: Fragment Crafting (29.9%), Lottery Machine #1 (0.66%), Wishing (2.7%), Expert Scrolls (7.6%)
A68: The Decameron | B68: AA | C68: CIV | K68: Fragment Crafting (3.7%), Lottery Machine #1 (0.8%), Wishing (0.34%), Britland Treasure Maps (10%), Expert Scrolls (0.95%)
A69: Ancient Lumber | H69: 12
A70: Nuclear Football | B70: AAA | C70: TECH | K70: Fragment Crafting (1.6%), Lottery Machine #1 (0.03%), Wishing (0.14%), Relic Forge (80 Relic RF)
A71: ARPAnet | B71: AAA | C71: FAME | K71: Fragment Crafting (1.6%), Lottery Machine #1 (0.03%), Wishing (0.14%), Tool Chest(1.5%), Relic Forge (80 Relic RF)
A72: ORANGE
A73: Output | D73: 14
A74: Notre Dame Bell | B74: S | C74: CIV | K74: Fragment Crafting (18.8%), Lottery Machine #1 (0.81%), Wishing (0.69%), Relic Forge (90 Relic RF)
A75: The Pieta | B75: S | C75: CIV | K75: Fragment Crafting (18.8%), Lottery Machine #1 (0.81%), Wishing (0.69%), Relic Forge (90 Relic RF)
A76: Ancient Lumber | H76: 14
A77: Das Kapital | B77: SS | C77: CIV | K77: Lottery Machine #1 (0.12%), Wishing (0.1%), Britland Treasure Maps (5%), Grandmaster Scrolls (1%), Relic Forge (100 Relic RF), beat Mr. Raccoon in combat
A78: The School of Athens | B78: SS | C78: ART | K78: Fragment Crafting (5.3%), Lottery Machine #1 (0.24%), Wishing (0.2%), Super Treasure Maps (5%), Master Scrolls (1.9%), Grandmaster Scrolls (2.1%), ART Master Scrolls (10.2%)
A79: MAX RESONANCE | D79: 36 | F79: 0 | H79: 36
A82: Total Lumber Output | B82: =D13+D16+D27+D30+D55+D79+D36+D19+D33+D22 -> 464
A83: Total Lumber Cap | B83: =F13+F16+F27+F30+F55+F79+F36+F19+F33 -> 245
A84: Total Ancient Lumber Gen | B84: =H13+H16+H27+H55+H79+H30+H36+H19 -> 128

Sheet Quarry
A1: Name | B1: Rarity | C1: Type | D1: Base Output | E1: Awakening Output | F1: Base Cap | G1: Awakening Cap | H1: Ancient Fossil | I1: Awakening Ancient Fossil | J1: AFFECT Boost | K1: Source
A2: INDIVIDUAL RELICS
A3: Cairo Declaration | B3: SS | C3: FAME | D3: 22 | F3: 22 | H3: 22 | I3: 20 | K3: Fragment Crafting (4.6%), Lottery Machine (0.18%), Wishing (0.17%), Grandmaster Scrolls (1.6%)
A4: David | B4: SS | C4: ART | D4: 22 | E4: 20 | F4: 22 | K4: Fragment Crafting (4%), Lottery Machine (0.18%), Wishing (0.15%), Demon God Chest (5%), Grandmaster Scrolls (1.6%)
A5: Plato's Republic | B5: SS | C5: CIV | D5: 22 | E5: 20 | K5: Lottery Machine (0.12%), Wishing (0.1%), Grandmaster Scrolls (1%), Relic Forge (100 Relic RF)
A6: King Dangun Statue | B6: S | C6: FTH | D6: 20 | K6: Fragment Crafting (15.1%), Lottery Machine (0.81%), Wishing (0.81%), Koryeo Treasure Map (5%), Relic Forge (90 Relic RF), Museum Value Pack I ($14.99)
A7: Galileo's Ball | B7: AAA | C7: FAME | H7: 18 | I7: 14 | K7: Fragment Crafting (1.6%), Lottery Machine (0.03%), Wishing (0.14%), Relic Forge (80 Relic RF)
A8: Phoenician Tablet | B8: AA | C8: CIV | D8: 16 | E8: 14 | F8: 16 | K8: Fragment Crafting (3.7%), Lottery Machine (0.8%), Wishing (0.34%), Kemetic Treasure Maps (10%), Expert Scrolls (0.95%)
A9: Peacock Throne | B9: AAA | C9: ART | D9: 5 | E9: 5 | K9: Supreme Relic
A10: Chronometer | B10: Blue | C10: TECH | D10: 10 | E10: 10 | K10: Lottery Machine (0.03%), Wishing (1.1%), Tool Chest (2%)
A11: Costa Rica Stone | B11: Blue | C11: FAME | F11: 10 | G11: 10 | K11: Lottery Machine (0.36%), Wishing (15.5%), Novice Scrolls (5%)
A12: Birdie | B12: Green | C12: FTH | D12: 6 | K12: Defeat Ronin Katsura
A13: Ancient Snail Fossil | B13: Green | C13: CIV | H13: 6 | K13: Zuckie's Ad Events
A14: MAX INDIVIDUAL RELICS | D14: =sum(D3:E13) -> 192 | F14: =sum(F3:G13) -> 80 | H14: =sum(H3:I13) -> 80
A16: PARTNER
A17: Taoist Yu Ji | D17: 30 | K17: lv30
A19: COLLECTORS TALENTS
A20: Civil Engineering | D20: 25 | F20: 25 | K20: 10 Blue Talent Points
A22: ROBOTS
A23: Surprise | D23: 3 | K23: Wormhole Refiner (0.03%)
A25: ORGAN
A26: Warp Horn | D26: 10 | F26: 10 | K26: lv20
A27: Alveolus of Gaia | D27: 20 | F27: 20 | K27: lv40
A28: MAX ORGAN | D28: =sum(D26:D27) -> 30 | F28: =sum(F26:F27) -> 30 | H28: =sum(H26:H27) -> 0
A30: INTEL
A31: Cathay | D31: 10
A33: ROCKET UPGRADES
A34: Eternal Hall | D34: 10 | F34: 10 | K34: Lv5
A36: AVATARS
A37: Mirage Avatar I Bonus | D37: 20 | F37: 40
A39: STAMPS
A40: Gaea's Hand | B40: SSS | C40: FTH | D40: 30 | F40: 30 | H40: 30 | K40: Wish Pack, Lottery Machine (0.09%), Wishing (0.06%), Grandmaster Scrolls (0.81%), Relic Forge (120 Relic RF)
A41: Aladdin Lamp | B41: SS | C41: FTH | D41: 30 | J41: 15 | K41: Lottery Machine (0.12%), Wishing (0.08%), Grandmaster Scrolls (1%), Relic Forge (100 Relic RF), Altar Value Pack II ($49.99)
A42: Mahakala Scroll | B42: SSS | C42: FTH | F42: 30 | H42: 30 | J42: 15 | K42: Jinx Points Bonus Reward
A43: The Argo | B43: SSS | C43: FTH | F43: 30 | H43: 30 | J43: 15 | K43: Lottery Machine (0.09%), Summer Festival Sept. 1-15, 2023
A44: Golden Finger | B44: S | C44: FTH | D44: 30 | K44: Fragment Crafting (15.1%), Lottery Machine (0.81%), Wishing (0.53%), Master Scrolls (6.5%), FTH Master Scrolls (31.5%), Relic Forge (90 Relic RF)
A45: Shroud of Turin | B45: S | C45: FTH | H45: 30 | K45: Fragment Crafting (15.1%), Lottery Machine (0.81%), Wishing (0.53%), Relic Forge (90 Relic RF)
A46: Ark of the Covenant | B46: S | C46: FTH | H46: 30 | K46: Fragment Crafting (15.1%), Lottery Machine (0.81%), Wishing (0.53%), Relic Forge (90 Relic RF)
A47: 3-Faced Statue | B47: S | C47: FTH | J47: 15 | K47: Fragment Crafting (4.4%), Lottery Machine (0.24%), Wishing (0.16%), Demon God Chest (5%), Master Scrolls (1.9%), Grandmaster Scrolls (2.1%), FTH Master Scrolls (9.2%), Indigent Nobleman (570K B-tads)
A48: The Key of Solomon | B48: SS | C48: FTH | F48: 30 | J48: 15 | K48: T7f Demon Gene Research
A49: Edison's Kinetoscope | B49: S | C49: TECH | D49: 30 | K49: Ad Shop
A50: Venus de Milo | B50: SS | C50: ART | D50: 30 | K50: T7 Angel Gene Research
A51: The Pieta | B51: S | C51: CIV | H51: 30 | K51: Fragment Crafting (18.8%), Lottery Machine (0.81%), Wishing (0.69%), Relic Forge (90 Relic RF)
A52: Das Capital | B52: SS | C52: CIV | J52: 15 | K52: Lottery Machine (0.12%), Wishing (0.1%), Britland Treasure Maps (5%), Grandmaster Scrolls (1%), Relic Forge (100 Relic RF), beat Mr. Raccoon in combat
A53: Devol's Robot | B53: S | C53: TECH | J53: 15 | K53: Fragment Crafting (17.8%), Wishing (0.65%), Ad Chest (3%), Master Scrolls (6.5%), TECH Master Scrolls (31.5%), Relic Forge (90 Relic RF)
A54: Tetromino | B54: S | C54: FAME | J54: 15 | K54: Fragment Crafting (20.7%), Lottery Machine (0.81%), Wishing (0.75%), Master Scrolls (6.5%), FAME Master Scrolls (31.5%), Relic Forge (90 Relic RF)
A55: Element R. | B55: S | C55: TECH | J55: 15 | K55: Fragment Crafting (17.8%), Lottery Machine (0.81%), Wishing (0.65%), Relic Forge (90 Relic RF)
A56: The Thinker | B56: SS | C56: ART | J56: 15 | K56: Fragment Crafting (5.3%), Lottery Machine (0.24%), Wishing (0.2%), Demon God Chest (5%), Master Scrolls (1.9%), Grandmaster Scrolls (2.1%), ART Master Scrolls (10.2%)
A57: Watt Steam Engine | B57: SS | C57: TECH | F57: 30 | K57: Lottery Machine (0.12%), Wishing (0.1%), Grandmaster Scrolls (1%), Relic Forge (100 Relic RF), Fissure Value Pack II ($49.99), Fissure Value Pack III ($99.99)
A58: Plato's Republic | B58: SS | C58: CIV | F58: 30 | K58: Lottery Machine (0.12%), Wishing (0.1%), Grandmaster Scrolls (1%), Relic Forge (100 Relic RF)
A59: Paradise Lost | B59: S | C59: CIV | F59: 30 | K59: Fragment Crafting (18.8%), Lottery Machine (0.81%), Wishing (0.69%), Super Treasure Maps (15%), Master Scrolls (6.5%), CIV Master Scrolls (34.7%), Relic Forge (90 Relic RF)
A60: MAX QUARRY STAMPS | D60: =D40+D42+D41 -> 60 | F60: =F40+F42+F41 -> 60 | H60: =H40+H42+H41 -> 60 | J60: 30
A62: RESONANCE
A63: BLUE
A64: Output | D64: 12
A65: Haradic Cube | B65: Blue | C65: FTH | K65: Lottery Machine (0.03%), Wishing (0.85%)
A66: Our Lady of Kazan | B66: Blue | C66: FTH | K66: Lottery Machine (0.36%), Wishing (10.6%), Novice Scrolls (5%)
A67: Chair of Busby | B67: Blue | C67: FTH | K67: Lottery Machine (0.03%), Wishing (0.85%)
A68: Ancient Fossil | H68: 12
A69: Peter Pan's Flute | B69: Blue | C69: FAME | K69: Lottery Machine (0.03%), Wishing (1.2%), Britland Treasure Map (20%), Indigent Nobleman (72K B-tads)
A70: Spinning Jenny | B70: Blue | C70: TECH | K70: Lottery Machine (0.36%), Wishing (13.2%), Tool Chest (2%), Novice Scroll (5%)
A71: Gregor Specimin | B71: Blue | C71: ART | K71: Lottery Machine (0.03%), Wishing (1.2%), Evolution Chest (2%)
A72: PURPLE
A73: Output | D73: 12
A74: Death of Marat | B74: AA | C74: ART | K74: Fragment Crafting (3.9%), Lottery Machine (0.08%), Wishing (0.36%), Expert Scrolls (0.95%), Indigent Nobleman (120K B-tads)
A75: Zoroaster's Torch | B75: AA | C75: FTH | K75: Fragment Crafting (3.8%), Lottery Machine (0.08%), Wishing (0.35%), Hellas Treasure Maps (%), Expert Scrolls (0.95%)
A76: Meditations | B76: A | C76: CIV | K76: Fragment Crafting (29.9%), Lottery Machine (0.66%), Wishing (2.7%), Expert Scrolls (7.6%)
A77: Ancient Fossil | H77: 12
A78: The Scream | B78: AAA | C78: ART | K78: Fragment Crafting (1.6%), Lottery Machine (0.03%), Wishing (0.14%), Relic Forge (80 Relic RF)
A79: Guernica | B79: AAA | C79: ART | K79: Fragment Crafting (1.6%), Lottery Machine (0.03%), Wishing (0.14%), Bharata Treasure Maps (%), Relic Forge (Relic RF 80)
A80: ORANGE
A81: Output | D81: 14
A82: Gaea's Hand | B82: SSS | C82: FTH | K82: Wish Pack, Lottery Machine (0.09%), Wishing (0.06%), Grandmaster Scrolls (0.81%), Relic Forge (120 Relic RF)
A83: Unispark | B83: SSS | C83: TECH | K83: Wishing (0.07%), Koryeo Treasure Map (0.01%), Relic Forge (120 Relic RF), Parama Ex Fight, Unispark Activation Lottery
A84: Ancient Fossil | H84: 14
A85: Iliad & Odyssey | B85: SSS | C85: CIV | K85: Daily Packs
A86: Arthur's Roundtable | B86: SSS | C86: CIV | K86: Unknown
A87: MAX RESONANCE | D87: =sum(D64:D86) -> 38 | F87: =sum(F64:F86) -> 0 | H87: =sum(H64:H86) -> 38
A90: Total Stone Output | B90: =D14+D17+D20+D28+D31+D37+D60+D87+D34+D23 -> 418
A91: Total Stone Cap | B91: =F14+F17+F20+F28+F31+F37+F60+F87+F34 -> 245
A92: Total Ancient Fossil Gen | B92: =H14+H17+H20+H28+H31+H37+H60+H87 -> 178

Sheet Quantum Amp
A1: Name | B1: Rarity | C1: Type | D1: Base Output | E1: Awakening Output | F1: Base Cap | G1: Awakening Cap | H1: Nebula Chest | I1: Awakening Nebula Chest | J1: AFFECT Boost | K1: Source
A2: INDIVIDUAL RELICS
A3: Olympic Torch | B3: SSS | C3: FAME | D3: 7.2 | E3: 6 | K3: Wish Box Album Relic #3
A4: Outer Space Treaty | B4: SSS | C4: FAME | D4: 7.2 | E4: 6 | K4: Star Chart Shop
A5: Great Mogul Diamond | B5: SSS | C5: ART | D5: 7.2 | E5: 6 | K5: Badge Shop
A6: Narmer Palette | B6: SSS | C6: CIV | H6: 7.2 | I6: 6 | K6: Traveler's Pack Reward #3
A7: Scales of Astraea | B7: SSS | C7: FTH | F7: 12 | G7: 10 | K7: Star Chart Shop
A8: Indus Seal | B8: AAA | C8: CIV | F8: 9 | G8: 7 | H8: 5.4 | K8: Indigent Nobleman (210K B-tads)
A9: Djinn Theory | B9: AAA | C9: CIV | F9: 9 | G9: 7 | K9: Lottery Box Relic #11
A10: Mesopotamian Wheel | B10: AAA | C10: FAME | D10: 5.4 | K10: Lottery Box Relic #17
A11: Biography of Great Artists | B11: AAA | C11: FAME | D11: 5.4 | E11: 4.2 | K11: Lottery Box Relic #13
A12: Nishijin Fabric | B12: AAA | C12: ART | D12: 5.4 | E12: 4.2 | K12: Lottery Box Relic #8
A13: Peacock Throne | B13: AAA | C13: ART | D13: 5 | E13: 5 | K13: Supreme Relic Reward
A14: V8 Engine | B14: AAA | C14: TECH | D14: 3.6 | E14: 2.8 | K14: Time Beacon Reward
A15: The Fifer | B15: AAA | C15: ART | F15: 9 | G15: 7 | K15: Lottery Box Relic #6
A16: MAX INDIVIDUAL RELICS | D16: =sum(D3:E15) -> 80.6 | F16: =sum(F3:G15) -> 70 | H16: =sum(H3:I15) -> 18.6
A18: ORGAN
A19: Warp Horn | D19: 10 | F19: 10 | K19: lv20
A20: Alveolus of Gaia | D20: 20 | F20: 20 | K20: lv40
A21: MAX ORGAN | D21: =sum(D19:D20) -> 30 | F21: =sum(F19:F20) -> 30 | H21: =sum(H19:H20) -> 0
A23: ROCKET UPGRADES
A24: Eternal Hall | D24: 10 | F24: 10 | K24: Lv5
A26: AVATARS
A27: Mirage Avatar I Bonus | D27: 20 | F27: 40
A29: STAMPS
A30: Natural History | B30: SSS | C30: FAME | D30: 15 | H30: 15 | J30: 15 | K30: Lottery Machine #3 (?%)
A31: Outer Space Treaty | B31: SSS | C31: FAME | D31: 15 | F31: 30 | J31: 15 | K31: Star Chart Shop
A32: Ram in a Thicket | B32: SSS | C32: ART | D32: 15 | F32: 30 | J32: 15 | K32: Daily Pack Relic #43
A33: Constellations | B33: SSS | C33: ART | F33: 30 | H33: 15 | J33: 15 | K33: Star Chart Shop
A34: Scales of Astraea | B34: SSS | C34: FTH | D34: 15 | H34: 15 | J34: 15 | K34: Star Chart Shop
A35: Ra's Solar Barque | B35: SSS | C35: FTH | D35: 15 | F35: 30 | J35: 15 | K35: Traveler's Pack #14
A36: Anna Karenina | B36: SSS | C36: CIV | D36: 15 | H36: 15 | J36: 15 | K36: Daily Pack Relic #49
A37: Hevelius Chart | B37: SSS | C37: CIV | D37: 15 | F37: 30 | J37: 15 | K37: Star Chart Shop
A38: Messier Catalogue | B38: SSS | C38: TECH | D38: 15 | F38: 30 | H38: 15 | K38: Star Chart Shop
A39: Infin. Improb. Eng. | B39: SSS | C39: TECH | D39: 15 | F39: 30 | J39: 15 | K39: Daily Pack Relic #51
A40: MAX QUANTUM AMP STAMPS | D40: =D30+D32+D34+D36+D38 -> 75 | F40: =F30+F32+F34+F36+F38 -> 60 | H40: =H30+H32+H34+H36+H38 -> 60 | J40: =J30+J32+J34+J36+J38 -> 60
A42: RESONANCE
A43: ORANGE
A44: Output | D44: 7
A45: Hevelius Chart | B45: SSS | C45: CIV | K45: Star Chart Shop
A46: Mysterious Relic | B46: SSS
A47: Cap 1 | F47: 7
A48: Constellations | B48: SSS | C48: ART | K48: Star Chart Shop
A49: Olympic Charter | B49: SSS | C49: FAME | K49: Lottery Machine #2 (?%)
A50: Cap 2 | F50: 7
A51: Energy Missile | B51: SSS | C51: TECH | K51: Lucky Box Reward Batch no. 1-7
A52: Quark Model | B52: SSS | C52: TECH | K52: Lucky Box Reward Batch no. 8-14
A53: MoCA | B53: SSS | C53: TECH | K53: Lucky Box Reward Batch no. 15-21
A54: MAX RESONANCE | D54: =sum(D43:D53) -> 7 | F54: =sum(F43:F53) -> 14 | H54: =sum(H43:H53) -> 0
A57: Total Base Output | B57: =D16+D21+D27+D40+D54+D24 -> 222.6
A58: Total Base Cap | B58: =F16+F21+F27+F40+F54+F24 -> 224
A59: Total Nebula Chest | B59: =H16+H21+H27+H40+H54 -> 78.6

Sheet Compass
A1: Dung Beetle | D1: Main AFFCT | E1: Stamp 1 | F1: Stamp 2 | G1: Stamp 3 | H1: HP | I1: ATK | J1: RUSH | K1: DEF | L1: CRIT | M1: CRIT DMG | N1: DMG | O1: DMG Reduc | P1: Hero DMG | Q1: ELMT DMG | R1: AFFCT | S1: Source | Y1: AFFCT | Z1: FAME | AA1: Non-FAME
A2: INDIVIDUAL RELICS | Y2: 49 | Z2: 0.5 | AA2: 2.4
A3: Celestial Mechanics | B3: SSS | C3: FAME | D3: 109 | E3: All ELMT DMG +15 | F3: RUSH +9% | G3: CRIT DMG +9% | J3: 9 | M3: 9 | Q3: 75 | S3: Lottery Machine No. 3 (0.12%) | Y3: 57 | Z3: 0.6 | AA3: 2.8
A4: Antarctic Treaty | B4: SSS | C4: FAME | D4: 108 | E4: Water DMG +60 | F4: FAME +15 | G4: CRIT DMG +9% | M4: 9 | Q4: 60 | R4: 15 | S4: Lottery Machine No. 2 (0.11%) | Y4: 66 | Z4: 0.7 | AA4: 3.3
A5: The Prince | B5: SSS | C5: FAME | D5: 106 | E5: ATK +6% | F5: FAME +15 | G5: CRIT DMG +6% | I5: 6 | M5: 6 | R5: 15 | S5: Lottery Machine No. 2 (0.11%) | Y5: 83 | Z5: 1 | AA5: 4.1
A6: Cross of Lorraine | B6: SS | C6: FAME | D6: 104 | E6: FAME +15 | F6: ATK +6% | I6: 6 | R6: 15 | S6: Lottery Machine No. 2 (?%) | Y6: 84 | Z6: 1 | AA6: 4.2
A7: Two-headed Serpent | B7: SSS | C7: ART | D7: 106 | E7: Hero DMG +6% | F7: Wind DMG +30 | G7: ATK +9% | I7: 9 | P7: 6 | Q7: 30 | S7: Lottery Machine No. 2 (0.11%), Relic Forge (120 RF) | Y7: 85 | Z7: 1 | AA7: 4.2
A8: Ivan the Terrible | B8: SSS | C8: ART | D8: 109 | E8: Wind DMG +60 | F8: DEF +9% | G8: RUSH +9% | J8: 9 | K8: 9 | Q8: 60 | S8: Lottery Machine No. 3 (0.12%) | Y8: 86 | Z8: 1 | AA8: 4.3
A9: Seated Voltaire | B9: SSS | C9: ART | D9: 106 | E9: DEF +6% | F9: ART +15 | G9: Wind DMG +30 | K9: 6 | Q9: 30 | R9: 15 | S9: Wish Box Relic Album #1 | Y9: 87 | Z9: 1 | AA9: 4.3
A10: Woman at Her Toilette | B10: SSS | C10: ART | D10: 109 | E10: ATK +6% | F10: RUSH +6% | G10: ART +15 | I10: 6 | J10: 6 | R10: 15 | S10: Minion Skin Lottery | Y10: 88 | Z10: 1.1 | AA10: 4.4
A11: Vedas | B11: SSS | C11: FTH | D11: 108 | E11: DEF +9% | F11: FTH +15 | G11: CRIT +9% | K11: 9 | L11: 9 | R11: 15 | S11: Lottery Machine No. 2 (0.11%) | Y11: 89 | Z11: 1.1 | AA11: 4.4
A12: Akashic Records | B12: SSS | C12: FTH | D12: 106 | E12: FTH +15 | F12: HP +9% | G12: DMG REDUC +6% | H12: 9 | O12: 6 | R12: 15 | S12: Lottery Machine No. 3 (0.12%) | Y12: 90 | Z12: 1.1 | AA12: 4.5
A13: The Myth of Etana | B13: S | C13: FTH | D13: 100 | E13: CRIT +9% | L13: 9 | S13: Lottery Machine No. 3 (1.63%) | Y13: 91 | Z13: 1.1 | AA13: 4.5
A14: Enuma Elish | B14: SSS | C14: FTH | D14: 107 | E14: FTH +15 | F14: ATK +6% | G14: RUSH +6% | I14: 6 | J14: 6 | R14: 15 | S14: Lottery Machine No. 2 (0.11%) | Y14: 92 | Z14: 1.1 | AA14: 4.6
A15: Beowulf | B15: SSS | C15: CIV | D15: 107 | E15: CIV +15 | F15: Fire DMG +60 | G15: Fire DMG +30 | Q15: 90 | R15: 15 | S15: Lottery Machine No. 2 (0.11%) | Y15: 93 | Z15: 1.1 | AA15: 4.6
A16: Of Human Bondage | B16: SSS | C16: CIV | D16: 109 | E16: CRIT +9% | F16: Hero DMG +6% | G16: Earth RES +60 | L16: 9 | P16: 6 | S16: Daily Pack #??
A17: Don Juan | B17: SSS | C17: CIV | D17: 106 | E17: CIV +15 | F17: HP +9% | G17: ATK +9% | H17: 9 | I17: 9 | R17: 15 | S17: Daily Pack #40 | Y17: 94 | Z17: 1.1 | AA17: 4.7
A18: Frederick Portrait | B18: SSS | C18: CIV | D18: 106 | E18: HP +9% | F18: RUSH +9% | G18: Water DMG +60 | H18: 9 | J18: 9 | Q18: 60 | S18: Unknown | Y18: 95 | Z18: 1.1 | AA18: 4.7
A19: Harem Wall Painting | B19: SS | C19: CIV | D19: 106 | E19: CIV +15 | F19: RUSH +6% | J19: 6 | R19: 15 | S19: Lottery Machine No. 2 (?%) | Y19: 96 | Z19: 1.2 | AA19: 4.8
A20: Volsunga Saga | B20: SSS | C20: CIV | D20: 109 | E20: CIV +15 | F20: ATK +9% | G20: DEF +9% | I20: 9 | K20: 9 | R20: 15 | S20: Gold Pack #6 | Y20: 97 | Z20: 1.2 | AA20: 4.8
A21: The King in Yellow | B21: SSS | C21: TECH | D21: 109 | E21: TECH +15 | F21: CRIT +9% | G21: CRIT DMG +9% | L21: 9 | M21: 9 | R21: 15 | S21: Gold Pack #7 | Y21: 98 | Z21: 1.2 | AA21: 4.9
A22: Goldbach Conjecture | B22: SSS | C22: TECH | D22: 108 | E22: ATK +9% | F22: DMG REDUC +6% | G22: TECH +15 | I22: 9 | O22: 6 | R22: 15 | S22: Traveler's Pack #2 | Y22: 99 | Z22: 1.2 | AA22: 4.9
A23: Superstring Computer | B23: SSS | C23: TECH | D23: 109 | E23: RUSH +9% | F23: DEF +9% | G23: Earth DMG +60 | J23: 9 | K23: 9 | Q23: 60 | S23: Clover Vendor Reward | Y23: 100 | Z23: 1.2 | AA23: 5
A24: TVC Engine | B24: S | C24: TECH | D24: 100 | E24: Earth DMG +60 | Q24: 60 | S24: Lottery Machine No. 3 (1.63%) | Y24: 101 | Z24: 1.2 | AA24: 5
A25: CRISPR | B25: S | C25: TECH | D25: 98 | E25: DEF +9% | K25: 9 | S25: Lottery Machine No. 2 (?%) | Y25: 102 | Z25: 1.2 | AA25: 5.1
Y26: 103 | Z26: 1.2 | AA26: 5.1
Y27: 104 | Z27: 1.3 | AA27: 5.2
Y28: 105 | Z28: 1.3 | AA28: 5.2
Y29: 106 | Z29: 1.3 | AA29: 5.3
Y30: 107 | Z30: 1.3 | AA30: 5.3
C31: Relic | E31: Slot | F31: Stat | G31: =D1 -> Main AFFCT | H31: HP | I31: ATK | J31: RUSH | K31: DEF | L31: CRIT | M31: CRIT DMG | N31: DMG | O31: DMG Reduc | P31: Hero DMG | Q31: ELMT DMG | R31: Alternatives | V31: Boosted | W31: Damage | Y31: 108 | Z31: 1.3 | AA31: 5.4
C32: =A3 -> Celestial Mechanics | E32: FAME | F32: HARD | G32: =VLOOKUP($C32,$A$3:$R$25,4,FALSE)+VLOOKUP($C32,$A$3:$R$25,18,FALSE) -> 109 | H32: =VLOOKUP($C32,$A$3:$R$25,8,FALSE)+VLOOKUP($G32,$Y$2:$AA$50,2) -> 1.3 | I32: =VLOOKUP($C32,$A$3:$R$25,9,FALSE)+VLOOKUP($G32,$Y$2:$AA$50,2) -> 1.3 | J32: =VLOOKUP($C32,$A$3:$R$25,10,FALSE)+VLOOKUP($G32,$Y$2:$AA$50,2) -> 10.3 | K32: =VLOOKUP($C32,$A$3:$R$25,11,FALSE)+VLOOKUP($G32,$Y$2:$AA$50,2) -> 1.3 | L32: =VLOOKUP($C32,$A$3:$R$25,12,FALSE) | M32: =VLOOKUP($C32,$A$3:$R$25,13,FALSE) -> 9 | N32: =VLOOKUP($C32,$A$3:$R$25,14,FALSE) | O32: =VLOOKUP($C32,$A$3:$R$25,15,FALSE) | P32: =VLOOKUP($C32,$A$3:$R$25,16,FALSE) | Q32: =VLOOKUP($C32,$A$3:$R$25,17,FALSE) -> 75 | R32: =A5 -> The Prince | U32: Troop: | Y32: 109 | Z32: 1.3 | AA32: 5.4
C33: =A7 -> Two-headed Serpent | E33: ART | F33: HP | G33: =VLOOKUP($C33,$A$3:$R$25,4,FALSE)+VLOOKUP($C33,$A$3:$R$25,18,FALSE) -> 106 | H33: =VLOOKUP($C33,$A$3:$R$25,8,FALSE)+VLOOKUP($G33,$Y$2:$AA$50,3) -> 5.3 | I33: =VLOOKUP($C33,$A$3:$R$25,9,FALSE) -> 9 | J33: =VLOOKUP($C33,$A$3:$R$25,10,FALSE) | K33: =VLOOKUP($C33,$A$3:$R$25,11,FALSE) | L33: =VLOOKUP($C33,$A$3:$R$25,12,FALSE) | M33: =VLOOKUP($C33,$A$3:$R$25,13,FALSE) | N33: =VLOOKUP($C33,$A$3:$R$25,14,FALSE) | O33: =VLOOKUP($C33,$A$3:$R$25,15,FALSE) | P33: =VLOOKUP($C33,$A$3:$R$25,16,FALSE) -> 6 | Q33: =VLOOKUP($C33,$A$3:$R$25,17,FALSE) -> 30 | R33: =A10 -> Woman at Her Toilette | U33: ATK | V33: =$Z$66*(1+I37/100) -> 1275962 | W33: =((V33-$Z$73)*(V35+P37/100)*((V36/100)*V37 + (1-V36/100)*1)) + LOG(V33,5)*Q37*(V35+P37/100) -> 661272.78 | Y33: 110 | Z33: 1.3 | AA33: 5.5
C34: =A14 -> Enuma Elish | E34: FTH | F34: RUSH | G34: =VLOOKUP($C34,$A$3:$R$25,4,FALSE)+VLOOKUP($C34,$A$3:$R$25,18,FALSE) -> 122 | H34: =VLOOKUP($C34,$A$3:$R$25,8,FALSE) | I34: =VLOOKUP($C34,$A$3:$R$25,9,FALSE) -> 6 | J34: =VLOOKUP($C34,$A$3:$R$25,10,FALSE)+VLOOKUP(G34,$Y$2:$AA$50,3) -> 12.1 | K34: =VLOOKUP($C34,$A$3:$R$25,11,FALSE) | L34: =VLOOKUP($C34,$A$3:$R$25,12,FALSE) | M34: =VLOOKUP($C34,$A$3:$R$25,13,FALSE) | N34: =VLOOKUP($C34,$A$3:$R$25,14,FALSE) | O34: =VLOOKUP($C34,$A$3:$R$25,15,FALSE) | P34: =VLOOKUP($C34,$A$3:$R$25,16,FALSE) | Q34: =VLOOKUP($C34,$A$3:$R$25,17,FALSE) | R34: =A11 -> Vedas | U34: RUSH | V34: =$Z$67*(1+J37/100) -> 1327140 | W34: =(V34-$Z$73)*(V35+P37/100)*((V36/100)*V37 + (1-V36/100)*1) + LOG(V34,5)*Q37*(V35+P37/100) -> 727209.89 | Y34: 111 | Z34: 1.3 | AA34: 5.5
C35: =A18 -> Frederick Portrait | E35: CIV | F35: ATK | G35: =VLOOKUP($C35,$A$3:$R$25,4,FALSE)+VLOOKUP($C35,$A$3:$R$25,18,FALSE) -> 106 | H35: =VLOOKUP($C35,$A$3:$R$25,8,FALSE) -> 9 | I35: =VLOOKUP($C35,$A$3:$R$25,9,FALSE)+VLOOKUP(G35,$Y$2:$AA$50,3) -> 5.3 | J35: =VLOOKUP($C35,$A$3:$R$25,10,FALSE) -> 9 | K35: =VLOOKUP($C35,$A$3:$R$25,11,FALSE) | L35: =VLOOKUP($C35,$A$3:$R$25,12,FALSE) | M35: =VLOOKUP($C35,$A$3:$R$25,13,FALSE) | N35: =VLOOKUP($C35,$A$3:$R$25,14,FALSE) | O35: =VLOOKUP($C35,$A$3:$R$25,15,FALSE) | P35: =VLOOKUP($C35,$A$3:$R$25,16,FALSE) | Q35: =VLOOKUP($C35,$A$3:$R$25,17,FALSE) -> 60 | R35: =A19 -> Harem Wall Painting | U35: DMG% | V35: =(1+($Z$68+N37)/100) -> 1.13 | Y35: 112 | Z35: 1.4 | AA35: 5.6
C36: =A22 -> Goldbach Conjecture | E36: TECH | F36: DEF | G36: =VLOOKUP($C36,$A$3:$R$25,4,FALSE)+VLOOKUP($C36,$A$3:$R$25,18,FALSE) -> 123 | H36: =VLOOKUP($C36,$A$3:$R$25,8,FALSE) | I36: =VLOOKUP($C36,$A$3:$R$25,9,FALSE) -> 9 | J36: =VLOOKUP($C36,$A$3:$R$25,10,FALSE) | K36: =VLOOKUP($C36,$A$3:$R$25,11,FALSE)+VLOOKUP(G36,$Y$2:$AA$50,3) -> 6.1 | L36: =VLOOKUP($C36,$A$3:$R$25,12,FALSE) | M36: =VLOOKUP($C36,$A$3:$R$25,13,FALSE) | N36: =VLOOKUP($C36,$A$3:$R$25,14,FALSE) | O36: =VLOOKUP($C36,$A$3:$R$25,15,FALSE) -> 6 | P36: =VLOOKUP($C36,$A$3:$R$25,16,FALSE) | Q36: =VLOOKUP($C36,$A$3:$R$25,17,FALSE) | R36: The Prince | U36: CRIT% | V36: =$Z$69+L37 -> 14 | Y36: 113 | Z36: 1.4 | AA36: 5.6
C37: Total | H37: =sum(H32:H36) -> 15.6 | I37: =sum(I32:I36) -> 30.6 | J37: =sum(J32:J36) -> 31.4 | K37: =sum(K32:K36) -> 7.4 | L37: =sum(L32:L36) -> 0 | M37: =sum(M32:M36) -> 9 | N37: =sum(N32:N36) -> 0 | O37: =sum(O32:O36) -> 6 | ... Q37: =sum(Q32:Q36) -> 165 | U37: CRIT DMG% | V37: =1.5+($Z$70+M37)/100 -> 1.59 | Y37: 114 | Z37: 1.4 | AA37: 5.7
C38: Damage Per Round | E38: =W33+W34 -> 1388482.7 | Y38: 115 | Z38: 1.4 | AA38: 5.7
Y39: 116 | Z39: 1.4 | AA39: 5.8
Y40: 117 | Z40: 1.4 | AA40: 5.8
A41: Goldfish | D41: Main AFFCT | E41: Stamp 1 | F41: Stamp 2 | G41: Stamp 3 | H41: HP | I41: ATK | J41: RUSH | K41: DEF | L41: CRIT | M41: CRIT DMG | N41: DMG | O41: DMG Reduc | P41: Hero DMG | Q41: ELMT DMG | R41: AFFCT | S41: Source | Y41: 118 | Z41: 1.4 | AA41: 5.9
A42: INDIVIDUAL RELICS | Y42: 119 | Z42: 1.4 | AA42: 5.9
A43: Kanner's Report | B43: SSS | C43: FAME | D43: 109 | E43: FAME +15 | F43: All ELMT DMG +15 | G43: HP +9% | H43: 9 | Q43: 75 | R43: 15 | S43: Lottery Machine No. 2 (0.11%) | Y43: 120 | Z43: 1.5 | AA43: 6
A44: Science Magazine Vol. 1 | B44: SSS | C44: FAME | D44: 107 | E44: AFFCT Check -150 | F44: Hero DMG +6% | G44: DEF +9% | K44: 9 | P44: 6 | S44: Lottery Machine No. 2 (0.11%), Relic Forge (120 RF) | Y44: 121 | Z44: 1.5 | AA44: 6
A45: The Prince | B45: SSS | C45: FAME | D45: 106 | E45: ATK +6% | F45: FAME +15 | G45: CRIT DMG +6% | I45: 6 | M45: 6 | R45: 15 | S45: Lottery Machine No. 2 (0.11%) | Y45: 122 | Z45: 1.5 | AA45: 6.1
A46: Cross of Lorraine | B46: SS | C46: FAME | D46: 104 | E46: FAME +15 | F46: ATK +6% | I46: 6 | R46: 15 | S46: Lottery Machine No. 2 (?%) | Y46: 123 | Z46: 1.5 | AA46: 6.1
A47: The Kiss | B47: SSS | C47: ART | D47: 108 | E47: CRIT +9% | F47: Hero DMG +6% | G47: Water RES +60 | L47: 9 | P47: 6 | S47: Daily Pack #62
A48: Capitoline Wolf | B48: SSS | C48: ART | D48: 108 | E48: ART +15 | F48: HP +9% | G48: RUSH +9% | H48: 9 | J48: 9 | R48: 15 | S48: Lottery Machine No. 2 (0.11%) | Y48: 124 | Z48: 1.5 | AA48: 6.2
A49: The Resurrection | B49: SSS | C49: ART | D49: 107 | E49: ART +15 | F49: DEF +9% | G49: ATK +9% | I49: 9 | K49: 9 | R49: 15 | S49: Easter Event | Y49: 125 | Z49: 1.5 | AA49: 6.2
A50: Woman at Her Toilette | B50: SSS | C50: ART | D50: 109 | E50: ATK +6% | F50: RUSH +6% | G50: ART +15 | I50: 6 | J50: 6 | R50: 15 | S50: Minion Skin Lottery | Y50: 125 | Z50: 1.5 | AA50: 6.2
A51: Seated Voltaire | B51: SSS | C51: ART | D51: 106 | E51: DEF +6% | F51: ART +15 | G51: Wind DMG +30 | K51: 6 | Q51: 30 | R51: 15 | S51: Wish Box Relic Album #1
A52: The Silver Key | B52: SSS | C52: FTH | D52: 108 | E52: ATK +9% | F52: Water RES +30 | G52: Water DMG +60 | I52: 9 | Q52: 60 | S52: Lottery Machine No. 2 (0.11%), Rift Treasure Maps (0.01%)
A53: Tauroctony | B53: SSS | C53: FTH | D53: 109 | E53: FTH +15 | F53: Hero DMG +6% | G53: DMG REDUC +6% | O53: 6 | P53: 6 | R53: 15 | S53: Daily Pack #29
A54: Ymir's Treasure Chest | B54: SS | C54: FTH | D54: 104 | E54: CRIT DMG +9% | F54: Fire DMG +60 | M54: 9 | Q54: 60 | S54: Lottery Machine No. 3 (0.36%)
A55: Enuma Elish | B55: SSS | C55: FTH | D55: 107 | E55: FTH +15 | F55: ATK +6% | G55: RUSH +6% | I55: 6 | J55: 6 | R55: 15 | S55: Lottery Machine No. 2 (0.11%)
A56: Bronze Goblet | B56: SSS | C56: CIV | D56: 107 | E56: ATK +9% | F56: Water DMG +60 | G56: Hero DMG +6% | I56: 9 | P56: 6 | Q56: 60 | S56: Lottery Machine No. 2 (?%)
A57: Metaphysics | B57: SSS | C57: CIV | D57: 109 | E57: CIV +15 | F57: DMG REDUC +6% | G57: HP +9% | H57: 9 | O57: 6 | R57: 15 | S57: Traveler's Pack #10
A58: Harem Wall Painting | B58: SS | C58: CIV | D58: 102 | E58: CIV +15 | F58: RUSH +6% | J58: 6 | R58: 15 | S58: Lottery Machine No. 2 (?%)
A59: Volsunga Saga | B59: SSS | C59: CIV | D59: 109 | E59: CIV +15 | F59: ATK +9% | G59: DEF +9% | I59: 9 | K59: 9 | R59: 15 | S59: Gold Pack #6
A60: The King in Yellow | B60: SSS | C60: TECH | D60: 109 | E60: TECH +15 | F60: CRIT +9% | G60: CRIT DMG +9% | L60: 9 | M60: 9 | R60: 15 | S60: Gold Pack #7
A61: Antimatter Bomb | B61: SSS | C61: TECH | D61: 108 | E61: RUSH +9% | F61: Hero DMG +6% | G61: CRIT +9% | J61: 9 | L61: 9 | O61: 6 | S61: Daily Silver Pack #4
A62: Xuanyuan Compass Chariot | B62: SSS | C62: TECH | D62: 107 | E62: Fire DMG +60 | F62: ATK +9% | G62: Hero DMG +6% | I62: 9 | P62: 6 | Q62: 60 | S62: Wish Box Relic Album #??
A63: Photon Rocket Engine | B63: SSS | C63: TECH | D63: 108 | E63: TECH +15 | F63: CRIT +9% | G63: DEF +9% | K63: 9 | L63: 9 | R63: 15 | S63: Lottery Machine No.3 (?%)
Z64: Base
Y65: Troop:
Y66: ATK | Z66: 977000
Y67: RUSH | Z67: 1010000
Y68: DMG% | Z68: 13
C69: Relic | E69: Slot | F69: Stat | G69: =D41 -> Main AFFCT | H69: HP | I69: ATK | J69: RUSH | K69: DEF | L69: CRIT | M69: CRIT DMG | N69: DMG | O69: DMG Reduc | P69: Hero DMG | Q69: ELMT DMG | R69: Alternatives | V69: Boosted | W69: Damage | Y69: CRIT% | Z69: 14
C70: =A44 -> Science Magazine Vol. 1 | E70: FAME | F70: HARD | G70: =VLOOKUP($C70,$A$43:$R$63,4,FALSE)+VLOOKUP($C70,$A$43:$R$63,18,FALSE) -> 107 | H70: =VLOOKUP($C70,$A$43:$R$63,8,FALSE)+VLOOKUP($G70,$Y$2:$AA$50,2) -> 1.3 | I70: =VLOOKUP($C70,$A$43:$R$63,9,FALSE)+VLOOKUP($G70,$Y$2:$AA$50,2) -> 1.3 | J70: =VLOOKUP($C70,$A$43:$R$63,10,FALSE)+VLOOKUP($G70,$Y$2:$AA$50,2) -> 1.3 | K70: =VLOOKUP($C70,$A$43:$R$63,11,FALSE)+VLOOKUP($G70,$Y$2:$AA$50,2) -> 10.3 | L70: =VLOOKUP($C70,$A$43:$R$63,12,FALSE) | M70: =VLOOKUP($C70,$A$43:$R$63,13,FALSE) | N70: =VLOOKUP($C70,$A$43:$R$63,14,FALSE) | O70: =VLOOKUP($C70,$A$43:$R$63,15,FALSE) | P70: =VLOOKUP($C70,$A$43:$R$63,16,FALSE) -> 6 | Q70: =VLOOKUP($C70,$A$43:$R$63,17,FALSE) | R70: =A45 -> The Prince | U70: Troop: | Y70: CRIT DMG% | Z70: 0
C71: =A48 -> Capitoline Wolf | E71: ART | F71: HP | G71: =VLOOKUP($C71,$A$43:$R$63,4,FALSE)+VLOOKUP($C71,$A$43:$R$63,18,FALSE) -> 123 | H71: =VLOOKUP($C71,$A$43:$R$63,8,FALSE)+VLOOKUP($G71,$Y$2:$AA$50,3) -> 15.1 | I71: =VLOOKUP($C71,$A$43:$R$63,9,FALSE) | J71: =VLOOKUP($C71,$A$43:$R$63,10,FALSE) -> 9 | K71: =VLOOKUP($C71,$A$43:$R$63,11,FALSE) | L71: =VLOOKUP($C71,$A$43:$R$63,12,FALSE) | M71: =VLOOKUP($C71,$A$43:$R$63,13,FALSE) | N71: =VLOOKUP($C71,$A$43:$R$63,14,FALSE) | O71: =VLOOKUP($C71,$A$43:$R$63,15,FALSE) | P71: =VLOOKUP($C71,$A$43:$R$63,16,FALSE) | Q71: =VLOOKUP($C71,$A$43:$R$63,17,FALSE) | R71: =A48 -> Capitoline Wolf | U71: ATK | V71: =$Z$66*(1+I75/100) -> 1188032 | W71: =((V71-$Z$73)*(V73+P75/100)*((V74/100)*V75 + (1-V74/100)*1)) + LOG(V71,5)*Q75*(V73+P75/100) -> 591646.43
C72: =A55 -> Enuma Elish | E72: FTH | F72: RUSH | G72: =VLOOKUP($C72,$A$43:$R$63,4,FALSE)+VLOOKUP($C72,$A$43:$R$63,18,FALSE) -> 122 | H72: =VLOOKUP($C72,$A$43:$R$63,8,FALSE) | I72: =VLOOKUP($C72,$A$43:$R$63,9,FALSE) -> 6 | J72: =VLOOKUP($C72,$A$43:$R$63,10,FALSE)+VLOOKUP(G72,$Y$2:$AA$50,3) -> 12.1 | K72: =VLOOKUP($C72,$A$43:$R$63,11,FALSE) | L72: =VLOOKUP($C72,$A$43:$R$63,12,FALSE) | M72: =VLOOKUP($C72,$A$43:$R$63,13,FALSE) | N72: =VLOOKUP($C72,$A$43:$R$63,14,FALSE) | O72: =VLOOKUP($C72,$A$43:$R$63,15,FALSE) | P72: =VLOOKUP($C72,$A$43:$R$63,16,FALSE) | Q72: =VLOOKUP($C72,$A$43:$R$63,17,FALSE) | R72: =A52 -> The Silver Key | U72: RUSH | V72: =$Z$67*(1+J75/100) -> 1327140 | W72: =(V72-$Z$73)*(V73+P75/100)*((V74/100)*V75 + (1-V74/100)*1) + LOG(V72,5)*Q75*(V73+P75/100) -> 785533.37 | Y72: Enemy:
C73: =A56 -> Bronze Goblet | E73: CIV | F73: ATK | G73: =VLOOKUP($C73,$A$43:$R$63,4,FALSE)+VLOOKUP($C73,$A$43:$R$63,18,FALSE) -> 107 | H73: =VLOOKUP($C73,$A$43:$R$63,8,FALSE) | I73: =VLOOKUP($C73,$A$43:$R$63,9,FALSE)+VLOOKUP(G73,$Y$2:$AA$50,3) -> 14.3 | J73: =VLOOKUP($C73,$A$43:$R$63,10,FALSE) | K73: =VLOOKUP($C73,$A$43:$R$63,11,FALSE) | L73: =VLOOKUP($C73,$A$43:$R$63,12,FALSE) | M73: =VLOOKUP($C73,$A$43:$R$63,13,FALSE) | N73: =VLOOKUP($C73,$A$43:$R$63,14,FALSE) | O73: =VLOOKUP($C73,$A$43:$R$63,15,FALSE) | P73: =VLOOKUP($C73,$A$43:$R$63,16,FALSE) -> 6 | Q73: =VLOOKUP($C73,$A$43:$R$63,17,FALSE) -> 60 | R73: =A58 -> Harem Wall Painting | U73: DMG% | V73: =(1+($Z$68+N75)/100) -> 1.13 | Y73: DEF | Z73: 764000
C74: =A61 -> Antimatter Bomb | E74: TECH | F74: DEF | G74: =VLOOKUP($C74,$A$43:$R$63,4,FALSE)+VLOOKUP($C74,$A$43:$R$63,18,FALSE) -> 108 | H74: =VLOOKUP($C74,$A$43:$R$63,8,FALSE) | I74: =VLOOKUP($C74,$A$43:$R$63,9,FALSE) | J74: =VLOOKUP($C74,$A$43:$R$63,10,FALSE) -> 9 | K74: =VLOOKUP($C74,$A$43:$R$63,11,FALSE)+VLOOKUP(G74,$Y$2:$AA$50,3) -> 5.4 | L74: =VLOOKUP($C74,$A$43:$R$63,12,FALSE) -> 9 | M74: =VLOOKUP($C74,$A$43:$R$63,13,FALSE) | N74: =VLOOKUP($C74,$A$43:$R$63,14,FALSE) | O74: =VLOOKUP($C74,$A$43:$R$63,15,FALSE) -> 6 | P74: =VLOOKUP($C74,$A$43:$R$63,16,FALSE) | Q74: =VLOOKUP($C74,$A$43:$R$63,17,FALSE) | R74: The Prince | U74: CRIT% | V74: =$Z$69+L75 -> 23
C75: Total | H75: =sum(H70:H74) -> 16.4 | I75: =sum(I70:I74) -> 21.6 | J75: =sum(J70:J74) -> 31.4 | K75: =sum(K70:K74) -> 15.7 | L75: =sum(L70:L74) -> 9 | M75: =sum(M70:M74) -> 0 | N75: =sum(N70:N74) -> 0 | O75: =sum(O70:O74) -> 6 | ... Q75: =sum(Q70:Q74) -> 60 | U75: CRIT DMG% | V75: =1.5+($Z$70+M75)/100 -> 1.5
C76: Damage Per Round | E76: =W71+W72 -> 1377179.8
H77: 16.4 | I77: 13.3 | J77: 37.4 | K77: 15.7
A79: Surf Clam | D79: Main AFFCT | E79: Stamp 1 | F79: Stamp 2 | G79: Stamp 3 | H79: HP | I79: ATK | J79: RUSH | K79: DEF | L79: CRIT | M79: CRIT DMG | N79: DMG | O79: DMG Reduc | P79: Hero DMG | Q79: ELMT DMG | R79: AFFCT | S79: Source
A80: INDIVIDUAL RELICS
A81: Potsdam Declaration | B81: SSS | C81: FAME | D81: 108 | E81: CRIT +9% | F81: Crit DMG +9% | G81: Hero DMG +6% | L81: 9 | M81: 9 | P81: 6 | S81: Daily Gold Pack #4
A82: The Prince | B82: SSS | C82: FAME | D82: 106 | E82: ATK +6% | F82: FAME +15 | G82: CRIT DMG +6% | I82: 6 | M82: 6 | R82: 15 | S82: Lottery Machine No. 2 (0.11%)
A83: Cross of Lorraine | B83: SS | C83: FAME | D83: 104 | E83: FAME +15 | F83: ATK +6% | I83: 6 | R83: 15 | S83: Lottery Machine No. 2 (?%)
A84: Louis XIV Portrait | B84: SSS | C84: ART | D84: 107 | E84: HP +9% | F84: CRIT +9% | G84: ART +15 | H84: 9 | L84: 9 | R84: 15 | S84: Lottery Machine No.2 (?%)
A85: Hunter in the Snow | B85: SSS | C85: ART | D85: 106 | E85: ART +15 | F85: HP +9% | G85: All ELMT DMG +15 | H85: 9 | Q85: 75 | R85: 15 | S85: Lottery Machine No.3 (?%)
A86: Woman at Her Toilette | B86: SSS | C86: ART | D86: 109 | E86: ATK +6% | F86: RUSH +6% | G86: ART +15 | I86: 6 | J86: 6 | R86: 15 | S86: Minion Skin Lottery
A87: Seated Voltaire | B87: SSS | C87: ART | D87: 106 | E87: DEF +6% | F87: ART +15 | G87: Wind DMG +30 | K87: 6 | Q87: 30 | R87: 15 | S87: Wish Box Relic Album #1
A88: Head of Bhairava | B88: SSS | C88: FTH | D88: 107 | E88: FTH +15 | F88: CRIT DMG +9% | G88: ATK +9% | I88: 9 | M88: 9 | R88: 15 | S88: Daily Pack #17
A89: Washington Portrait | B89: SSS | C89: FTH | D89: 108 | E89: FTH +15 | F89: DMG REDUC +6% | G89: HP +9% | H89: 9 | O89: 6 | R89: 15 | S89: Unknown
A90: Enuma Elish | B90: SSS | C90: FTH | D90: 107 | E90: FTH +15 | F90: ATK +6% | G90: RUSH +6% | I90: 6 | J90: 6 | R90: 15 | S90: Lottery Machine No. 2 (0.11%)
A91: Isabella I Portrait | B91: SSS | C91: CIV | D91: 107 | E91: CIV +15 | F91: CRIT +9% | G91: CRIT DMG +9% | L91: 9 | M91: 9 | R91: 15 | S91: Unknown
A92: Four-goat Square Zun | B92: SSS | C92: CIV | D92: 108 | E92: CIV +15 | F92: ATK +9% | G92: DEF +9% | I92: 9 | K92: 9 | R92: 15 | S92: Lottery Machine No.3 (0.12%)
A93: Crime and Punishment | B93: SSS | C93: CIV | D93: 106 | E93: ATK +9% | F93: DEF +9% | G93: CIV +15 | I93: 9 | K93: 9 | R93: 15 | S93: Lottery Machine No. 2 (0.11%)
A94: Harem Wall Painting | B94: SS | C94: CIV | D94: 106 | E94: CIV +15 | F94: RUSH +6% | J94: 6 | R94: 15 | S94: Lottery Machine No. 2 (?%)
A95: Volsunga Saga | B95: SSS | C95: CIV | D95: 109 | E95: CIV +15 | F95: ATK +9% | G95: DEF +9% | I95: 9 | K95: 9 | R95: 15 | S95: Gold Pack #6
A96: The King in Yellow | B96: SSS | C96: TECH | D96: 109 | E96: TECH +15 | F96: CRIT +9% | G96: CRIT DMG +9% | L96: 9 | M96: 9 | R96: 15 | S96: Gold Pack #7
A97: Black Body | B97: SSS | C97: TECH | D97: 108 | E97: TECH +15 | F97: RUSH +9% | G97: CRIT DMG +9% | J97: 9 | M97: 9 | R97: 15 | S97: Lottery Machine No. 2 (0.11%)
A98: Talos' Bronze Gears | B98: SSS | C98: TECH | D98: 108 | E98: Wind RES +60 | F98: DEF +9% | G98: Hero DMG +6% | K98: 9 | P98: 6 | S98: Wish Box Relic Album #??
A99: Phase-Shift Spatial Gate | B99: SSS | C99: TECH | D99: 108 | E99: Earth DMG +60 | F99: DMG REDUC +6% | G99: RUSH +9% | J99: 9 | O99: 6 | Q99: 60 | S99: Daily Pack #46
A100: Capsian Sea Monster | B100: SS | C100: TECH | D100: 105 | E100: Water DMG +60 | F100: Water RES +60 | G100: RUSH +9% | J100: 9 | Q100: 60 | S100: Lottery Machine No.3 (0.48%)
C106: Relic | E106: Slot | F106: Stat | G106: =D79 -> Main AFFCT | H106: HP | I106: ATK | J106: RUSH | K106: DEF | L106: CRIT | M106: CRIT DMG | N106: DMG | O106: DMG Reduc | P106: Hero DMG | Q106: ELMT DMG | R106: Alternatives | V106: Boosted | W106: Damage
...

Sheet Cost Reductions
A1: Name | B1: Rarity | C1: Type | D1: Btad Cost | E1: Awakening Btad Cost | F1: Wood Cost | G1: Awakening Wood Cost | H1: Stone Cost | I1: Awakening Stone Cost | J1: Source
A2: TADPOLE POND
A3: Golden Finger | B3: S | C3: FTH | D3: 10 | J3: Fragment Crafting (15.1%), Lottery Machine #1 (0.81%), Wishing (0.53%), Master Scrolls (6.5%), FTH Master Scrolls (31.5%), Relic Forge (90 Relic RF)
A4: Epic of Gilgamesh | B4: SS | C4: CIV | I4: 10 | J4: Fragment Crafting (4.1%), Lottery Machine #1 (0.18%), Wishing (0.15%), Dragon Chest (5%), Grandmaster Scrolls (1.5%)
A5: Haulers on Volga | B5: AAA | C5: ART | F5: 9 | J5: Fragment Crafting (1.6%), Lottery Machine #1 (0.03%), Wishing (0.14%), Relic Forge (Relic RF 80)
A6: San Plate | B6: AAA | C6: FAME | F6: 9 | G6: 7 | J6: Museum Operation Reward
A7: Observatory | B7: A | C7: TECH | H7: 7 | I7: 7 | J7: Fragment Crafting (31.5%), Lottery Machine #1 (0.66%), Wishing (2.9%), Fungus Chest (1.5%), Expert Scrolls (7.6%)
A8: Boy with Goose | B8: A | C8: ART | D8: 7 | E8: 7 | J8: Fragment Crafting (31.2%), Lottery Machine #1 (0.66%), Wishing (2.8%), Expert Scrolls (7.6%)
A9: MAX TADPOLE POND | D9: =sum(D3:E8) -> 24 | F9: =sum(F3:G8) -> 25 | H9: =sum(H3:I8) -> 24
A11: Name | B11: Rarity | C11: Type | D11: Btad Cost | E11: Awakening Btad Cost | F11: Wood Cost | G11: Awakening Wood Cost | H11: Stone Cost | I11: Awakening Stone Cost | J11: Source
A12: FUNGUS FARM
A13: Golden Finger | B13: S | C13: FTH | D13: 10 | J13: Fragment Crafting (15.1%), Lottery Machine #1 (0.81%), Wishing (0.53%), Master Scrolls (6.5%), FTH Master Scrolls (31.5%), Relic Forge (90 Relic RF)
A14: Fuchun Mountains | B14: AA | C14: ART | F14: 8 | G14: 7 | J14: Fragment Crafting (3.9%), Lottery Machine #1 (0.08%), Wishing (0.36%), Expert Scrolls (0.95%)
A15: Boy with Goose | B15: A | C15: ART | D15: 7 | J15: Fragment Crafting (31.2%), Lottery Machine #1 (0.66%), Wishing (2.8%), Expert Scrolls (7.6%)
A16: Rosetta Stone | B16: A | C16: FAME | H16: 7 | J16: Fragment Crafting (31%), Lottery Machine #1 (0.66%), Wishing (2.8%), Kemetic Treasure Maps (10%), Expert Scrolls (7.6%)
A17: MAX FUNGUS FARM | D17: =sum(D13:E16) -> 17 | F17: =sum(F13:G16) -> 15 | H17: =sum(H13:I16) -> 7
A20: Name | B20: Rarity | C20: Type | D20: Btad Cost | E20: Awakening Btad Cost | F20: Wood Cost | G20: Awakening Wood Cost | H20: Stone Cost | I20: Awakening Stone Cost | J20: Source
A21: TIME MACHINE
A22: Golden Finger | B22: S | C22: FTH | D22: 10 | E22: 10 | J22: Fragment Crafting (15.1%), Lottery Machine #1 (0.81%), Wishing (0.53%), Master Scrolls (6.5%), FTH Master Scrolls (31.5%), Relic Forge (90 Relic RF)
A23: Bell's Telephone | B23: AAA | C23: TECH | D23: 9 | J23: Fragment Crafting (1.6%), Lottery Machine #1 (0.03%), Wishes (0.14%), Relic Forge (80 Relic RF)
A24: ENIAC Prototype | B24: AA | C24: TECH | F24: 8 | H24: 8 | I24: 7 | J24: Fragment Crafting (3.9%), Lottery Machine #1 (0.08%), Wishing (0.36%), Murikan Treasure Map (10%), Expert Scrolls (0.95%)
A25: Franklin's Kite | B25: Blue | C25: FAME | D25: 5 | E25: 5 | J25: Lottery Machine #1 (0.07%), Wishing (3.1%), Murikan Treasure Map (20%), Novice Scrolls (1%)
A26: MAX TIME MACHINE | D26: =sum(D22:E25) -> 39 | F26: =sum(F22:G25) -> 8 | H26: =sum(H22:I25) -> 15
A29: Name | B29: Rarity | C29: Type | D29: Btad Cost | E29: Awakening Btad Cost | F29: Wood Cost | G29: Awakening Wood Cost | H29: Stone Cost | I29: Awakening Stone Cost | J29: Source
A30: LUMBER CAMP
A31: The Tales of Genji | B31: S | C31: CIV | D31: 10 | E31: 10 | F31: 10 | H31: 10 | J31: Fragment Crafting (18.8%), Lottery Machine #1 (0.81%), Wishing (0.69%), Yamato Treasure Map (5%), Master Scroll (6.5%), CIV Master Scroll (37.5%), Relic Forge (90 Relic RF)
A32: Plantagenet Badge | B32: AAA | C32: FAME | D32: 9 | H32: 9 | I32: 7 | J32: Fragment Crafting (1.6%), Lottery Machine #1 (0.03%), Wishing (0.14%), Relic Forge (80 Relic RF)
A33: Pine Trees Screen | B33: AA | C33: ART | F33: 8 | G33: 7 | J33: Fragment Crafting (3.9%), Lottery Machine #1 (0.08%), Wishing (0.36%), Yamato Treasure Maps (10%), Expert Scrolls (0.95%)
A34: MAX LUMBER CAMP | D34: =sum(D31:E33) -> 29 | F34: =sum(F31:G33) -> 25 | H34: =sum(H31:I33) -> 26
A37: Name | B37: Rarity | C37: Type | D37: Btad Cost | E37: Awakening Btad Cost | F37: Wood Cost | G37: Awakening Wood Cost | H37: Stone Cost | I37: Awakening Stone Cost | J37: Source
A38: QUARRY
A39: Epic of Gilgamesh | B39: SS | C39: CIV | D39: 11 | F39: 11 | H39: 11 | J39: Fragment Crafting (4.1%), Lottery Machine #1 (0.18%), Wishing (0.15%), Dragon Chest (5%), Grandmaster Scrolls (1.5%)
A40: Killing Stone | B40: AAA | C40: FTH | H40: 9 | J40: Fragment Crafting (1.5%), Lottery Machine #1 (0.03%), Wishing (0.14%), Relic Forge (80 Relic RF)
A41: Spirit of Laws | B41: AA | C41: FAME | D41: 8 | E41: 7 | F41: 8 | J41: Fragment Crafting (3.9%), Lottery Machine #1 (0.08%), Wishing (0.35%), Expert Scrolls (0.95%)
A42: Musician Figure | B42: Blue | C42: CIV | D42: 5 | E42: 5 | J42: Lottery Machine #1 (0.03%), Wish (0.82%), Cathay Treasure Maps (20%)
A43: MAX QUARRY | D43: =sum(D39:E42) -> 36 | F43: =sum(F39:G42) -> 19 | H43: =sum(H39:I42) -> 20
A46: Name | B46: Rarity | C46: Type | D46: Btad Cost | E46: Awakening Btad Cost | F46: Wood Cost | G46: Awakening Wood Cost | H46: Stone Cost | I46: Awakening Stone Cost | J46: Source
A47: QUANTUM AMP
A48: Almagest | B48: Green | C48: TECH | D48: 1.8 | J48: Star Chart Shop
A49: MAX QUANTUM AMP | D49: =sum(D48:E48) -> 1.8 | F49: =sum(F48:G48) -> 0 | H49: =sum(H48:I48) -> 0

Sheet Lottery
A1: Name | B1: Rarity | C1: Type | D1: White -> Green | E1: Green -> Blue | F1: Blue -> Purple | G1: Purple -> Orange | H1: Source
A2: INDIVIDUAL RELICS
A3: Divine Comedy | B3: SSS | C3: CIV | E3: 1 | F3: 2.4 | H3: Lottery Machine #1 (0.09%), Wishing (0.08%), Grandmaster Scrolls (0.81%), Relic Forge (120 Relic RF)
A4: Lotus Chalice | B4: SSS | C4: ART | F4: 3.4 | H4: Wish Box, Lottery Machine #1 (0.09%), Wishing (0.08%), Kemetic Treasure Chests (0.01%), Grandmaster Scrolls (0.81%), Relic Forge (120 Relic RF)
A5: Mahakala Scroll | B5: SSS | C5: FTH | E5: 2.4 | F5: 2.4 | G5: 3.4 | H5: Jinx Points Bonus Reward
A6: Ode to Joy | B6: SSS | C6: ART | G6: 2.4 | H6: Lottery Machine #2 (0.12%)
A7: Swan Lake | B7: SS | C7: ART | D7: 3.2 | E7: 2.2 | H7: Lottery Machine #1 (0.12%), Wishing (0.1%), Grandmaster Scrolls (1%), Relic Forge (100 Relic RF)
A8: Truth Crystal | B8: AAA | C8: CIV | F8: 2.5 | H8: Fragment Crafting (1.5%), Lottery Machine #1 (0.03%), Wishing (0.14%), Relic Forge (80 Relic RF), Nebula Chest (1.5%)
A9: Nocturnes | B9: Blue | C9: ART | E9: 1.5 | H9: Lottery Machine #1 (0.03%), Wishing (1.2%)
A10: Color Bead No. 6 | B10: Green | C10: CIV | E10: 0.6 | H10: It Takes 5 minigame
A11: Spirit Bead | B11: Green | C11: FTH | F11: 0.6 | H11: Defeat Deity Taiyi
A12: Golden Ball Award | B12: Green | C12: CIV | G12: 1.5 | H12: Domain Avatar Score Reward
A14: Resonance: Orange | G14: 2.4
A15: Deep Navy Computer | B15: SSS | C15: TECH | H15: Lottery Machine #2 (0.12%)
A16: Kepler Telescope | B16: SSS | C16: TECH | H16: Weekly Special Relic #1
A17: Nautilus | B17: SSS | C17: TECH | H17: Daily Pack Relic #8
A18: AH602 | B18: SSS | C18: TECH | H18: Lottery Machine #2 (0.12%), Relic Forge (120 RF), 120 Objects Shot Down Reward
A19: 5th Element | B19: SS | C19: TECH | H19: Fragment Crafting (5.2%), Lottery Machine #1 (0.24%), Wishing (0.19%), Master Scrolls (1.9%), Grandmaster Scrolls (2.1%), TECH Master Scrolls (9.2%)
A20: Dyson Sphere | B20: SSS | C20: TECH | H20: Lottery Machine #1 (0.09%), Wishing (0.07%), Grandmaster Scrolls (0.81%), Relic Forge (120 Relic RF)
A21: Resonance: Purple | F21: 1.8
A22: Tesla Coil | B22: AAA | C22: TECH | H22: Fragment Crafting (1.6%), Lottery Machine #1 (0.03%), Wishing (0.14%), Tool Chest (1.5%), Relic Forge (80 Relic RF)
A23: The Starry Night | B23: AA | C23: ART | H23: Fragment Crafting (3.9%), Lottery Machine #1 (0.08%), Wishing (0.36%), Expert Scrolls (0.95%), Nebula Chest (1.5%)
A24: Voynich Script | B24: AAA | C24: CIV | H24: Form Evo Pack
A25: Corinthian Pillar | B25: AAA | C25: FTH | H25: Fragment Crafting (1.5%), Lottery Machine #1 (0.03%), Wishing (0.14%), Relic Forge (80 Relic RF)
A26: Gordian Knot | B26: AAA | C26: FAME | H26: Fragment Crafting (1.6%), Lottery Machine #1 (0.03%), Wishing (0.14%), Relic Forge (80 Relic RF)
A27: Resonance: Blue | E27: 1.6
A28: Throne of Pope | B28: Blue | C28: FTH | H28: Lottery Machine #1 (0.36%), Wishing (10.6%), Novice Scrolls (5%)
A29: Sleeping Gypsy | B29: Blue | C29: ART | H29: Lottery Machine #1 (0.03%), Wishing (1.2%)
A30: Pumpkin Coach | B30: Blue | C30: CIV | H30: Lottery Machine #1 (0.07%), Wishing (2.1%), Novice Scrolls (1%)
A31: Penicillin Sample | B31: Blue | C31: TECH | H31: Lottery Machine #1 (0.03%), Wishing (1.1%), Evolution Chest (2%)
A32: Faraday's Dynamo | B32: Blue | C32: TECH | H32: Lottery Machine #1 (0.07%), Wishing (2.6%), Tool Chest (2%), Novice Scrolls (1%)
A33: Resonance: Blue | D33: 1
A34: Klein Bottle | B34: Blue | C34: TECH | H34: Lottery Machine #1 (0.07%), Wishing (2.6%), Novice Scrolls (1%)
A35: Spinning Jenny | B35: Blue | C35: ART | H35: Lottery Machine #1 (0.36%), Wishing (13.2%), Tool Chest (2%), Novice Scroll (5%)
A37: MAX INDIVIDUAL RELICS | D37: =sum(D3:D36) -> 4.2 | E37: =sum(E3:E36) -> 9.3 | F37: =sum(F3:F36) -> 13.1 | G37: =sum(G3:G36) -> 9.7
A40: PARTNER
A41: Nito UR | F41: 9 | H41: lv30
A43: COLLECTORS TALENTS
A44: Jewelry Expert | F44: 5 | H44: 5 Purple Talent Points
A45: Jewelry Master | G45: 5 | H45: 5 Orange Talent Points
A46: MAX COLLECTORS TALENTS | D46: =sum(D44:D45) -> 0 | E46: =sum(E44:E45) -> 0 | F46: =sum(F44:F45) -> 5 | G46: =sum(G44:G45) -> 5
A48: ORGAN
A49: Fire Slug's Eye | D49: 10
A51: ROCKET UPGRADES
A52: Revelation Hall | F52: 2.5 | G52: 2.5 | H52: lv5
A57: Totals
A58: White -> Green | B58: =D37+D41+D46+D49+D52 -> 14.2
A59: Green -> Blue | B59: =E37+E41+E46+E49+E52 -> 9.3
A60: Blue -> Purple | B60: =F37+F41+F46+F52 -> 29.6
A61: Purple -> Orange | B61: =G37+G46+G41+G49+G52 -> 17.2

Sheet Minion Base Stats
B1: HP | C1: ATK | D1: DEF | E1: RUSH
A2: ZOMBIE
A3: Tomb Guardian | H3: Minion Base Stats Growth Factor Multiplier | L3: Minion Total Base Stats
A4: Growth Factor | B4: =(B13-B11)/4 -> 160 | C4: =(C13-C11)/4 -> 14 | D4: =(D13-D11)/4 -> 10 | E4: =(E13-E11)/4 -> 10 | I4: Non-Dragon | J4: Dragon | M4: Non-Dragon | N4: Dragon
A5: T1 | B5: =B6-B$28 -> 350 | C5: =C6-C$28 -> 25 | D5: =D6-D$28 -> 20 | E5: =E6-E$28 -> 20 | H5: T1 | I5: 2 | J5: 2.5 | L5: T1 | M5: =50*I5 -> 100 | N5: =52.5*J5 -> 131.25
A6: T2 | B6: =B7-B$28 -> 505 | C6: =C7-C$28 -> 39.5 | D6: =D7-D$28 -> 30 | E6: =E7-E$28 -> 30 | H6: T2 | I6: 3 | J6: 3.5 | L6: T2 | M6: =50*I6 -> 150 | N6: =52.5*J6 -> 183.75
A7: T3 | B7: =B8-B$28 -> 660 | C7: =C8-C$28 -> 54 | D7: =D8-D$28 -> 40 | E7: =E8-E$28 -> 40 | H7: T3 | I7: 4 | J7: 4.5 | L7: T3 | M7: =50*I7 -> 200 | N7: =52.5*J7 -> 236.25
A8: T4 | B8: =B9-B$28 -> 815 | C8: =C9-C$28 -> 68.5 | D8: =D9-D$28 -> 50 | E8: =E9-E$28 -> 50 | H8: T4 | I8: 5 | J8: 5.5 | L8: T4 | M8: =50*I8 -> 250 | N8: =52.5*J8 -> 288.75
A9: T5 | B9: =B10-B$28 -> 970 | C9: =C10-C$28 -> 83 | D9: =D10-D$28 -> 60 | E9: =E10-E$28 -> 60 | H9: T5 | I9: 6 | J9: 6.5 | L9: T5 | M9: =50*I9 -> 300 | N9: =52.5*J9 -> 341.25
A10: T6 | B10: =B11-B$28 -> 1125 | C10: =C11-C$28 -> 97.5 | D10: =D11-D$28 -> 70 | E10: =E11-E$28 -> 70 | H10: T6 | I10: 7 | J10: 7.5 | L10: T6 | M10: =50*I10 -> 350 | N10: =52.5*J10 -> 393.75
A11: T7 | B11: 1280 | C11: 112 | D11: 80 | E11: 80 | H11: T7 | I11: 8 | J11: 8.5 | L11: T7 | M11: =50*I11 -> 400 | N11: =52.5*J11 -> 446.25
A12: T8 | B12: 1440 | C12: 126 | D12: 90 | E12: 90 | H12: T8 | I12: 9 | J12: 10.5 | L12: T8 | M12: =50*I12 -> 450 | N12: =52.5*J12 -> 551.25
A13: T9 | B13: 1920 | C13: 168 | D13: 120 | E13: 120 | H13: T9 | I13: 12 | J13: 14 | L13: T9 | M13: =50*I13 -> 600 | N13: =52.5*J13 -> 735
A15: Undead Turtle
A16: Growth Factor | B16: =(B25-B23)/4 -> 165 | C16: =(C25-C23)/4 -> 13.5 | D16: =(D25-D23)/4 -> 10 | E16: =(E25-E23)/4 -> 10
A17: T1 | B17: =B18-B$16 -> 330 | C17: =C18-C$16 -> 27 | D17: =D18-D$16 -> 20 | E17: =E18-E$16 -> 20 | I17: HP | J17: ATK | K17: DEF | L17: RUSH | M17: HARD SUM
A18: T2 | B18: =B19-B$16 -> 495 | C18: =C19-C$16 -> 40.5 | D18: =D19-D$16 -> 30 | E18: =E19-E$16 -> 30 | H18: =A3 -> Tomb Guardian | I18: =B4 -> 160 | J18: =C4 -> 14 | K18: =D4 -> 10 | L18: =E4 -> 10 | M18: =I18/10+J18+K18+L18 -> 50
A19: T3 | B19: =B20-B$16 -> 660 | C19: =C20-C$16 -> 54 | D19: =D20-D$16 -> 40 | E19: =E20-E$16 -> 40 | H19: =A15 -> Undead Turtle | I19: =B16 -> 165 | J19: =C16 -> 13.5 | K19: =D16 -> 10 | L19: =E16 -> 10 | M19: =I19/10+J19+K19+L19 -> 50
A20: T4 | B20: =B21-B$16 -> 825 | C20: =C21-C$16 -> 67.5 | D20: =D21-D$16 -> 50 | E20: =E21-E$16 -> 50 | H20: =A27 -> Wraith | I20: =B28 -> 155 | J20: =C28 -> 14.5 | K20: =D28 -> 10 | L20: =E28 -> 10 | M20: =I20/10+J20+K20+L20 -> 50
A21: T5 | B21: =B22-B$16 -> 990 | C21: =C22-C$16 -> 81 | D21: =D22-D$16 -> 60 | E21: =E22-E$16 -> 60 | H21: =A39 -> Mummy | I21: =B40 -> 165 | J21: =C40 -> 14 | K21: =D40 -> 10.5 | L21: =E40 -> 9 | M21: =I21/10+J21+K21+L21 -> 50
A22: T6 | B22: =B23-B$16 -> 1155 | C22: =C23-C$16 -> 94.5 | D22: =D23-D$16 -> 70 | E22: =E23-E$16 -> 70 | H22: =A51 -> Baby Bud | I22: =B52 -> 155 | J22: =C52 -> 15 | K22: =D52 -> 9 | L22: =E52 -> 10.5 | M22: =I22/10+J22+K22+L22 -> 50
A23: T7 | B23: 1320 | C23: 108 | D23: 80 | E23: 80 | H23: =A67 -> Ironball Thrower | I23: =B68 -> 100 | J23: =C68 -> 15 | K23: =D68 -> 11 | L23: =E68 -> 14 | M23: =I23/10+J23+K23+L23 -> 50
A24: T8 | B24: 1485 | C24: 122 | D24: 90 | E24: 90 | H24: =A79 -> Nightmare Steed | I24: =B80 -> 100 | J24: =C80 -> 15 | K24: =D80 -> 10.5 | L24: =E80 -> 14.5 | M24: =I24/10+J24+K24+L24 -> 50
A25: T9 | B25: 1980 | C25: 162 | D25: 120 | E25: 120 | H25: =A91 -> Imp | I25: =B92 -> 110 | J25: =C92 -> 15.5 | K25: =D92 -> 10.5 | L25: =E92 -> 13 | M25: =I25/10+J25+K25+L25 -> 50
H26: =A103 -> Berserker | I26: =B104 -> 115 | J26: =C104 -> 15 | K26: =D104 -> 10 | L26: =E104 -> 13.5 | M26: =I26/10+J26+K26+L26 -> 50
A27: Wraith | H27: =A115 -> Vampire | I27: =B116 -> 105 | J27: =C116 -> 16 | K27: =D116 -> 9.5 | L27: =E116 -> 14 | M27: =I27/10+J27+K27+L27 -> 50
A28: Growth Factor | B28: =(B37-B35)/4 -> 155 | C28: =(C37-C35)/4 -> 14.5 | D28: =(D37-D35)/4 -> 10 | E28: =(E37-E35)/4 -> 10 | H28: =A131 -> Koryeon Snail | I28: =B132 -> 155 | J28: =C132 -> 10 | K28: =D132 -> 9.5 | L28: =E132 -> 15 | M28: =I28/10+J28+K28+L28 -> 50
A29: T1 | B29: =B30-B$4 -> 280 | C29: =C30-C$4 -> 32 | D29: =D30-D$4 -> 20 | E29: =E30-E$4 -> 20 | H29: =A143 -> Stan | I29: =B144 -> 155 | J29: =C144 -> 10 | K29: =D144 -> 8.5 | L29: =E144 -> 16 | M29: =I29/10+J29+K29+L29 -> 50
A30: T2 | B30: =B31-B$4 -> 440 | C30: =C31-C$4 -> 46 | D30: =D31-D$4 -> 30 | E30: =E31-E$4 -> 30 | H30: =A155 -> Catcolyte | I30: =B156 -> 155 | J30: =C156 -> 10 | K30: =D156 -> 9 | L30: =E156 -> 15.5 | M30: =I30/10+J30+K30+L30 -> 50
A31: T3 | B31: =B32-B$4 -> 600 | C31: =C32-C$4 -> 60 | D31: =D32-D$4 -> 40 | E31: =E32-E$4 -> 40 | H31: =A167 -> Sanctum Warrior | I31: =B168 -> 160 | J31: =C168 -> 9.5 | K31: =D168 -> 9 | L31: =E168 -> 15.5 | M31: =I31/10+J31+K31+L31 -> 50
A32: T4 | B32: =B33-B$4 -> 760 | C32: =C33-C$4 -> 74 | D32: =D33-D$4 -> 50 | E32: =E33-E$4 -> 50 | H32: =A179 -> Gaiastapo | I32: =B180 -> 145 | J32: =C180 -> 9 | K32: =D180 -> 10 | L32: =E180 -> 16.5 | M32: =I32/10+J32+K32+L32 -> 50
A33: T5 | B33: =B34-B$4 -> 920 | C33: =C34-C$4 -> 88 | D33: =D34-D$4 -> 60 | E33: =E34-E$4 -> 60 | H33: =A195 -> Chika | I33: =B196 -> 110 | J33: =C196 -> 15 | K33: =D196 -> 9 | L33: =E196 -> 15 | M33: =I33/10+J33+K33+L33 -> 50
A34: T6 | B34: =B35-B$4 -> 1080 | C34: =C35-C$4 -> 102 | D34: =D35-D$4 -> 70 | E34: =E35-E$4 -> 70 | H34: =A207 -> Minorino | I34: =B208 -> 120 | J34: =C208 -> 14.5 | K34: =D208 -> 9 | L34: =E208 -> 14.5 | M34: =I34/10+J34+K34+L34 -> 50
A35: T7 | B35: 1240 | C35: 116 | D35: 80 | E35: 80 | H35: =A219 -> Demonic Tentacle | I35: =B220 -> 110 | J35: =C220 -> 14.5 | K35: =D220 -> 9 | L35: =E220 -> 15.5 | M35: =I35/10+J35+K35+L35 -> 50
A36: T8 | B36: 1395 | C36: 131 | D36: 90 | E36: 90 | H36: =A231 -> Little Monk | I36: =B232 -> 105 | J36: =C232 -> 15 | K36: =D232 -> 9.5 | L36: =E232 -> 15 | M36: =I36/10+J36+K36+L36 -> 50
A37: T9 | B37: 1860 | C37: 174 | D37: 120 | E37: 120 | H37: =A243 -> Roachikun | I37: =B244 -> 95 | J37: =C244 -> 15 | K37: =D244 -> 9 | L37: =E244 -> 16.5 | M37: =I37/10+J37+K37+L37 -> 50
H38: =A259 -> Mechanic | I38: =B260 -> 120 | J38: =C260 -> 11.5 | K38: =D260 -> 10.5 | L38: =E260 -> 16 | M38: =I38/10+J38+K38+L38 -> 50
A39: Mummy | H39: =A271 -> Wood Golem | I39: =B272 -> 125 | J39: =C272 -> 11.5 | K39: =D272 -> 10.5 | L39: =E272 -> 15.5 | M39: =I39/10+J39+K39+L39 -> 50
A40: Growth Factor | B40: =(B49-B47)/4 -> 165 | C40: =(C49-C47)/4 -> 14 | D40: =(D49-D47)/4 -> 10.5 | E40: =(E49-E47)/4 -> 9 | H40: =A283 -> Keyboard Warrior | I40: =B284 -> 125 | J40: =C284 -> 11 | K40: =D284 -> 11 | L40: =E284 -> 15.5 | M40: =I40/10+J40+K40+L40 -> 50
A41: T1 | B41: =B42-B$40 -> 330 | C41: =C42-C$40 -> 28 | D41: =D42-D$40 -> 21 | E41: =E42-E$40 -> 18 | H41: =A295 -> Snail Mech | I41: =B296 -> 130 | J41: =C296 -> 11.5 | K41: =D296 -> 10.5 | L41: =E296 -> 15 | M41: =I41/10+J41+K41+L41 -> 50
A42: T2 | B42: =B43-B$40 -> 495 | C42: =C43-C$40 -> 42 | D42: =D43-D$40 -> 31.5 | E42: =E43-E$40 -> 27 | H42: =A307 -> NeuroMecha | I42: =B308 -> 125 | J42: =C308 -> 10 | K42: =D308 -> 10 | L42: =E308 -> 17.5 | M42: =I42/10+J42+K42+L42 -> 50
A43: T3 | B43: =B44-B$40 -> 660 | C43: =C44-C$40 -> 56 | D43: =D44-D$40 -> 42 | E43: =E44-E$40 -> 36 | H43: =A323 -> Drawn Dragon | I43: =B324 -> 110 | J43: =C324 -> 16.5 | K43: =D324 -> 10 | L43: =E324 -> 15 | M43: =I43/10+J43+K43+L43 -> 52.5
A44: T4 | B44: =B45-B$40 -> 825 | C44: =C45-C$40 -> 70 | D44: =D45-D$40 -> 52.5 | E44: =E45-E$40 -> 45 | H44: =A335 -> Slug Dragonling | I44: =B336 -> 150 | J44: =C336 -> 15 | K44: =D336 -> 10 | L44: =E336 -> 12.5 | M44: =I44/10+J44+K44+L44 -> 52.5
A45: T5 | B45: =B46-B$40 -> 990 | C45: =C46-C$40 -> 84 | D45: =D46-D$40 -> 63 | E45: =E46-E$40 -> 54 | H45: =A347 -> Nanosaur | I45: =B348 -> 130 | J45: =C348 -> 15.5 | K45: =D348 -> 10 | L45: =E348 -> 14 | M45: =I45/10+J45+K45+L45 -> 52.5
A46: T6 | B46: =B47-B$40 -> 1155 | C46: =C47-C$40 -> 98 | D46: =D47-D$40 -> 73.5 | E46: =E47-E$40 -> 63 | H46: =A359 -> Frost Drake | I46: =B360 -> 100 | J46: =C360 -> 17.5 | K46: =D360 -> 10 | L46: =E360 -> 15 | M46: =I46/10+J46+K46+L46 -> 52.5
A47: T7 | B47: 1320 | C47: 112 | D47: 84 | E47: 72 | H47: =A371 -> Jaden Embryo | I47: =B372 -> 100 | J47: =C372 -> 18 | K47: =D372 -> 8.5 | L47: =E372 -> 16 | M47: =I47/10+J47+K47+L47 -> 52.5
A48: T8 | B48: 1485 | C48: 126 | D48: 95 | E48: 81
A49: T9 | B49: 1980 | C49: 168 | D49: 126 | E49: 108
A51: Baby Bud
A52: Growth Factor | B52: =(B61-B59)/4 -> 155 | C52: =(C61-C59)/4 -> 15 | D52: =(D61-D59)/4 -> 9 | E52: =(E61-E59)/4 -> 10.5
A53: T1 | B53: 310 | C53: 30 | D53: 18 | E53: 21
A54: T2 | B54: 465 | C54: 45 | D54: 27 | E54: 32
A55: T3 | B55: 620 | C55: 60 | D55: 36 | E55: 42
A56: T4 | B56: 775 | C56: 75 | D56: 45 | E56: 53
A57: T5 | B57: 930 | C57: 90 | D57: 54 | E57: 63
A58: T6 | B58: 1085 | C58: 105 | D58: 63 | E58: 74
A59: T7 | B59: 1240 | C59: 120 | D59: 72 | E59: 84
A60: T8 | B60: 1395 | C60: 135 | D60: 81 | E60: 95
A61: T9 | B61: 1860 | C61: 180 | D61: 108 | E61: 126
A66: DEMON
A67: Ironball Thrower
A68: Growth Factor | B68: =(B77-B75)/4 -> 100 | C68: =(C77-C75)/4 -> 15 | D68: =(D77-D75)/4 -> 11 | E68: =(E77-E75)/4 -> 14
A69: T1 | B69: =B70-B$68 -> 200 | C69: =C70-C$68 -> 30 | D69: =D70-D$68 -> 22 | E69: =E70-E$68 -> 28
A70: T2 | B70: =B71-B$68 -> 300 | C70: =C71-C$68 -> 45 | D70: =D71-D$68 -> 33 | E70: =E71-E$68 -> 42
A71: T3 | B71: =B72-B$68 -> 400 | C71: =C72-C$68 -> 60 | D71: =D72-D$68 -> 44 | E71: =E72-E$68 -> 56
A72: T4 | B72: =B73-B$68 -> 500 | C72: =C73-C$68 -> 75 | D72: =D73-D$68 -> 55 | E72: =E73-E$68 -> 70
A73: T5 | B73: =B74-B$68 -> 600 | C73: =C74-C$68 -> 90 | D73: =D74-D$68 -> 66 | E73: =E74-E$68 -> 84
A74: T6 | B74: =B75-B$68 -> 700 | C74: =C75-C$68 -> 105 | D74: =D75-D$68 -> 77 | E74: =E75-E$68 -> 98
A75: T7 | B75: 800 | C75: 120 | D75: 88 | E75: 112
A76: T8 | B76: 900 | C76: 135 | D76: 99 | E76: 126
A77: T9 | B77: 1200 | C77: 180 | D77: 132 | E77: 168
A79: Nightmare Steed
A80: Growth Factor | B80: =(B89-B87)/4 -> 100 | C80: =(C89-C87)/4 -> 15 | D80: =(D89-D87)/4 -> 10.5 | E80: =(E89-E87)/4 -> 14.5
A81: T1 | B81: =B82-B$80 -> 200 | C81: =C82-C$80 -> 30 | D81: =D82-D$80 -> 21 | E81: =E82-E$80 -> 29
A82: T2 | B82: =B83-B$80 -> 300 | C82: =C83-C$80 -> 45 | D82: =D83-D$80 -> 31.5 | E82: =E83-E$80 -> 43.5
A83: T3 | B83: =B84-B$80 -> 400 | C83: =C84-C$80 -> 60 | D83: =D84-D$80 -> 42 | E83: =E84-E$80 -> 58
A84: T4 | B84: =B85-B$80 -> 500 | C84: =C85-C$80 -> 75 | D84: =D85-D$80 -> 52.5 | E84: =E85-E$80 -> 72.5
A85: T5 | B85: =B86-B$80 -> 600 | C85: =C86-C$80 -> 90 | D85: =D86-D$80 -> 63 | E85: =E86-E$80 -> 87
A86: T6 | B86: =B87-B$80 -> 700 | C86: =C87-C$80 -> 105 | D86: =D87-D$80 -> 73.5 | E86: =E87-E$80 -> 101.5
A87: T7 | B87: 800 | C87: 120 | D87: 84 | E87: 116
A88: T8 | B88: 900 | C88: 135 | D88: 95 | E88: 131
A89: T9 | B89: 1200 | C89: 180 | D89: 126 | E89: 174
A91: Imp
A92: Growth Factor | B92: =(B101-B99)/4 -> 110 | C92: =(C101-C99)/4 -> 15.5 | D92: =(D101-D99)/4 -> 10.5 | E92: =(E101-E99)/4 -> 13
A93: T1 | B93: =B94-B$92 -> 220 | C93: =C94-C$92 -> 31 | D93: =D94-D$92 -> 21 | E93: =E94-E$92 -> 26
A94: T2 | B94: =B95-B$92 -> 330 | C94: =C95-C$92 -> 46.5 | D94: =D95-D$92 -> 31.5 | E94: =E95-E$92 -> 39
A95: T3 | B95: =B96-B$92 -> 440 | C95: =C96-C$92 -> 62 | D95: =D96-D$92 -> 42 | E95: =E96-E$92 -> 52
A96: T4 | B96: =B97-B$92 -> 550 | C96: =C97-C$92 -> 77.5 | D96: =D97-D$92 -> 52.5 | E96: =E97-E$92 -> 65
A97: T5 | B97: =B98-B$92 -> 660 | C97: =C98-C$92 -> 93 | D97: =D98-D$92 -> 63 | E97: =E98-E$92 -> 78
A98: T6 | B98: =B99-B$92 -> 770 | C98: =C99-C$92 -> 108.5 | D98: =D99-D$92 -> 73.5 | E98: =E99-E$92 -> 91
A99: T7 | B99: 880 | C99: 124 | D99: 84 | E99: 104
A100: T8 | B100: 990 | C100: 140 | D100: 95 | E100: 117
A101: T9 | B101: 1320 | C101: 186 | D101: 126 | E101: 156
A103: Berserker
A104: Growth Factor | B104: =(B113-B111)/4 -> 115 | C104: =(C113-C111)/4 -> 15 | D104: =(D113-D111)/4 -> 10 | E104: =(E113-E111)/4 -> 13.5
A105: T1 | B105: 230 | C105: 30 | D105: 20 | E105: 27
A106: T2 | B106: 345 | C106: 45 | D106: 30 | E106: 41
A107: T3 | B107: 460 | C107: 60 | D107: 40 | E107: 54
A108: T4 | B108: 575 | C108: 75 | D108: 50 | E108: 68
A109: T5 | B109: 690 | C109: 90 | D109: 60 | E109: 81
...

Sheet Partner Research Costs
A3: Partner | B3: Son of Will
A4: Specialty | B4: =VLOOKUP($B$3,$A$23:$H$51,8, FALSE) -> Angel
B6: Zombie | C6: Demon | D6: Angel | E6: Mutant | F6: Mecha | G6: Dragon
A7: Starting Skill | B7: =VLOOKUP($B$3,$A$23:$H$51,2,FALSE) -> 22 | C7: =VLOOKUP($B$3,$A$23:$H$51,3,FALSE) -> 36 | D7: =VLOOKUP($B$3,$A$23:$H$51,4,FALSE) -> 75 | E7: =VLOOKUP($B$3,$A$23:$H$51,5,FALSE) -> 19 | F7: =VLOOKUP($B$3,$A$23:$H$51,6,FALSE) -> 25 | G7: =VLOOKUP($B$3,$A$23:$H$51,7,FALSE) -> 23
A8: Target | B8: 93 | C8: 93 | D8: 95 | E8: 93 | F8: 93 | G8: 93
A9: Manual Cost | B9: =IF(B8<=B7,0,SUM(OFFSET($B$75,B7+1,0,B8-B7))*IF(B6=$B$4,0.5,1)) -> 1654 | C9: =IF(C8<=C7,0,SUM(OFFSET($B$75,C7+1,0,C8-C7))*IF(C6=$B$4,0.5,1)) -> 1606 | D9: =IF(D8<=D7,0,SUM(OFFSET($B$75,D7+1,0,D8-D7))*IF(D6=$B$4,0.5,1)) -> 600 | E9: =IF(E8<=E7,0,SUM(OFFSET($B$75,E7+1,0,E8-E7))*IF(E6=$B$4,0.5,1)) -> 1662 | F9: =IF(F8<=F7,0,SUM(OFFSET($B$75,F7+1,0,F8-F7))*IF(F6=$B$4,0.5,1)) -> 1645 | G9: =IF(G8<=G7,0,SUM(OFFSET($B$75,G7+1,0,G8-G7))*IF(G6=$B$4,0.5,1)) -> 1651
A11: Decor Bonus | B11: FALSE
A12: Partner Level | B12: =VLOOKUP(SUM(B8:G8)+IF(B11,10,0),D76:E105,2, TRUE) -> 28
A22: Partner | B22: Zombie | C22: Demon | D22: Angel | E22: Mutant | F22: Mecha | G22: Dragon | H22: Specialty
A23: Kim Chi-yum | B23: 43 | C23: 32 | D23: 70 | E23: 19 | F23: 11 | G23: 25 | H23: Angel
A24: Athena | B24: 16 | C24: 18 | D24: 76 | E24: 38 | F24: 22 | G24: 30 | H24: Angel
A25: Toraemon | B25: 12 | C25: 20 | D25: 73 | E25: 42 | F25: 22 | G25: 31 | H25: Angel
A26: Leeku | B26: 8 | C26: 25 | D26: 71 | E26: 16 | F26: 55 | G26: 25 | H26: Angel
A27: Son of Will | B27: 22 | C27: 36 | D27: 75 | E27: 19 | F27: 25 | G27: 23 | H27: Angel
A28: Prince Nerd | B28: 70 | C28: 45 | D28: 8 | E28: 18 | F28: 29 | G28: 30 | H28: Zombie
A29: Ghost Zadako | B29: 73 | C29: 20 | D29: 12 | E29: 22 | F29: 42 | G29: 31 | H29: Zombie
A30: Sewer Turtle | B30: 71 | C30: 12 | D30: 43 | E30: 32 | F30: 25 | G30: 17 | H30: Zombie
A31: Nito UR | B31: 71 | C31: 14 | D31: 41 | E31: 30 | F31: 25 | G31: 19 | H31: Zombie
A32: Babyeater | B32: 76 | C32: 32 | D32: 27 | E32: 43 | F32: 18 | G32: 4 | H32: Zombie
A33: Big Gal Park | B33: 22 | C33: 71 | D33: 32 | E33: 42 | F33: 14 | G33: 19 | H33: Demon
A34: Red Doe | B34: 8 | C34: 70 | D34: 47 | E34: 24 | F34: 26 | G34: 25 | H34: Demon
... A51: Dragoness Hub | B51: 33 | C51: 20 | D51: 18 | E51: 26 | F51: 27 | G51: 76 | H51: Dragon
A75: Research Level | B75: Manual Cost | D75: Total Research | E75: Partner Level
A76: 1 | B76: 1 | D76: 0 | E76: 1
A77: 2 | B77: 1 | D77: 180 | E77: 2
A78: 3 | B78: 1 | D78: 190 | E78: 3
A79: 4 | B79: 1 | D79: 200 | E79: 4
A80: 5 | B80: 1 | D80: 210 | E80: 5
A81: 6 | B81: 1 | D81: 220 | E81: 6
A82: 7 | B82: 1 | D82: 230 | E82: 7
A83: 8 | B83: 1 | D83: 240 | E83: 8
A84: 9 | B84: 1 | D84: 250 | E84: 9
A85: 10 | B85: 1 | D85: 260 | E85: 10
A86: 11 | B86: 2 | D86: 270 | E86: 11
A87: 12 | B87: 2 | D87: 285 | E87: 12
... A105: 30 | B105: 3 | D105: 600 | E105: 30
A106: 31 | B106: 4
A107: 32 | B107: 4
A108: 33 | B108: 4
A109: 34 | B109: 4
A110: 35 | B110: 4
A111: 36 | B111: 4
A112: 37 | B112: 4
A113: 38 | B113: 4
A114: 39 | B114: 4
A115: 40 | B115: 4
A116: 41 | B116: 5
A117: 42 | B117: 5
... A175: 100 | B175: 800

Sheet DNA Costs
A1: T5 -> T6 Research | H1: T6 -> T7 Research | O1: T7 -> T8 Research
A2: 1A - HP Up III | B2: Time | C2: Cells | D2: Btads | F2: DNA Points | H2: 1A - Troop DEF Up III | I2: Time (hours) | J2: Cells | K2: Btads | M2: DNA Points | O2: 1A - HP Up IV | P2: Time (days) | Q2: Cells | R2: Btads | T2: DNA Points
A3: 1 | B3: 6 | C3: 4000 | D3: 10000 | E3: Snail HP +60 | F3: 80 | H3: 1 | I3: 12 | J3: 10000 | K3: 50000 | L3: Per 30 Minions, Troop DEF +9 | M3: 120 | O3: 1 | P3: 2 | Q3: 20000 | R3: 200000 | S3: Snail HP +180 | T3: 200
A4: 2 | B4: 9 | C4: 5000 | D4: 12500 | E4: Snail HP +140 | F4: 120 | H4: 2 | I4: 20 | J4: 12500 | K4: 62500 | L4: Per 30 Minions, Troop DEF +18 | M4: 180 | O4: 2 | P4: 3 | Q4: 25000 | R4: 250000 | S4: Snail HP +390 | T4: 300
A5: 3 | B5: 12 | C5: 6000 | D5: 15000 | E5: Snail HP +240 | F5: 160 | H5: 3 | I5: 28 | J5: 15000 | K5: 75000 | L5: Per 30 Minions, Troop DEF +27 | M5: 240 | O5: 3 | P5: 4 | Q5: 30000 | R5: 300000 | S5: Snail HP +630 | T5: 400
A6: 4 | B6: 15 | C6: 7000 | D6: 17500 | E6: Snail HP +360 | F6: 200 | H6: 4 | I6: 36 | J6: 17500 | K6: 87500 | L6: Per 30 Minions, Troop DEF +36 | M6: 300 | O6: 4 | P6: 5 | Q6: 35000 | R6: 350000 | S6: Snail HP +900 | T6: 500
A7: 5 | B7: 18 | C7: 8000 | D7: 20000 | E7: Snail HP +500 | F7: 240 | H7: 5 | I7: 44 | J7: 20000 | K7: 100000 | L7: Per 30 Minions, Troop DEF +45 | M7: 360 | O7: 5 | P7: 6 | Q7: 40000 | R7: 400000 | S7: Snail HP +1200 | T7: 600
A8: 6 | B8: 21 | C8: 9000 | D8: 22500 | E8: Snail HP +660 | F8: 280 | H8: 6 | I8: 52 | J8: 22500 | K8: 112500 | L8: Per 30 Minions, Troop DEF +54 | M8: 420 | O8: 6 | P8: 7 | Q8: 45000 | R8: 450000 | S8: Snail HP +1530 | T8: 700
A9: 7 | B9: 24 | C9: 10000 | D9: 25000 | E9: Snail HP +840 | F9: 320 | H9: 7 | I9: 60 | J9: 25000 | K9: 125000 | L9: Per 30 Minions, Troop DEF +63 | M9: 480 | O9: 7 | P9: 8 | Q9: 50000 | R9: 500000 | S9: Snail HP +1890 | T9: 800
A10: 8 | B10: 27 | C10: 11000 | D10: 25000 | E10: Snail HP +1,040 | F10: 360 | H10: 8 | I10: 68 | J10: 27500 | K10: 137500 | L10: Per 30 Minions, Troop DEF +72 | M10: 540 | O10: 8 | P10: 9 | Q10: 55000 | R10: 550000 | S10: Snail HP +2280 | T10: 900
A11: 9 | B11: 30 | C11: 12000 | D11: 30000 | E11: Snail HP +1,260 | F11: 400 | H11: 9 | I11: 76 | J11: 30000 | K11: 150000 | L11: Per 30 Minions, Troop DEF +81 | M11: 600 | O11: 9 | P11: 10 | Q11: 60000 | R11: 600000 | S11: Snail HP +2700 | T11: 1000
A12: 10 | B12: 33 | C12: 13000 | D12: 32500 | E12: Snail HP +1,500 | F12: 440 | H12: 10 | I12: 84 | J12: 32500 | K12: 162500 | L12: Per 30 Minions, Troop DEF +90 | M12: 660 | O12: 10 | P12: 11 | Q12: 65000 | R12: 650000 | S12: Snail HP +3150 | T12: 1100
A13: Total | B13: =SUM(B3:B12) -> 195 | C13: =SUM(C3:C12) -> 85000 | D13: =SUM(D3:D12) -> 210000 | F13: =SUM(F3:F12) -> 2600 | H13: Total | I13: =SUM(I3:I12) -> 480 | J13: =SUM(J3:J12) -> 212500 | K13: =SUM(K3:K12) -> 1062500 | M13: =SUM(M3:M12) -> 3900 | O13: Total | P13: =SUM(P3:P12) -> 65 | Q13: =SUM(Q3:Q12) -> 425000 | R13: =SUM(R3:R12) -> 4250000 | T13: =SUM(T3:T12) -> 6500
A16: 1B - ATK Up III | C16: Cells | D16: Btads | F16: DNA Points | H16: 1B - Troop RUSH Up III | J16: Cells | K16: Btads | M16: DNA Points | O16: 1B - ATK Up IV | Q16: Cells | R16: Btads | T16: DNA Points
A17: 1 | B17: 8 | C17: 6000 | D17: 15000 | E17: Snail ATK +12 | F17: 90 | H17: 1 | I17: 15 | J17: 12000 | K17: 60000 | L17: Per 30 Minions, Troop RUSH +9 | M17: 140 | O17: 1 | P17: 4 | Q17: 32000 | R17: 320000 | S17: Snail ATK +36 | T17: 240
A18: 2 | B18: 12 | C18: 7500 | D18: 18750 | E18: Snail ATK +28 | F18: 135 | H18: 2 | I18: 25 | J18: 15000 | K18: 75000 | L18: Per 30 Minions, Troop RUSH +18 | M18: 210 | O18: 2 | P18: 6 | Q18: 40000 | R18: 400000 | S18: Snail ATK +78 | T18: 360
A19: 3 | B19: 16 | C19: 9000 | D19: 22500 | E19: Snail ATK +48 | F19: 180 | H19: 3 | I19: 35 | J19: 18000 | K19: 90000 | L19: Per 30 Minions, Troop RUSH +27 | M19: 280 | O19: 3 | P19: 8 | Q19: 48000 | R19: 480000 | S19: Snail ATK +126 | T19: 480
A20: 4 | B20: 20 | C20: 10500 | D20: 26250 | E20: Snail ATK +72 | F20: 225 | H20: 4 | I20: 45 | J20: 21000 | K20: 105000 | L20: Per 30 Minions, Troop RUSH +36 | M20: 350 | O20: 4 | P20: 10 | Q20: 56000 | R20: 560000 | S20: Snail ATK +180 | T20: 600
A21: 5 | B21: 24 | C21: 12000 | D21: 30000 | E21: Snail ATK +100 | F21: 270 | H21: 5 | I21: 55 | J21: 24000 | K21: 120000 | L21: Per 30 Minions, Troop RUSH +45 | M21: 420 | O21: 5 | P21: 12 | Q21: 64000 | R21: 640000 | S21: Snail ATK +240 | T21: 720
A22: 6 | B22: 28 | C22: 13500 | D22: 37500 | E22: Snail ATK +132 | F22: 315 | H22: 6 | I22: 65 | J22: 27000 | K22: 135000 | L22: Per 30 Minions, Troop RUSH +54 | M22: 490 | O22: 6 | P22: 14 | Q22: 72000 | R22: 720000 | S22: Snail ATK +306 | T22: 840
A23: 7 | B23: 32 | C23: 15000 | D23: 37500 | E23: Snail ATK +168 | F23: 360 | H23: 7 | I23: 75 | J23: 30000 | K23: 150000 | L23: Per 30 Minions, Troop RUSH +63 | M23: 560 | O23: 7 | P23: 16 | Q23: 80000 | R23: 800000 | S23: Snail ATK +378 | T23: 960
A24: 8 | B24: 36 | C24: 16500 | D24: 41250 | E24: Snail ATK +208 | F24: 405 | H24: 8 | I24: 85 | J24: 33000 | K24: 165000 | L24: Per 30 Minions, Troop RUSH +72 | M24: 630 | O24: 8 | P24: 18 | Q24: 88000 | R24: 880000 | S24: Snail ATK +456 | T24: 1080
A25: 9 | B25: 40 | C25: 18000 | D25: 45000 | E25: Snail ATK +252 | F25: 450 | H25: 9 | I25: 95 | J25: 36000 | K25: 180000 | L25: Per 30 Minions, Troop RUSH +81 | M25: 700 | O25: 9 | P25: 20 | Q25: 96000 | R25: 960000 | S25: Snail ATK +540 | T25: 1200
A26: 10 | B26: 44 | C26: 19500 | D26: 48750 | E26: Snail ATK +300 | F26: 495 | H26: 10 | I26: 105 | J26: 39000 | K26: 195000 | L26: Per 30 Minions, Troop RUSH +90 | M26: 770 | O26: 10 | P26: 22 | Q26: 104000 | R26: 1040000 | S26: Snail ATK +630 | T26: 1320
A27: Total | B27: =SUM(B17:B26) -> 260 | C27: =SUM(C17:C26) -> 127500 | D27: =SUM(D17:D26) -> 322500 | F27: =SUM(F17:F26) -> 2925 | H27: Total | I27: =SUM(I17:I26) -> 600 | J27: =SUM(J17:J26) -> 255000 | K27: =SUM(K17:K26) -> 1275000 | M27: =SUM(M17:M26) -> 4550 | O27: Total | P27: =SUM(P17:P26) -> 130 | Q27: =SUM(Q17:Q26) -> 680000 | R27: =SUM(R17:R26) -> 6800000 | T27: =SUM(T17:T26) -> 7800
A30: 1C - AFFCT Up III | C30: Cells | D30: Btads | F30: DNA Points | H30: 1C - Troop HARD Up III | J30: Cells | K30: Btads | M30: DNA Points | O30: 1C - AFFCT Up IV | Q30: Cells | R30: Btads | T30: DNA Points
A31: 1 | B31: 10 | C31: 8000 | D31: 20000 | E31: AFFCT +30 | F31: 100 | H31: 1 | I31: 18 | J31: 16000 | K31: 80000 | L31: Per 30 Minions, Troop HARD +3 | M31: 160 | O31: 1 | P31: 6 | Q31: 48000 | R31: 480000 | S31: AFFCT +60 | T31: 280
A32: 2 | B32: 15 | C32: 10000 | D32: 25000 | E32: AFFCT +70 | F32: 150 | H32: 2 | I32: 30 | J32: 20000 | K32: 100000 | L32: Per 30 Minions, Troop HARD +6 | M32: 240 | O32: 2 | P32: 9 | Q32: 60000 | R32: 600000 | S32: AFFCT +130 | T32: 420
A33: 3 | B33: 20 | C33: 12000 | D33: 30000 | E33: AFFCT +120 | F33: 200 | H33: 3 | I33: 42 | J33: 24000 | K33: 120000 | L33: Per 30 Minions, Troop HARD +9 | M33: 320 | O33: 3 | P33: 12 | Q33: 72000 | R33: 720000 | S33: AFFCT +210 | T33: 560
A34: 4 | B34: 25 | C34: 14000 | D34: 35000 | E34: AFFCT +180 | F34: 250 | H34: 4 | I34: 54 | J34: 28000 | K34: 140000 | L34: Per 30 Minions, Troop HARD +12 | M34: 400 | O34: 4 | P34: 15 | Q34: 84000 | R34: 840000 | S34: AFFCT +300 | T34: 700
A35: 5 | B35: 30 | C35: 16000 | D35: 40000 | E35: AFFCT +250 | F35: 300 | H35: 5 | I35: 66 | J35: 32000 | K35: 160000 | L35: Per 30 Minions, Troop HARD +15 | M35: 480 | O35: 5 | P35: 18 | Q35: 96000 | R35: 960000 | S35: AFFCT +400 | T35: 840
A36: 6 | B36: 35 | C36: 18000 | D36: 45000 | E36: AFFCT +330 | F36: 350 | H36: 6 | I36: 78 | J36: 36000 | K36: 180000 | L36: Per 30 Minions, Troop HARD +18 | M36: 560 | O36: 6 | P36: 21 | Q36: 108000 | R36: 1080000 | S36: AFFCT +510 | T36: 980
A37: 7 | B37: 40 | C37: 20000 | D37: 50000 | E37: AFFCT +420 | F37: 400 | H37: 7 | I37: 90 | J37: 40000 | K37: 200000 | L37: Per 30 Minions, Troop HARD +21 | M37: 640 | O37: 7 | P37: 24 | Q37: 120000 | R37: 1200000 | S37: AFFCT +630 | T37: 1120
A38: 8 | B38: 45 | C38: 22000 | D38: 55000 | E38: AFFCT +520 | F38: 450 | H38: 8 | I38: 102 | J38: 44000 | K38: 220000 | L38: Per 30 Minions, Troop HARD +24 | M38: 720 | O38: 8 | P38: 27 | Q38: 132000 | R38: 1320000 | S38: AFFCT +760 | T38: 1260
A39: 9 | B39: 50 | C39: 24000 | D39: 60000 | E39: AFFCT +630 | F39: 500 | H39: 9 | I39: 114 | J39: 48000 | K39: 240000 | L39: Per 30 Minions, Troop HARD +27 | M39: 800 | O39: 9 | P39: 30 | Q39: 144000 | R39: 1440000 | S39: AFFCT +900 | T39: 1400
A40: 10 | B40: 55 | C40: 26000 | D40: 65000 | E40: AFFCT +750 | F40: 550 | H40: 10 | I40: 126 | J40: 52000 | K40: 260000 | L40: Per 30 Minions, Troop HARD +30 | M40: 880 | O40: 10 | P40: 33 | Q40: 156000 | R40: 1560000 | S40: AFFCT +1050 | T40: 1540
A41: Total | B41: =SUM(B31:B40) -> 325 | C41: =SUM(C31:C40) -> 170000 | D41: =SUM(D31:D40) -> 425000 | F41: =SUM(F31:F40) -> 3250 | H41: Total | I41: =SUM(I31:I40) -> 720 | J41: =SUM(J31:J40) -> 340000 | K41: =SUM(K31:K40) -> 1700000 | M41: =SUM(M31:M40) -> 5200 | O41: Total | P41: =SUM(P31:P40) -> 195 | Q41: =SUM(Q31:Q40) -> 1020000 | R41: =SUM(R31:R40) -> 10200000 | T41: =SUM(T31:T40) -> 9100
A44: 2A - HP Up Gene III | C44: Cells | D44: Btads | F44: DNA Points | H44: 2A - DEF Up III | J44: Cells | K44: Btads | M44: DNA Points | O44: 2A - HP Up Gene IV | Q44: Cells | R44: Btads | T44: DNA Points
A45: 1 | B45: 6 | C45: 4000 | D45: 10000 | E45: Per 30 Minions, Troop HP +90 | F45: 80 | H45: 1 | I45: 12 | J45: 10000 | K45: 50000 | L45: Snail DEF +12 | M45: 120 | O45: 1 | P45: 2 | Q45: 20000 | R45: 200000 | S45: Per 60 Minions, Troop HP +300 | T45: 200
A46: 2 | B46: 9 | C46: 5000 | D46: 12500 | E46: Per 30 Minions, Troop HP +180 | F46: 120 | H46: 2 | I46: 20 | J46: 12500 | K46: 62500 | L46: Snail DEF +28 | M46: 180 | O46: 2 | P46: 3 | Q46: 25000 | R46: 250000 | S46: Per 60 Minions, Troop HP +600 | T46: 300
A47: 3 | B47: 12 | C47: 6000 | D47: 15000 | E47: Per 30 Minions, Troop HP +270 | F47: 160 | H47: 3 | I47: 28 | J47: 15000 | K47: 75000 | L47: Snail DEF +48 | M47: 240 | O47: 3 | P47: 4 | Q47: 30000 | R47: 300000 | S47: Per 60 Minions, Troop HP +900 | T47: 400
A48: 4 | B48: 15 | C48: 7000 | D48: 17500 | E48: Per 30 Minions, Troop HP +360 | F48: 200 | H48: 4 | I48: 36 | J48: 17500 | K48: 87500 | L48: Snail DEF +72 | M48: 300 | O48: 4 | P48: 5 | Q48: 35000 | R48: 350000 | S48: Per 60 Minions, Troop HP +1200 | T48: 500
A49: 5 | B49: 18 | C49: 8000 | D49: 20000 | E49: Per 30 Minions, Troop HP +450 | F49: 240 | H49: 5 | I49: 44 | J49: 20000 | K49: 100000 | L49: Snail DEF +100 | M49: 360 | O49: 5 | P49: 6 | Q49: 40000 | R49: 400000 | S49: Per 60 Minions, Troop HP +1500 | T49: 600
A50: 6 | B50: 21 | C50: 9000 | D50: 22500 | E50: Per 30 Minions, Troop HP +540 | F50: 280 | H50: 6 | I50: 52 | J50: 22500 | K50: 112500 | L50: Snail DEF +132 | M50: 420 | O50: 6 | P50: 7 | Q50: 45000 | R50: 450000 | S50: Per 60 Minions, Troop HP +1800 | T50: 700
A51: 7 | B51: 24 | C51: 10000 | D51: 25000 | E51: Per 30 Minions, Troop HP +630 | F51: 320 | H51: 7 | I51: 60 | J51: 25000 | K51: 125000 | L51: Snail DEF +168 | M51: 480 | O51: 7 | P51: 8 | Q51: 50000 | R51: 500000 | S51: Per 60 Minions, Troop HP +2100 | T51: 800
A52: 8 | B52: 27 | C52: 11000 | D52: 27500 | E52: Per 30 Minions, Troop HP +720 | F52: 360 | H52: 8 | I52: 68 | J52: 27500 | K52: 137500 | L52: Snail DEF +208 | M52: 540 | O52: 8 | P52: 9 | Q52: 55000 | R52: 550000 | S52: Per 60 Minions, Troop HP +2400 | T52: 900
A53: 9 | B53: 30 | C53: 12000 | D53: 30000 | E53: Per 30 Minions, Troop HP +810 | F53: 400 | H53: 9 | I53: 76 | J53: 30000 | K53: 150000 | L53: Snail DEF +252 | M53: 600 | O53: 9 | P53: 10 | Q53: 60000 | R53: 600000 | S53: Per 60 Minions, Troop HP +2700 | T53: 1000
A54: 10 | B54: 33 | C54: 13000 | D54: 32500 | E54: Per 30 Minions, Troop HP +900 | F54: 440 | H54: 10 | I54: 84 | J54: 32500 | K54: 162500 | L54: Snail DEF +300 | M54: 660 | O54: 10 | P54: 11 | Q54: 65000 | R54: 650000 | S54: Per 60 Minions, Troop HP +3000 | T54: 1100
A55: Total | B55: =SUM(B45:B54) -> 195 | C55: =SUM(C45:C54) -> 85000 | D55: =SUM(D45:D54) -> 212500 | F55: =SUM(F45:F54) -> 2600 | H55: Total | I55: =SUM(I45:I54) -> 480 | J55: =SUM(J45:J54) -> 212500 | K55: =SUM(K45:K54) -> 1062500 | M55: =SUM(M45:M54) -> 3900 | O55: Total | P55: =SUM(P45:P54) -> 65 | Q55: =SUM(Q45:Q54) -> 425000 | R55: =SUM(R45:R54) -> 4250000 | T55: =SUM(T45:T54) -> 6500
A58: 2B - ATK Up Gene III | C58: Cells | D58: Btads | F58: DNA Points | H58: 2B - RUSH Up III | J58: Cells | K58: Btads | M58: DNA Points | O58: 2B - ATK Up Gene IV | Q58: Cells | R58: Btads | T58: DNA Points
A59: 1 | B59: 8 | C59: 6000 | D59: 15000 | E59: Per 30 Minions, Troop ATK +9 | F59: 90 | H59: 1 | I59: 15 | J59: 12000 | K59: 60000 | L59: Snail RUSH +12 | M59: 140 | O59: 1 | P59: 4 | Q59: 32000 | R59: 320000 | S59: Per 60 Minions, Troop ATK +30 | T59: 240
A60: 2 | B60: 12 | C60: 7500 | D60: 18750 | E60: Per 30 Minions, Troop ATK +18 | F60: 135 | H60: 2 | I60: 25 | J60: 15000 | K60: 75000 | L60: Snail RUSH +28 | M60: 210 | O60: 2 | P60: 6 | Q60: 40000 | R60: 400000 | S60: Per 60 Minions, Troop ATK +60 | T60: 360
A61: 3 | B61: 16 | C61: 9000 | D61: 22500 | E61: Per 30 Minions, Troop ATK +27 | F61: 180 | H61: 3 | I61: 35 | J61: 18000 | K61: 90000 | L61: Snail RUSH +48 | M61: 280 | O61: 3 | P61: 8 | Q61: 48000 | R61: 480000 | S61: Per 60 Minions, Troop ATK +90 | T61: 480
A62: 4 | B62: 20 | C62: 10500 | D62: 26250 | E62: Per 30 Minions, Troop ATK +36 | F62: 25 | H62: 4 | I62: 45 | J62: 21000 | K62: 105000 | L62: Snail RUSH +72 | M62: 350 | O62: 4 | P62: 10 | Q62: 56000 | R62: 560000 | S62: Per 60 Minions, Troop ATK +120 | T62: 600
A63: 5 | B63: 24 | C63: 12000 | D63: 30000 | E63: Per 30 Minions, Troop ATK +45 | F63: 270 | H63: 5 | I63: 55 | J63: 24000 | K63: 120000 | L63: Snail RUSH +100 | M63: 420 | O63: 5 | P63: 12 | Q63: 64000 | R63: 640000 | S63: Per 60 Minions, Troop ATK +150 | T63: 720
A64: 6 | B64: 28 | C64: 13500 | D64: 33750 | E64: Per 30 Minions, Troop ATK +54 | F64: 315 | H64: 6 | I64: 65 | J64: 27000 | K64: 135000 | L64: Snail RUSH +132 | M64: 490 | O64: 6 | P64: 14 | Q64: 72000 | R64: 720000 | S64: Per 60 Minions, Troop ATK +180 | T64: 840
A65: 7 | B65: 32 | C65: 15000 | D65: 37500 | E65: Per 30 Minions, Troop ATK +63 | F65: 360 | H65: 7 | I65: 75 | J65: 30000 | K65: 150000 | L65: Snail RUSH +168 | M65: 560 | O65: 7 | P65: 16 | Q65: 80000 | R65: 800000 | S65: Per 60 Minions, Troop ATK +210 | T65: 960
A66: 8 | B66: 36 | C66: 16500 | D66: 41250 | E66: Per 30 Minions, Troop ATK +72 | F66: 405 | H66: 8 | I66: 85 | J66: 33000 | K66: 165000 | L66: Snail RUSH +208 | M66: 630 | O66: 8 | P66: 18 | Q66: 88000 | R66: 880000 | S66: Per 60 Minions, Troop ATK +240 | T66: 1080
A67: 9 | B67: 40 | C67: 18000 | D67: 45000 | E67: Per 30 Minions, Troop ATK +81 | F67: 450 | H67: 9 | I67: 95 | J67: 36000 | K67: 180000 | L67: Snail RUSH +252 | M67: 700 | O67: 9 | P67: 20 | Q67: 96000 | R67: 960000 | S67: Per 60 Minions, Troop ATK +270 | T67: 1200
A68: 10 | B68: 44 | C68: 19500 | D68: 48750 | E68: Per 30 Minions, Troop ATK +90 | F68: 495 | H68: 10 | I68: 105 | J68: 39000 | K68: 195000 | L68: Snail RUSH +300 | M68: 770 | O68: 10 | P68: 22 | Q68: 104000 | R68: 1040000 | S68: Per 60 Minions, Troop ATK +300 | T68: 1320
A69: Total | B69: =SUM(B59:B68) -> 260 | C69: =SUM(C59:C68) -> 127500 | D69: =SUM(D59:D68) -> 318750 | F69: =SUM(F59:F68) -> 2725 | H69: Total | I69: =SUM(I59:I68) -> 600 | J69: =SUM(J59:J68) -> 255000 | K69: =SUM(K59:K68) -> 1275000 | M69: =SUM(M59:M68) -> 4550 | O69: Total | P69: =SUM(P59:P68) -> 130 | Q69: =SUM(Q59:Q68) -> 680000 | R69: =SUM(R59:R68) -> 6800000 | T69: =SUM(T59:T68) -> 7800
A72: 2C - All Genes Up III | C72: Cells | D72: Btads | F72: DNA Points | H72: 2C - AFFCT Up III | J72: Cells | K72: Btads | M72: DNA Points | O72: 2C - All Genes Up IV | Q72: Cells | R72: Btads | T72: DNA Points
A73: 1 | B73: 10 | C73: 8000 | D73: 20000 | E73: Per 30 Minions, Troop HARD +3 | F73: 100 | H73: 1 | I73: 18 | J73: 16000 | K73: 80000 | L73: AFFCT +30 | M73: 160 | O73: 1 | P73: 6 | Q73: 48000 | R73: 480000 | S73: Per 60 Minions, Troop HARD +10 | T73: 280
A74: 2 | B74: 15 | C74: 10000 | D74: 25000 | E74: Per 30 Minions, Troop HARD +6 | F74: 150 | H74: 2 | I74: 30 | J74: 20000 | K74: 100000 | L74: AFFCT +70 | M74: 240 | O74: 2 | P74: 9 | Q74: 60000 | R74: 600000 | S74: Per 60 Minions, Troop HARD +20 | T74: 420
A75: 3 | B75: 20 | C75: 12000 | D75: 30000 | E75: Per 30 Minions, Troop HARD +9 | F75: 200 | H75: 3 | I75: 42 | J75: 24000 | K75: 120000 | L75: AFFCT +120 | M75: 320 | O75: 3 | P75: 12 | Q75: 72000 | R75: 720000 | S75: Per 60 Minions, Troop HARD +30 | T75: 560
A76: 4 | B76: 25 | C76: 14000 | D76: 35000 | E76: Per 30 Minions, Troop HARD +12 | F76: 250 | H76: 4 | I76: 54 | J76: 28000 | K76: 140000 | L76: AFFCT +180 | M76: 400 | O76: 4 | P76: 15 | Q76: 84000 | R76: 840000 | S76: Per 60 Minions, Troop HARD +40 | T76: 700
A77: 5 | B77: 30 | C77: 16000 | D77: 40000 | E77: Per 30 Minions, Troop HARD +15 | F77: 300 | H77: 5 | I77: 66 | J77: 32000 | K77: 160000 | L77: AFFCT +250 | M77: 480 | O77: 5 | P77: 18 | Q77: 96000 | R77: 960000 | S77: Per 60 Minions, Troop HARD +50 | T77: 840
A78: 6 | B78: 35 | C78: 18000 | D78: 45000 | E78: Per 30 Minions, Troop HARD +18 | F78: 350 | H78: 6 | I78: 78 | J78: 36000 | K78: 180000 | L78: AFFCT +330 | M78: 560 | O78: 6 | P78: 21 | Q78: 108000 | R78: 1080000 | S78: Per 60 Minions, Troop HARD +60 | T78: 980
A79: 7 | B79: 40 | C79: 20000 | D79: 50000 | E79: Per 30 Minions, Troop HARD +21 | F79: 400 | H79: 7 | I79: 90 | J79: 40000 | K79: 200000 | L79: AFFCT +420 | M79: 640 | O79: 7 | P79: 24 | Q79: 120000 | R79: 1200000 | S79: Per 60 Minions, Troop HARD +70 | T79: 1120
A80: 8 | B80: 45 | C80: 22000 | D80: 55000 | E80: Per 30 Minions, Troop HARD +24 | F80: 450 | H80: 8 | I80: 102 | J80: 44000 | K80: 220000 | L80: AFFCT +520 | M80: 720 | O80: 8 | P80: 27 | Q80: 132000 | R80: 1320000 | S80: Per 60 Minions, Troop HARD +80 | T80: 1260
A81: 9 | B81: 50 | C81: 24000 | D81: 60000 | E81: Per 30 Minions, Troop HARD +27 | F81: 500 | H81: 9 | I81: 114 | J81: 48000 | K81: 240000 | L81: AFFCT +630 | M81: 800 | O81: 9 | P81: 30 | Q81: 144000 | R81: 1440000 | S81: Per 60 Minions, Troop HARD +90 | T81: 1400
A82: 10 | B82: 55 | C82: 26000 | D82: 65000 | E82: Per 30 Minions, Troop HARD +30 | F82: 550 | H82: 10 | I82: 126 | J82: 52000 | K82: 260000 | L82: AFFCT +750 | M82: 880 | O82: 10 | P82: 33 | Q82: 156000 | R82: 1560000 | S82: Per 60 Minions, Troop HARD +100 | T82: 1540
A83: Total | B83: =SUM(B73:B82) -> 325 | C83: =SUM(C73:C82) -> 170000 | D83: =SUM(D73:D82) -> 425000 | F83: =SUM(F73:F82) -> 3250 | H83: Total | I83: =SUM(I73:I82) -> 720 | J83: =SUM(J73:J82) -> 340000 | K83: =SUM(K73:K82) -> 1700000 | M83: =SUM(M73:M82) -> 5200 | O83: Total | P83: =SUM(P73:P82) -> 195 | Q83: =SUM(Q73:Q82) -> 1020000 | R83: =SUM(R73:R82) -> 10200000 | T83: =SUM(T73:T82) -> 9100
A86: 3 - Compass Upgrade | C86: Cells | D86: Btads | F86: DNA Points | H86: 3 - AA Relic + Leadership | J86: Cells | K86: Btads | M86: DNA Points | O86: 3 - SS Relic | Q86: Cells | R86: Btads | T86: DNA Points
A87: 1 | B87: 20 | C87: 20000 | D87: 50000 | E87: All Compasses effect +40% | F87: 400 | H87: 1 | I87: 72 | J87: 50000 | K87: 120000 | L87: Leadership +10, AA Frags +20 | M87: 1800 | O87: 1 | P87: 10 | Q87: 72000 | R87: 720000 | S87: SS RelicFrags +40 | T87: 6000
A88: 2 | B88: 40 | C88: 40000 | D88: 100000 | E88: All Compasses effect +60% | F88: 450 | H88: 2 | I88: 216 | J88: 150000 | K88: 360000 | L88: Leadership +20, AA Frags +20 | M88: 2100 | O88: 2 | P88: 18 | Q88: 94000 | R88: 1040000 | S88: SS Relic Frags +40 | T88: 7000
A89: 3 | B89: 60 | C89: 60000 | D89: 150000 | E89: All Compasses effect +80% | F89: 500 | H89: 3 | I89: 360 | J89: 250000 | K89: 600000 | L89: Leadership +30, AA Frags +40 | M89: 2400 | O89: 3 | P89: 26 | Q89: 136000 | R89: 1360000 | S89: SS Relic Frags +40 | T89: 8000
A90: Total | B90: =SUM(B87:B89) -> 120 | C90: =sum(C87:C89) -> 120000 | D90: =sum(D87:D89) -> 300000 | F90: =sum(F87:F89) -> 1350 | H90: Total | I90: =SUM(I87:I89) -> 648 | J90: =sum(J87:J89) -> 450000 | K90: =sum(K87:K89) -> 1080000 | M90: =sum(M87:M89) -> 6300 | O90: 4 | P90: 34 | Q90: 168000 | R90: 1680000 | S90: SS Relic Frags +80 | T90: 9000
O91: 5 | P91: 42 | Q91: 200000 | R91: 2000000 | S91: SS Relic Frags +80 | T91: 10000
O92: Total | P92: =SUM(P87:P91) -> 130 | Q92: =sum(Q87:Q91) -> 670000 | R92: =sum(R87:R91) -> 6800000 | T92: =sum(T87:T91) -> 40000
A93: 4 - Form Ritual VI | C93: Cells | D93: Btads | F93: DNA Points | H93: 4 - Form Ritual VII | J93: Cells | K93: Btads | M93: DNA Points
A94: 1 | B94: 120 | C94: 30000 | D94: 75000 | F94: 500 | H94: 1 | I94: 720 | J94: 60000 | K94: 300000 | M94: 800
O95: 4 - Form Ritual VIII | Q95: Cells | R95: Btads | T95: DNA Points
O96: 1 | P96: 180 | Q96: 160000 | R96: 1600000 | T96: 1500
A97: T5->T6 | B97: Time (hr) | C97: Time (days) | D97: Cells | E97: B-tads | F97: DNA Points | H97: T6->T7 | I97: Time (hr) | J97: Time (days) | K97: Cells | L97: B-tads | M97: DNA Points
A98: Total | B98: =B13+B27+B41+B55+B69+B83+B90+B94 -> 1800 | C98: =B98/24 -> 75 | D98: =C13+C27+C41+C55+C69+C83+C90+C94 -> 915000 | E98: =D13+D27+D41+D55+D69+D83+D90+D94 -> 2288750 | F98: =F13+F27+F41+F55+F69+F83+F90+F94 -> 19200 | H98: Total | I98: =I13+I27+I41+I55+I69+I83+I90+I94 -> 4968 | J98: =I98/24 -> 207 | K98: =J13+J27+J41+J55+J69+J83+J90+J94 -> 2125000 | L98: =K13+K27+K41+K55+K69+K83+K90+K94 -> 9455000 | M98: =M13+M27+M41+M55+M69+M83+M90+M94 -> 34400
A99: To Center | B99: =B55+B69+B90 -> 575 | C99: =B99/24 -> 23.958333 | D99: =C55+C69+C90 -> 332500 | E99: =D55+D69+D90 -> 831250 | F99: =F55+F69+F90 -> 6675 | H99: To Center | I99: =I55+I69+I90 -> 1728 | J99: =I99/24 -> 72 | K99: =J55+J69+J90 -> 917500 | L99: =K55+K69+K90 -> 3417500 | M99: =M55+M69+M90 -> 14750 | O99: T7->T8 | P99: Time (days) | Q99: Cells | R99: B-tads | S99: DNA Points
A100: Remaining | B100: =B98-B99 -> 1225 | C100: =B100/24 -> 51.041667 | D100: =D98-D99 -> 582500 | E100: =E98-E99 -> 1457500 | F100: =F98-F99 -> 12525 | H100: Remaining | I100: =I98-I99 -> 3240 | J100: =I100/24 -> 135 | K100: =K98-K99 -> 1207500 | L100: =L98-L99 -> 6037500 | M100: =M98-M99 -> 19650 | O100: Total | P100: =P13+P27+P41+P55+P69+P83+P92+P96 -> 1090 | Q100: =Q13+Q27+Q41+Q55+Q69+Q83+Q92+Q96 -> 5080000 | R100: =R13+R27+R41+R55+R69+R83+R92+R96 -> 50900000 | S100: =T13+T27+T41+T55+T69+T83+T92+T96 -> 88300
O101: To Center | P101: =P55+P69+P92 -> 325 | Q101: =Q55+Q69+Q92 -> 1775000 | R101: =R55+R69+R92 -> 17850000 | S101: =T55+T69+T92 -> 54300
O102: Remaining | P102: =P100-P101 -> 765 | Q102: =Q100-Q101 -> 3305000 | R102: =R100-R101 -> 33050000 | S102: =S100-S101 -> 34000

Sheet Dragon DNA Costs
A1: T5 -> T6 Research | I1: T6 -> T7 Research | Q1: T7 -> T8 Research
A2: 1A - HP Up III | B2: Time | C2: Zombie | D2: Demon | E2: Btads | G2: DNA Points | I2: 1A - Troop DEF Up III | J2: Time (hours) | K2: Zombie | L2: Demon | M2: Btads | O2: DNA Points | Q2: 1A - HP Up IV | R2: Time (days) | S2: Zombie | T2: Demon | U2: Btads | W2: DNA Points
A3: 1 | B3: 6 | C3: 8100 | D3: 5400 | E3: 10000 | F3: Snail HP +60 | G3: 80 | I3: 1 | J3: 12 | K3: 17000 | L3: 11000 | M3: 50000 | N3: Per 30 Minions, Troop DEF +9 | O3: 120 | Q3: 1 | R3: 2 | S3: 45000 | T3: 30000 | U3: 200000 | V3: Snail HP +180 | W3: 200
A4: 2 | B4: 9 | C4: 10000 | D4: 6700 | E4: 12500 | F4: Snail HP +140 | G4: 120 | I4: 2 | J4: 20 | K4: 21000 | L4: 14000 | M4: 62500 | N4: Per 30 Minions, Troop DEF +18 | O4: 180 | Q4: 2 | R4: 3 | S4: 56000 | T4: 37000 | U4: 250000 | V4: Snail HP +390 | W4: 300
A5: 3 | B5: 12 | C5: 12000 | D5: 8100 | E5: 15000 | F5: Snail HP +240 | G5: 160 | I5: 3 | J5: 28 | K5: 25000 | L5: 17000 | M5: 75000 | N5: Per 30 Minions, Troop DEF +27 | O5: 240 | Q5: 3 | R5: 4 | S5: 67000 | T5: 45000 | U5: 300000 | V5: Snail HP +630 | W5: 400
A6: 4 | B6: 15 | C6: 14000 | D6: 9400 | E6: 17500 | F6: Snail HP +360 | G6: 200 | I6: 4 | J6: 36 | K6: 29000 | L6: 19000 | M6: 87500 | N6: Per 30 Minions, Troop DEF +36 | O6: 300 | Q6: 4 | R6: 5 | S6: 78000 | T6: 52000 | U6: 350000 | V6: Snail HP +900 | W6: 500
A7: 5 | B7: 18 | C7: 16000 | D7: 10000 | E7: 20000 | F7: Snail HP +500 | G7: 240 | I7: 5 | J7: 44 | K7: 34000 | L7: 22000 | M7: 100000 | N7: Per 30 Minions, Troop DEF +45 | O7: 360 | Q7: 5 | R7: 6 | S7: 90000 | T7: 60000 | U7: 400000 | V7: Snail HP +1200 | W7: 600
A8: 6 | B8: 21 | C8: 18000 | D8: 12000 | E8: 22500 | F8: Snail HP +660 | G8: 280 | I8: 6 | J8: 52 | K8: 38000 | L8: 25000 | M8: 112500 | N8: Per 30 Minions, Troop DEF +54 | O8: 420 | Q8: 6 | R8: 7 | S8: 100000 | T8: 67000 | U8: 450000 | V8: Snail HP +1530 | W8: 700
A9: 7 | B9: 24 | C9: 20000 | D9: 13000 | E9: 25000 | F9: Snail HP +840 | G9: 320 | I9: 7 | J9: 60 | K9: 42000 | L9: 28000 | M9: 125000 | N9: Per 30 Minions, Troop DEF +63 | O9: 480 | Q9: 7 | R9: 8 | S9: 110000 | T9: 75000 | U9: 500000 | V9: Snail HP +1890 | W9: 800
A10: 8 | B10: 27 | C10: 22000 | D10: 14000 | E10: 25000 | F10: Snail HP +1,040 | G10: 360 | I10: 8 | J10: 68 | K10: 47000 | L10: 31000 | M10: 137500 | N10: Per 30 Minions, Troop DEF +72 | O10: 540 | Q10: 8 | R10: 9 | S10: 120000 | T10: 82000 | U10: 550000 | V10: Snail HP +2280 | W10: 900
A11: 9 | B11: 30 | C11: 24000 | D11: 16000 | E11: 30000 | F11: Snail HP +1,260 | G11: 400 | I11: 9 | J11: 76 | K11: 51000 | L11: 34000 | M11: 150000 | N11: Per 30 Minions, Troop DEF +81 | O11: 600 | Q11: 9 | R11: 10 | S11: 130000 | T11: 90000 | U11: 600000 | V11: Snail HP +2700 | W11: 1000
A12: 10 | B12: 33 | C12: 26000 | D12: 17000 | E12: 32500 | F12: Snail HP +1,500 | G12: 440 | I12: 10 | J12: 84 | K12: 55000 | L12: 37000 | M12: 162500 | N12: Per 30 Minions, Troop DEF +90 | O12: 660 | Q12: 10 | R12: 11 | S12: 140000 | T12: 97000 | U12: 650000 | V12: Snail HP +3150 | W12: 1100
A13: Total | B13: =SUM(B3:B12) -> 195 | C13: =SUM(C3:C12) -> 170100 | D13: =SUM(D3:D12) -> 111600 | E13: =SUM(E3:E12) -> 210000 | G13: =SUM(G3:G12) -> 2600 | I13: Total | J13: =SUM(J3:J12) -> 480 | K13: =SUM(K3:K12) -> 359000 | L13: =SUM(L3:L12) -> 238000 | M13: =SUM(M3:M12) -> 1062500 | O13: =SUM(O3:O12) -> 3900 | Q13: Total | R13: =SUM(R3:R12) -> 65 | S13: =SUM(S3:S12) -> 936000 | T13: =SUM(T3:T12) -> 635000 | U13: =SUM(U3:U12) -> 4250000 | W13: =SUM(W3:W12) -> 6500
A16: 1B - ATK Up III | C16: Angel | D16: Mutant | E16: Btads | G16: DNA Points | I16: 1B - Troop RUSH Up III | K16: Angel | L16: Mutant | M16: Btads | Q16: 1B - ATK Up IV | S16: Angel | T16: Mutant
A17: 1 | B17: 8 | C17: 10000 | D17: 5400 | E17: 15000 | F17: Snail ATK +12 | G17: 90 | I17: 1 | J17: 15 | K17: 22000 | L17: 11000 | M17: 60000 | N17: Per 30 Minions, Troop RUSH +9 | O17: 140 | Q17: 1 | R17: 4 | S17: 63000 | T17: 30000 | U17: 320000 | V17: Snail ATK +36 | W17: 240
A18: 2 | B18: 12 | C18: 13000 | D18: 6700 | E18: 18750 | F18: Snail ATK +28 | G18: 135 | I18: 2 | J18: 25 | K18: 28000 | L18: 14000 | M18: 75000 | N18: Per 30 Minions, Troop RUSH +18 | O18: 210 | Q18: 2 | R18: 6 | S18: 78000 | T18: 37000 | U18: 400000 | V18: Snail ATK +78 | W18: 360
A19: 3 | B19: 16 | C19: 16000 | D19: 8100 | E19: 22500 | F19: Snail ATK +48 | G19: 180 | I19: 3 | J19: 35 | K19: 34000 | L19: 17000 | M19: 90000 | N19: Per 30 Minions, Troop RUSH +27 | O19: 280 | Q19: 3 | R19: 8 | U19: 480000 | V19: Snail ATK +126 | W19: 480
A20: 4 | B20: 20 | C20: 18000 | D20: 9400 | E20: 26250 | F20: Snail ATK +72 | G20: 225 | I20: 4 | J20: 45 | K20: 39000 | L20: 19000 | M20: 105000 | N20: Per 30 Minions, Troop RUSH +36 | O20: 350 | Q20: 4 | R20: 10 | U20: 560000 | V20: Snail ATK +180 | W20: 600
A21: 5 | B21: 24 | C21: 21000 | D21: 10000 | E21: 30000 | F21: Snail ATK +100 | G21: 270 | I21: 5 | J21: 55 | K21: 45000 | L21: 22000 | M21: 120000 | N21: Per 30 Minions, Troop RUSH +45 | O21: 420 | Q21: 5 | R21: 12 | U21: 640000 | V21: Snail ATK +240 | W21: 720
A22: 6 | B22: 28 | C22: 24000 | D22: 12000 | E22: 37500 | F22: Snail ATK +132 | G22: 315 | I22: 6 | J22: 65 | K22: 51000 | L22: 25000 | M22: 135000 | N22: Per 30 Minions, Troop RUSH +54 | O22: 490 | Q22: 6 | R22: 14 | U22: 720000 | V22: Snail ATK +306 | W22: 840
A23: 7 | B23: 32 | C23: 27000 | D23: 13000 | E23: 37500 | F23: Snail ATK +168 | G23: 360 | I23: 7 | J23: 75 | K23: 57000 | L23: 28000 | M23: 150000 | N23: Per 30 Minions, Troop RUSH +63 | O23: 560 | Q23: 7 | R23: 16 | S23: 170000 | T23: 86000 | U23: 800000 | V23: Snail ATK +378 | W23: 960
A24: 8 | B24: 36 | C24: 29000 | D24: 14000 | E24: 41250 | F24: Snail ATK +208 | G24: 405 | I24: 8 | J24: 85 | K24: 62000 | L24: 31000 | M24: 165000 | N24: Per 30 Minions, Troop RUSH +72 | O24: 630 | Q24: 8 | R24: 18 | U24: 880000 | V24: Snail ATK +456 | W24: 1080
A25: 9 | B25: 40 | C25: 32000 | D25: 16000 | E25: 45000 | F25: Snail ATK +252 | G25: 450 | I25: 9 | J25: 95 | K25: 68000 | L25: 34000 | M25: 180000 | N25: Per 30 Minions, Troop RUSH +81 | O25: 700 | Q25: 9 | R25: 20 | U25: 960000 | V25: Snail ATK +540 | W25: 1200
A26: 10 | B26: 44 | C26: 35000 | D26: 17000 | E26: 48750 | F26: Snail ATK +300 | G26: 495 | I26: 10 | J26: 105 | K26: 74000 | L26: 37000 | M26: 195000 | N26: Per 30 Minions, Troop RUSH +90 | O26: 770 | Q26: 10 | R26: 22 | U26: 1040000 | V26: Snail ATK +630 | W26: 1320
A27: Total | B27: =SUM(B17:B26) -> 260 | C27: =SUM(C17:C26) -> 225000 | D27: =SUM(D17:D26) -> 111600 | E27: =SUM(E17:E26) -> 322500 | G27: =SUM(G17:G26) -> 2925 | I27: Total | J27: =SUM(J17:J26) -> 600 | K27: =SUM(K17:K26) -> 480000 | L27: =SUM(L17:L26) -> 238000 | M27: =SUM(M17:M26) -> 1275000 | O27: =SUM(O17:O26) -> 4550 | Q27: Total | R27: =SUM(R17:R26) -> 130 | S27: =SUM(S17:S26) -> 311000 | T27: =SUM(T17:T26) -> 153000 | U27: =SUM(U17:U26) -> 6800000 | W27: =SUM(W17:W26) -> 7800
A30: 1C - AFFCT Up III | C30: Zombie | D30: Mecha | E30: Btads | G30: DNA Points | I30: 1C - Troop HARD Up III | K30: Zombie | L30: Mecha | M30: Btads | Q30: 1C - AFFCT Up IV | S30: Zombie | T30: Mecha
A31: 1 | B31: 10 | C31: 8100 | D31: 16000 | E31: 20000 | F31: AFFCT +30 | G31: 100 | I31: 1 | J31: 18 | K31: 17000 | L31: 34000 | M31: 80000 | N31: Per 30 Minions, Troop HARD +3 | O31: 160 | Q31: 1 | R31: 6 | S31: 45000 | T31: 90000 | U31: 480000 | V31: AFFCT +60 | W31: 280
A32: 2 | B32: 15 | C32: 10000 | D32: 20000 | E32: 25000 | F32: AFFCT +70 | G32: 150 | I32: 2 | J32: 30 | K32: 21000 | L32: 42000 | M32: 100000 | N32: Per 30 Minions, Troop HARD +6 | O32: 240 | Q32: 2 | R32: 9 | U32: 600000 | V32: AFFCT +130 | W32: 420
A33: 3 | B33: 20 | C33: 12000 | D33: 24000 | E33: 30000 | F33: AFFCT +120 | G33: 200 | I33: 3 | J33: 42 | K33: 25000 | L33: 51000 | M33: 120000 | N33: Per 30 Minions, Troop HARD +9 | O33: 320 | Q33: 3 | R33: 12 | U33: 720000 | V33: AFFCT +210 | W33: 560
A34: 4 | B34: 25 | C34: 14000 | D34: 28000 | E34: 35000 | F34: AFFCT +180 | G34: 250 | I34: 4 | J34: 54 | K34: 29000 | L34: 59000 | M34: 140000 | N34: Per 30 Minions, Troop HARD +12 | O34: 400 | Q34: 4 | R34: 15 | U34: 840000 | V34: AFFCT +300 | W34: 700
A35: 5 | B35: 30 | C35: 16000 | D35: 32000 | E35: 40000 | F35: AFFCT +250 | G35: 300 | I35: 5 | J35: 66 | K35: 34000 | L35: 68000 | M35: 160000 | N35: Per 30 Minions, Troop HARD +15 | O35: 480 | Q35: 5 | R35: 18 | U35: 960000 | V35: AFFCT +400 | W35: 840
A36: 6 | B36: 35 | C36: 18000 | D36: 36000 | E36: 45000 | F36: AFFCT +330 | G36: 350 | I36: 6 | J36: 78 | K36: 38000 | L36: 76000 | M36: 180000 | N36: Per 30 Minions, Troop HARD +18 | O36: 560 | Q36: 6 | R36: 21 | U36: 1080000 | V36: AFFCT +510 | W36: 980
A37: 7 | B37: 40 | C37: 20000 | D37: 40000 | E37: 50000 | F37: AFFCT +420 | G37: 400 | I37: 7 | J37: 90 | K37: 42000 | L37: 85000 | M37: 200000 | N37: Per 30 Minions, Troop HARD +21 | O37: 640 | Q37: 7 | R37: 24 | U37: 1200000 | V37: AFFCT +630 | W37: 1120
A38: 8 | B38: 45 | C38: 22000 | D38: 44000 | E38: 55000 | F38: AFFCT +520 | G38: 450 | I38: 8 | J38: 102 | K38: 47000 | L38: 94000 | M38: 220000 | N38: Per 30 Minions, Troop HARD +24 | O38: 720 | Q38: 8 | R38: 27 | U38: 1320000 | V38: AFFCT +760 | W38: 1260
A39: 9 | B39: 50 | C39: 24000 | D39: 48000 | E39: 60000 | F39: AFFCT +630 | G39: 500 | I39: 9 | J39: 114 | K39: 51000 | L39: 100000 | M39: 240000 | N39: Per 30 Minions, Troop HARD +27 | O39: 800 | Q39: 9 | R39: 30 | U39: 1440000 | V39: AFFCT +900 | W39: 1400
A40: 10 | B40: 55 | C40: 26000 | D40: 52000 | E40: 65000 | F40: AFFCT +750 | G40: 550 | I40: 10 | J40: 126 | K40: 55000 | L40: 110000 | M40: 260000 | N40: Per 30 Minions, Troop HARD +30 | O40: 880 | Q40: 10 | R40: 33 | U40: 1560000 | V40: AFFCT +1050 | W40: 1540
A41: Total | B41: =SUM(B31:B40) -> 325 | C41: =SUM(C31:C40) -> 170100 | D41: =SUM(D31:D40) -> 340000 | E41: =SUM(E31:E40) -> 425000 | G41: =SUM(G31:G40) -> 3250 | I41: Total | J41: =SUM(J31:J40) -> 720 | K41: =SUM(K31:K40) -> 359000 | L41: =SUM(L31:L40) -> 719000 | M41: =SUM(M31:M40) -> 1700000 | O41: =SUM(O31:O40) -> 5200 | Q41: Total | R41: =SUM(R31:R40) -> 195 | S41: =SUM(S31:S40) -> 45000 | T41: =SUM(T31:T40) -> 90000 | U41: =SUM(U31:U40) -> 10200000 | W41: =SUM(W31:W40) -> 9100
A44: 2A - HP Up Gene III | C44: Zombie | D44: Demon | E44: Btads | G44: DNA Points | I44: 2A - DEF Up III | K44: Zombie | L44: Demon | M44: Btads | Q44: 2A - HP Up Gene IV | S44: Zombie | T44: Demon
A45: 1 | B45: 6 | C45: 5400 | D45: 8100 | E45: 10000 | F45: Per 30 Minions, Troop HP +90 | G45: 80 | I45: 1 | J45: 12 | K45: 11000 | L45: 17000 | M45: 50000 | N45: Snail DEF +12 | O45: 120 | Q45: 1 | R45: 2 | S45: 30000 | T45: 45000 | U45: 200000 | V45: Per 60 Minions, Troop HP +300 | W45: 200
A46: 2 | B46: 9 | C46: 6700 | D46: 10000 | E46: 12500 | F46: Per 30 Minions, Troop HP +180 | G46: 120 | I46: 2 | J46: 20 | K46: 14000 | L46: 21000 | M46: 62500 | N46: Snail DEF +28 | O46: 180 | Q46: 2 | R46: 3 | S46: 37000 | T46: 54000 | U46: 250000 | V46: Per 60 Minions, Troop HP +600 | W46: 300
A47: 3 | B47: 12 | C47: 8100 | D47: 12000 | E47: 15000 | F47: Per 30 Minions, Troop HP +270 | G47: 160 | I47: 3 | J47: 28 | K47: 17000 | L47: 25000 | M47: 75000 | N47: Snail DEF +48 | O47: 240 | Q47: 3 | R47: 4 | S47: 45000 | T47: 65000 | U47: 300000 | V47: Per 60 Minions, Troop HP +900 | W47: 400
A48: 4 | B48: 15 | C48: 9400 | D48: 14000 | E48: 17500 | F48: Per 30 Minions, Troop HP +360 | G48: 200 | I48: 4 | J48: 36 | K48: 19000 | L48: 29000 | M48: 87500 | N48: Snail DEF +72 | O48: 300 | Q48: 4 | R48: 5 | S48: 52000 | T48: 75000 | U48: 350000 | V48: Per 60 Minions, Troop HP +1200 | W48: 500
A49: 5 | B49: 18 | C49: 10000 | D49: 16000 | E49: 20000 | F49: Per 30 Minions, Troop HP +450 | G49: 240 | I49: 5 | J49: 44 | K49: 22000 | L49: 34000 | M49: 100000 | N49: Snail DEF +100 | O49: 360 | Q49: 5 | R49: 6 | S49: 60000 | T49: 86000 | U49: 400000 | V49: Per 60 Minions, Troop HP +1500 | W49: 600
A50: 6 | B50: 21 | C50: 12000 | D50: 18000 | E50: 22500 | F50: Per 30 Minions, Troop HP +540 | G50: 280 | I50: 6 | J50: 52 | K50: 25000 | L50: 38000 | M50: 112500 | N50: Snail DEF +132 | O50: 420 | Q50: 6 | R50: 7 | S50: 67000 | T50: 97000 | U50: 450000 | V50: Per 60 Minions, Troop HP +1800 | W50: 700
A51: 7 | B51: 24 | C51: 13000 | D51: 20000 | E51: 25000 | F51: Per 30 Minions, Troop HP +630 | G51: 320 | I51: 7 | J51: 60 | K51: 28000 | L51: 42000 | M51: 125000 | N51: Snail DEF +168 | O51: 480 | Q51: 7 | R51: 8 | S51: 75000 | T51: 100000 | U51: 500000 | V51: Per 60 Minions, Troop HP +2100 | W51: 800
